Workbook
Name cfg_ConsNom: '[1]01 Configuration'!$B$72:$B$74
Name cfg_NivNom: '[1]01 Configuration'!$B$61:$B$66
Name cfg_TipoNom: '[1]01 Configuration'!$F$72:$F$74
Name lst_Dim: '[1]01 Configuration'!$AB$5:$AB$15
Name lst_Foco: '[1]01 Configuration'!$N$5:$N$7

Sheet INICIO - DASHBOARD
B2: #VALUE! | C2: EVALUACIÓN DE MADUREZ EN LA GESTIÓN DE FATIGA & SOMNOLENCIA - V01
B3: Guía de uso y acceso a las secciones de la herramienta / Dashboard resultados
B5: DATOS DE LA EVALUACIÓN
B6: Empresa
B7: Fecha de evaluación
B8: Realizado por
B9: Entrevistado
B11: OBJETIVO: | C11: Evaluar el nivel de madurez de la gestión de fatiga y somnolencia de la organización, identificando fortalezas, brechas y oportunidades de mejora en los procesos, controles y capacidades organizacionales, con el fin de priorizar acciones que reduzcan los riesgos para las personas, la seguridad operacional y la continuidad de las operaciones.
B13: METODOLOGÍA: | C13: La metodología utilizada es una evaluación cualitativa estructurada, basada en 12 dimensiones aplicando 128 preguntas de medición de cumplimiento (5 por componente) que entregan un nivel de porcentaje según una rúbrica de 5 niveles de madurez.
B15: RESULTADOS: | C15: Entrega una visión integral del estado de madurez de la gestión de fatiga y somnolencia, mostrando la posición de la organización respecto de las mejores prácticas y permitiendo priorizar iniciativas para fortalecer los controles, la cultura preventiva y la seguridad operacional.
B17: INSTRUCTIVO DE USO | M17: ESCALA CLASIFICACIÓN GENERAL NIVEL DE MADUREZ
B18: 1. Registre los antecedentes de la evaluación en los campos superiores.
B19: 2. Defina las dimensiones a aplicar | M19: Nivel 1 (0% - 39%) | N19: Inicial/Reactivo
B20: 3. Abra la hoja Preguntas y responda las 20 preguntas (5 por componente) seleccionando uno de los 5 criterios en la columna "Nivel de cumplimiento". Al inicio la celda indica "EVA" (EVALUAR). Al responder, se asigna un valor de 0%, 25%, 50%, 75% o 100% según el nivel de cumplimiento o gestión particular respecto a lo evaluado. | M20: Nivel 2 (40% - 59%) | N20: Dependiente
B21: 4. El DASHBOARD calcula automáticamente el cumplimiento de los cuatro componentes y el nivel global de BCM. | M21: Nivel 3 (60% - 79%) | N21: Independiente
B22: 5. Revise la hoja Escala: se resaltará el nivel alcanzado en cada componente con el color correspondiente. | M22: Nivel 4 (80% - 99%) | N22: Interdependiente
B23: 6. Utilice el DASHBOARD para identificar brechas, comparar componentes y definir prioridades del plan de cierre de brechas. | M23: Nivel 5 (100%) | N23: Predictivo
B24: 7. En Matriz Prioridades establezca las acciones a seguir considerando la factibilidad de las mismas.
B25: Nota: las preguntas sin respuesta se consideran pendientes y reducen el avance mostrado en el dashboard.
B27: CONTENIDO DEL LIBRO
B28: Instrucciones | C28: Registro inicial y guía de uso.
B29: Preguntas | C29: Cuestionario de 20 preguntas (5 por dimensiones) con evaluación de nivel de cumplimiento.
B30: Rúbrica de Evaluación | C30: Detalle de los criterios de evaluación por nivel de cumplimiento (0/25/50/75/100%).
B31: Escala | C31: Interpretación detallada de los cinco niveles de madurez, general y por componente.
B32: Listas Evaluación | C32: Listas de opciones de respuesta utilizadas en los desplegables del cuestionario.
Q33: SOPORTE GRÁFICO (cálculo automático - no editar)
B34: DASHBOARD DE MADUREZ EN GESTIÓN F&S | R34: 1 | S34: 2 | T34: 3 | U34: 4 | V34: 5
B35: COMPONENTE EVALUADO | D35: ¿APLICA? | E35: % | G35: CLASIFICACIÓN ESPECÍFICA POR COMPONENTE | J35: CUMPLIMIENTO GLOBAL | M35: RESPUESTAS REGISTRADAS | Q35: Dimensión | R35: =Escala!$I$21 -> Inicial / Reactivo | S35: =Escala!$I$22 -> Dependiente | T35: =Escala!$I$23 -> Independiente | U35: =Escala!$I$24 -> Interdependiente | V35: =Escala!$I$25 -> Predictivo | W35: % | X35: N° nivel | Y35: Nivel | Z35: Etiqueta
B36: D1. Gobernanza, organización y liderazgo | D36: Decidir | E36: =IF($D36="NO","No Aplica",IF(OR(COUNTIF(Preguntas!G5:G21,"EVA")>0,COUNTBLANK(Preguntas!G5:G21)>0),"EVA",AVERAGE(Preguntas!G5:G21))) -> EVA | G36: =IF(E36="No Aplica","No Aplica",IF(E36="EVA","POR EVALUAR",IF(E36<=39%,"Inicial / Reactivo",IF(E36<=59%,"Dependiente",IF(E36<=79%,"Independiente",IF(E36<=99%,"Interdependiente","Predictivo")))))) -> POR EVALUAR | J36: =IF(COUNTIF(E36:E47,"*eva*")>0,"EVALUAR",IF(COUNT(E36:E47)=0,"No Aplica",AVERAGE(E36:E47))) -> EVALUAR | M36: =(128-COUNTIF(Preguntas!$F$5:$F$132,"EVA"))&" / 128" -> 0 / 128 | Q36: =B36 -> D1. Gobernanza, organización y liderazgo | R36: =IF($X36=R$34,$W36,NA()) -> #N/A | S36: =IF($X36=S$34,$W36,NA()) -> #N/A | T36: =IF($X36=T$34,$W36,NA()) -> #N/A | U36: =IF($X36=U$34,$W36,NA()) -> #N/A | V36: =IF($X36=V$34,$W36,NA()) -> #N/A | W36: =E36 -> EVA | X36: =IF(ISNUMBER(W36),COUNTIF(Escala!$J$21:$J$24,"<"&W36)+1,"") | Y36: {=IF(X36="","",INDEX(Escala!$I$21:$I$25,X36))} | Z36: =IF(ISNUMBER(W36),TEXT(W36,"0%")&" | "&Y36,W36) -> EVA
B37: D.2 Gestión del riesgo de fatiga | D37: Decidir | E37: =IF($D37="NO","No Aplica",IF(OR(COUNTIF(Preguntas!G22:G32,"EVA")>0,COUNTBLANK(Preguntas!G22:G32)>0),"EVA",AVERAGE(Preguntas!G22:G32))) -> EVA | G37: =IF(E37="No Aplica","No Aplica",IF(E37="EVA","POR EVALUAR",IF(E37<=39%,"Inicial / Reactivo",IF(E37<=59%,"Dependiente",IF(E37<=79%,"Independiente",IF(E37<=99%,"Interdependiente","Predictivo")))))) -> POR EVALUAR | Q37: =B37 -> D.2 Gestión del riesgo de fatiga | R37: =IF($X37=R$34,$W37,NA()) -> #N/A | S37: =IF($X37=S$34,$W37,NA()) -> #N/A | T37: =IF($X37=T$34,$W37,NA()) -> #N/A | U37: =IF($X37=U$34,$W37,NA()) -> #N/A | V37: =IF($X37=V$34,$W37,NA()) -> #N/A | W37: =E37 -> EVA | X37: =IF(ISNUMBER(W37),COUNTIF(Escala!$J$21:$J$24,"<"&W37)+1,"") | Y37: {=IF(X37="","",INDEX(Escala!$I$21:$I$25,X37))} | Z37: =IF(ISNUMBER(W37),TEXT(W37,"0%")&" | "&Y37,W37) -> EVA
B38: D.3 Diseño de turnos y jornadas | D38: Decidir | E38: =IF($D38="NO","No Aplica",IF(OR(COUNTIF(Preguntas!G33:G43,"EVA")>0,COUNTBLANK(Preguntas!G33:G43)>0),"EVA",AVERAGE(Preguntas!G33:G43))) -> EVA | G38: =IF(E38="No Aplica","No Aplica",IF(E38="EVA","POR EVALUAR",IF(E38<=39%,"Inicial / Reactivo",IF(E38<=59%,"Dependiente",IF(E38<=79%,"Independiente",IF(E38<=99%,"Interdependiente","Predictivo")))))) -> POR EVALUAR | J38: DIMENSIONES APLICADAS | M38: NIVEL GENERAL | Q38: =B38 -> D.3 Diseño de turnos y jornadas | R38: =IF($X38=R$34,$W38,NA()) -> #N/A | S38: =IF($X38=S$34,$W38,NA()) -> #N/A | T38: =IF($X38=T$34,$W38,NA()) -> #N/A | U38: =IF($X38=U$34,$W38,NA()) -> #N/A | V38: =IF($X38=V$34,$W38,NA()) -> #N/A | W38: =E38 -> EVA | X38: =IF(ISNUMBER(W38),COUNTIF(Escala!$J$21:$J$24,"<"&W38)+1,"") | Y38: {=IF(X38="","",INDEX(Escala!$I$21:$I$25,X38))} | Z38: =IF(ISNUMBER(W38),TEXT(W38,"0%")&" | "&Y38,W38) -> EVA
B39: D.4 Gestión operacional de la fatiga | D39: Decidir | E39: =IF($D39="NO","No Aplica",IF(OR(COUNTIF(Preguntas!G44:G60,"EVA")>0,COUNTBLANK(Preguntas!G44:G60)>0),"EVA",AVERAGE(Preguntas!G44:G60))) -> EVA | G39: =IF(E39="No Aplica","No Aplica",IF(E39="EVA","POR EVALUAR",IF(E39<=39%,"Inicial / Reactivo",IF(E39<=59%,"Dependiente",IF(E39<=79%,"Independiente",IF(E39<=99%,"Interdependiente","Predictivo")))))) -> POR EVALUAR | J39: =(12-COUNTIF(D36:D47,"NO"))&" / 12" -> 12 / 12 | M39: =IF(COUNT($E$36:$E$47)<MIN(4,COUNTIF($D$36:$D$47,"<>NO")),"POR EVALUAR",IF(COUNT($E$36:$E$47)=0,"No Aplica",IF(AVERAGE($E$36:$E$47)<=39%,"Inicial / Reactivo",IF(AVERAGE($E$36:$E$47)<=59%,"Dependiente",IF(AVERAGE($E$36:$E$47)<=79%,"Independiente",IF(AVERAGE($E$36:$E$47)<=99%,"Interdependiente","Predictivo")))))) -> POR EVALUAR | Q39: =B39 -> D.4 Gestión operacional de la fatiga | R39: =IF($X39=R$34,$W39,NA()) -> #N/A | S39: =IF($X39=S$34,$W39,NA()) -> #N/A | T39: =IF($X39=T$34,$W39,NA()) -> #N/A | U39: =IF($X39=U$34,$W39,NA()) -> #N/A | V39: =IF($X39=V$34,$W39,NA()) -> #N/A | W39: =E39 -> EVA | X39: =IF(ISNUMBER(W39),COUNTIF(Escala!$J$21:$J$24,"<"&W39)+1,"") | Y39: {=IF(X39="","",INDEX(Escala!$I$21:$I$25,X39))} | Z39: =IF(ISNUMBER(W39),TEXT(W39,"0%")&" | "&Y39,W39) -> EVA
B40: D.5 Gestión de la somnolencia | D40: Decidir | E40: =IF($D40="NO","No Aplica",IF(OR(COUNTIF(Preguntas!G61:G72,"EVA")>0,COUNTBLANK(Preguntas!G61:G72)>0),"EVA",AVERAGE(Preguntas!G61:G72))) -> EVA | G40: =IF(E40="No Aplica","No Aplica",IF(E40="EVA","POR EVALUAR",IF(E40<=39%,"Inicial / Reactivo",IF(E40<=59%,"Dependiente",IF(E40<=79%,"Independiente",IF(E40<=99%,"Interdependiente","Predictivo")))))) -> POR EVALUAR | Q40: =B40 -> D.5 Gestión de la somnolencia | R40: =IF($X40=R$34,$W40,NA()) -> #N/A | S40: =IF($X40=S$34,$W40,NA()) -> #N/A | T40: =IF($X40=T$34,$W40,NA()) -> #N/A | U40: =IF($X40=U$34,$W40,NA()) -> #N/A | V40: =IF($X40=V$34,$W40,NA()) -> #N/A | W40: =E40 -> EVA | X40: =IF(ISNUMBER(W40),COUNTIF(Escala!$J$21:$J$24,"<"&W40)+1,"") | Y40: {=IF(X40="","",INDEX(Escala!$I$21:$I$25,X40))} | Z40: =IF(ISNUMBER(W40),TEXT(W40,"0%")&" | "&Y40,W40) -> EVA
B41: D.6 Salud ocupacional y trastornos del sueño | D41: Decidir | E41: =IF($D41="NO","No Aplica",IF(OR(COUNTIF(Preguntas!G73:G78,"EVA")>0,COUNTBLANK(Preguntas!G73:G78)>0),"EVA",AVERAGE(Preguntas!G73:G78))) -> EVA | G41: =IF(E41="No Aplica","No Aplica",IF(E41="EVA","POR EVALUAR",IF(E41<=39%,"Inicial / Reactivo",IF(E41<=59%,"Dependiente",IF(E41<=79%,"Independiente",IF(E41<=99%,"Interdependiente","Predictivo")))))) -> POR EVALUAR | J41: LECTURA RÁPIDA | Q41: =B41 -> D.6 Salud ocupacional y trastornos del sueño | R41: =IF($X41=R$34,$W41,NA()) -> #N/A | S41: =IF($X41=S$34,$W41,NA()) -> #N/A | T41: =IF($X41=T$34,$W41,NA()) -> #N/A | U41: =IF($X41=U$34,$W41,NA()) -> #N/A | V41: =IF($X41=V$34,$W41,NA()) -> #N/A | W41: =E41 -> EVA | X41: =IF(ISNUMBER(W41),COUNTIF(Escala!$J$21:$J$24,"<"&W41)+1,"") | Y41: {=IF(X41="","",INDEX(Escala!$I$21:$I$25,X41))} | Z41: =IF(ISNUMBER(W41),TEXT(W41,"0%")&" | "&Y41,W41) -> EVA
B42: D.7 Controles críticos | D42: Decidir | E42: =IF($D42="NO","No Aplica",IF(OR(COUNTIF(Preguntas!G79:G86,"EVA")>0,COUNTBLANK(Preguntas!G79:G86)>0),"EVA",AVERAGE(Preguntas!G79:G86))) -> EVA | G42: =IF(E42="No Aplica","No Aplica",IF(E42="EVA","POR EVALUAR",IF(E42<=39%,"Inicial / Reactivo",IF(E42<=59%,"Dependiente",IF(E42<=79%,"Independiente",IF(E42<=99%,"Interdependiente","Predictivo")))))) -> POR EVALUAR | J42: =IF((20-COUNTIF(Preguntas!$F$5:$F$119,"EVA"))<20,"Evaluación en curso: se han registrado "&(20-COUNTIF(Preguntas!$F$5:$F$119,"EVA"))&" de 20 respuestas. Complete las preguntas pendientes para consolidar el diagnóstico.","La evaluación presenta un cumplimiento global de "&TEXT(AVERAGE($E$36:$E$47),"0%")&". El componente más sólido es "&INDEX($B$36:$B$47,MATCH(MAX($E$36:$E$47),$E$36:$E$47,0))&" y la principal brecha está en "&INDEX($B$36:$B$47,MATCH(MIN($E$36:$E$47),$E$36:$E$47,0))&".") -> Evaluación en curso: se han registrado -95 de 20 respuestas. Complete las preguntas pendientes para consolidar el diagnóstico. | Q42: =B42 -> D.7 Controles críticos | R42: =IF($X42=R$34,$W42,NA()) -> #N/A | S42: =IF($X42=S$34,$W42,NA()) -> #N/A | T42: =IF($X42=T$34,$W42,NA()) -> #N/A | U42: =IF($X42=U$34,$W42,NA()) -> #N/A | V42: =IF($X42=V$34,$W42,NA()) -> #N/A | W42: =E42 -> EVA | X42: =IF(ISNUMBER(W42),COUNTIF(Escala!$J$21:$J$24,"<"&W42)+1,"") | Y42: {=IF(X42="","",INDEX(Escala!$I$21:$I$25,X42))} | Z42: =IF(ISNUMBER(W42),TEXT(W42,"0%")&" | "&Y42,W42) -> EVA
B43: D.8 Tecnología y sistemas de monitoreo | D43: Decidir | E43: =IF($D43="NO","No Aplica",IF(OR(COUNTIF(Preguntas!G87:G93,"EVA")>0,COUNTBLANK(Preguntas!G87:G93)>0),"EVA",AVERAGE(Preguntas!G87:G93))) -> EVA | G43: =IF(E43="No Aplica","No Aplica",IF(E43="EVA","POR EVALUAR",IF(E43<=39%,"Inicial / Reactivo",IF(E43<=59%,"Dependiente",IF(E43<=79%,"Independiente",IF(E43<=99%,"Interdependiente","Predictivo")))))) -> POR EVALUAR | Q43: =B43 -> D.8 Tecnología y sistemas de monitoreo | R43: =IF($X43=R$34,$W43,NA()) -> #N/A | S43: =IF($X43=S$34,$W43,NA()) -> #N/A | T43: =IF($X43=T$34,$W43,NA()) -> #N/A | U43: =IF($X43=U$34,$W43,NA()) -> #N/A | V43: =IF($X43=V$34,$W43,NA()) -> #N/A | W43: =E43 -> EVA | X43: =IF(ISNUMBER(W43),COUNTIF(Escala!$J$21:$J$24,"<"&W43)+1,"") | Y43: {=IF(X43="","",INDEX(Escala!$I$21:$I$25,X43))} | Z43: =IF(ISNUMBER(W43),TEXT(W43,"0%")&" | "&Y43,W43) -> EVA
B44: D.9 Factores humanos y organizacionales | D44: Decidir | E44: =IF($D44="NO","No Aplica",IF(OR(COUNTIF(Preguntas!G94:G98,"EVA")>0,COUNTBLANK(Preguntas!G94:G98)>0),"EVA",AVERAGE(Preguntas!G94:G98))) -> EVA | G44: =IF(E44="No Aplica","No Aplica",IF(E44="EVA","POR EVALUAR",IF(E44<=39%,"Inicial / Reactivo",IF(E44<=59%,"Dependiente",IF(E44<=79%,"Independiente",IF(E44<=99%,"Interdependiente","Predictivo")))))) -> POR EVALUAR | J44: PRIORIDAD GENERAL SUGERIDA | Q44: =B44 -> D.9 Factores humanos y organizacionales | R44: =IF($X44=R$34,$W44,NA()) -> #N/A | S44: =IF($X44=S$34,$W44,NA()) -> #N/A | T44: =IF($X44=T$34,$W44,NA()) -> #N/A | U44: =IF($X44=U$34,$W44,NA()) -> #N/A | V44: =IF($X44=V$34,$W44,NA()) -> #N/A | W44: =E44 -> EVA | X44: =IF(ISNUMBER(W44),COUNTIF(Escala!$J$21:$J$24,"<"&W44)+1,"") | Y44: {=IF(X44="","",INDEX(Escala!$I$21:$I$25,X44))} | Z44: =IF(ISNUMBER(W44),TEXT(W44,"0%")&" | "&Y44,W44) -> EVA
B45: D.10 Cultura de seguridad observable | D45: Decidir | E45: =IF($D45="NO","No Aplica",IF(OR(COUNTIF(Preguntas!G99:G111,"EVA")>0,COUNTBLANK(Preguntas!G99:G111)>0),"EVA",AVERAGE(Preguntas!G99:G111))) -> EVA | G45: =IF(E45="No Aplica","No Aplica",IF(E45="EVA","POR EVALUAR",IF(E45<=39%,"Inicial / Reactivo",IF(E45<=59%,"Dependiente",IF(E45<=79%,"Independiente",IF(E45<=99%,"Interdependiente","Predictivo")))))) -> POR EVALUAR | J45: =IF((20-COUNTIF(Preguntas!$F$5:$F$119,"EVA"))<20,"Finalice primero las respuestas pendientes; los resultados actuales son preliminares.",IF(MAX($E$36:$E$47)=MIN($E$36:$E$47),"Todos los componentes tienen el mismo resultado ("&TEXT(AVERAGE($E$36:$E$47),"0%")&").",INDEX($B$36:$B$47,MATCH(MIN($E$36:$E$47),$E$36:$E$47,0))&" registra el menor cumplimiento ("&TEXT(MIN($E$36:$E$47),"0%")&"). Priorice un plan de acción para este componente.")) -> Finalice primero las respuestas pendientes; los resultados actuales son preliminares. | Q45: =B45 -> D.10 Cultura de seguridad observable | R45: =IF($X45=R$34,$W45,NA()) -> #N/A | S45: =IF($X45=S$34,$W45,NA()) -> #N/A | T45: =IF($X45=T$34,$W45,NA()) -> #N/A | U45: =IF($X45=U$34,$W45,NA()) -> #N/A | V45: =IF($X45=V$34,$W45,NA()) -> #N/A | W45: =E45 -> EVA | X45: =IF(ISNUMBER(W45),COUNTIF(Escala!$J$21:$J$24,"<"&W45)+1,"") | Y45: {=IF(X45="","",INDEX(Escala!$I$21:$I$25,X45))} | Z45: =IF(ISNUMBER(W45),TEXT(W45,"0%")&" | "&Y45,W45) -> EVA
B46: D.11 Factores preventivos | D46: Decidir | E46: =IF($D46="NO","No Aplica",IF(OR(COUNTIF(Preguntas!G112:G119,"EVA")>0,COUNTBLANK(Preguntas!G112:G119)>0),"EVA",AVERAGE(Preguntas!G112:G119))) -> EVA | G46: =IF(E46="No Aplica","No Aplica",IF(E46="EVA","POR EVALUAR",IF(E46<=39%,"Inicial / Reactivo",IF(E46<=59%,"Dependiente",IF(E46<=79%,"Independiente",IF(E46<=99%,"Interdependiente","Predictivo")))))) -> POR EVALUAR | Q46: =B46 -> D.11 Factores preventivos | R46: =IF($X46=R$34,$W46,NA()) -> #N/A | S46: =IF($X46=S$34,$W46,NA()) -> #N/A | T46: =IF($X46=T$34,$W46,NA()) -> #N/A | U46: =IF($X46=U$34,$W46,NA()) -> #N/A | V46: =IF($X46=V$34,$W46,NA()) -> #N/A | W46: =E46 -> EVA | X46: =IF(ISNUMBER(W46),COUNTIF(Escala!$J$21:$J$24,"<"&W46)+1,"") | Y46: {=IF(X46="","",INDEX(Escala!$I$21:$I$25,X46))} | Z46: =IF(ISNUMBER(W46),TEXT(W46,"0%")&" | "&Y46,W46) -> EVA
B47: D.12 Factores correctivos | D47: Decidir | E47: =IF($D47="NO","No Aplica",IF(OR(COUNTIF(Preguntas!G120:G132,"EVA")>0,COUNTBLANK(Preguntas!G120:G132)>0),"EVA",AVERAGE(Preguntas!G120:G132))) -> EVA | G47: =IF(E47="No Aplica","No Aplica",IF(E47="EVA","POR EVALUAR",IF(E47<=39%,"Inicial / Reactivo",IF(E47<=59%,"Dependiente",IF(E47<=79%,"Independiente",IF(E47<=99%,"Interdependiente","Predictivo")))))) -> POR EVALUAR | Q47: =B47 -> D.12 Factores correctivos | R47: =IF($X47=R$34,$W47,NA()) -> #N/A | S47: =IF($X47=S$34,$W47,NA()) -> #N/A | T47: =IF($X47=T$34,$W47,NA()) -> #N/A | U47: =IF($X47=U$34,$W47,NA()) -> #N/A | V47: =IF($X47=V$34,$W47,NA()) -> #N/A | W47: =E47 -> EVA | X47: =IF(ISNUMBER(W47),COUNTIF(Escala!$J$21:$J$24,"<"&W47)+1,"") | Y47: {=IF(X47="","",INDEX(Escala!$I$21:$I$25,X47))} | Z47: =IF(ISNUMBER(W47),TEXT(W47,"0%")&" | "&Y47,W47) -> EVA
B49: DISTRIBUCIÓN DE PRIORIDADES DE ACCIÓN DESDE MATRIZ | D49: =COUNTIF('Matriz de Prioridades'!S5:T16,"PRIORIDAD 1")+COUNTIF('Matriz de Prioridades'!S5:T16,"PRIORIDAD 2")+COUNTIF('Matriz de Prioridades'!S5:T16,"PRIORIDAD 3")+COUNTIF('Matriz de Prioridades'!S5:T16,"PRIORIDAD 4") -> 12 | G49: =CONCATENATE('Matriz de Prioridades'!B41) -> PRIORIDAD 1 = 3 | H49: =CONCATENATE('Matriz de Prioridades'!B42) -> PRIORIDAD 2 = 0 | K49: =CONCATENATE('Matriz de Prioridades'!B43) -> PRIORIDAD 3 = 6 | N49: =CONCATENATE('Matriz de Prioridades'!B44) -> PRIORIDAD 4 = 2

Sheet Preguntas
B2: PREGUNTAS POR DIMENSIONES
B4: DIMENSIÓN | C4: PREGUNTAS | D4: Tipo de evidencia | E4: EVIDENCIA OBSERVADA/ENTREVISTA | F4: NIVEL DE CUMPLIMIENTO | G4: % LOGRADO
B5: D1. Gobernanza, organización y liderazgo | C5: ¿En qué medida están definidas las responsabilidades frente a los riesgos críticos (incluidas la fatiga y la somnolencia) para cada nivel: gerencia, superintendencia, supervisión, despacho, trabajadores y contratistas, incluida la autoridad para detener una tarea o retirar a una persona? | D5: Documental | F5: EVA | G5: =IF(F5="EVA","EVA",IFERROR((MATCH(F5,'Listas Evaluación'!A1:F1,0)-2)/4,"")) -> EVA
C6: ¿En qué medida las personas de distintos niveles describen correctamente qué les corresponde hacer frente a un riesgo crítico, por ejemplo ante un trabajador con signos de fatiga o somnolencia? | D6: Entrevista | F6: EVA | G6: =IF(F6="EVA","EVA",IFERROR((MATCH(F6,'Listas Evaluación'!A2:F2,0)-2)/4,"")) -> EVA
C7: ¿En qué medida el desempeño en seguridad de los responsables se revisa y tiene consecuencias en la práctica (reconocimiento, corrección, apoyo), y no solo el desempeño productivo? | D7: Registro | F7: EVA | G7: =IF(F7="EVA","EVA",IFERROR((MATCH(F7,'Listas Evaluación'!A3:F3,0)-2)/4,"")) -> EVA
C8: ¿En qué medida la alta dirección demuestra con acciones concretas su compromiso con la gestión de los riesgos críticos (presencia en terreno, asignación de recursos, participación en revisiones, decisiones que priorizan la seguridad)? | D8: Registro | F8: EVA | G8: =IF(F8="EVA","EVA",IFERROR((MATCH(F8,'Listas Evaluación'!A4:F4,0)-2)/4,"")) -> EVA
C9: ¿En qué medida supervisores y jefaturas realizan acciones concretas y visibles de seguridad durante el turno (conversaciones de riesgo, verificación de controles, detención de trabajos inseguros, atención a la fatiga del equipo), incluido el turno de noche? | D9: Observación en terreno | F9: EVA | G9: =IF(F9="EVA","EVA",IFERROR((MATCH(F9,'Listas Evaluación'!A5:F5,0)-2)/4,"")) -> EVA
C10: ¿En qué medida la organización tiene objetivos claros y verificables para sus riesgos críticos, incluidas la fatiga y la somnolencia, y la línea de mando los conoce? | D10: Documental | F10: EVA | G10: =IF(F10="EVA","EVA",IFERROR((MATCH(F10,'Listas Evaluación'!A6:F6,0)-2)/4,"")) -> EVA
C11: ¿En qué medida existen instancias o criterios para tomar decisiones operacionales (cambios de turno, extensiones de jornada, programación de tareas críticas, metas de producción) considerando explícitamente los riesgos críticos? | D11: Documental | F11: EVA | G11: =IF(F11="EVA","EVA",IFERROR((MATCH(F11,'Listas Evaluación'!A7:F7,0)-2)/4,"")) -> EVA
C12: ¿En qué medida la planificación diaria, semanal y de proyectos (por ejemplo, paradas de planta) incorpora en la práctica la dotación, los turnos y el control de la fatiga antes de comprometer metas o plazos? | D12: Registro | F12: EVA | G12: =IF(F12="EVA","EVA",IFERROR((MATCH(F12,'Listas Evaluación'!A8:F8,0)-2)/4,"")) -> EVA
C13: ¿En qué medida la dirección revisa periódicamente información sobre fatiga y riesgos críticos (exposición, alertas, eventos, desviaciones) y deja decisiones con responsable? | D13: Registro | F13: EVA | G13: =IF(F13="EVA","EVA",IFERROR((MATCH(F13,'Listas Evaluación'!A9:F9,0)-2)/4,"")) -> EVA
C14: ¿En qué medida las decisiones tomadas sobre riesgos críticos se implementaron y muestran efecto en los resultados asociados (por ejemplo, menos turnos fuera de límite)? | D14: Análisis de tendencia | F14: EVA | G14: =IF(F14="EVA","EVA",IFERROR((MATCH(F14,'Listas Evaluación'!A10:F10,0)-2)/4,"")) -> EVA
C15: ¿En qué medida los recursos necesarios para controlar la fatiga (relevos, tecnología, apoyo de salud) están disponibles en todos los turnos y no solo en el turno de día? | D15: Registro | F15: EVA | G15: =IF(F15="EVA","EVA",IFERROR((MATCH(F15,'Listas Evaluación'!A11:F11,0)-2)/4,"")) -> EVA
C16: ¿En qué medida la información sobre riesgos fluye en ambos sentidos entre la dirección, la supervisión y los trabajadores, y las preocupaciones planteadas reciben respuesta? | D16: Entrevista | F16: EVA | G16: =IF(F16="EVA","EVA",IFERROR((MATCH(F16,'Listas Evaluación'!A12:F12,0)-2)/4,"")) -> EVA
C17: ¿En qué medida los trabajadores tienen y usan formas reales de participar y plantear preocupaciones sobre los riesgos (comités, reuniones, canales directos, participación en el diseño de turnos o tareas)? | D17: Registro | F17: EVA | G17: =IF(F17="EVA","EVA",IFERROR((MATCH(F17,'Listas Evaluación'!A13:F13,0)-2)/4,"")) -> EVA
... C21: ¿En qué medida se verifica con datos (control de acceso, registros de turnos) que los contratistas cumplen los límites de jornada y descanso? | D21: Datos de sistema | F21: EVA | G21: =IF(F21="EVA","EVA",IFERROR((MATCH(F21,'Listas Evaluación'!A17:F17,0)-2)/4,"")) -> EVA
B22: D.2 Gestión del riesgo de fatiga | C22: ¿En qué medida la organización sabe qué tareas y cargos son sensibles a la fatiga o la somnolencia (equipos móviles, aislamiento, izaje, conducción, operación de planta) y cuántas personas están expuestas en cada turno? | D22: Documental | F22: EVA | G22: =IF(F22="EVA","EVA",IFERROR((MATCH(F22,'Listas Evaluación'!A18:F18,0)-2)/4,"")) -> EVA
C23: ¿En qué medida esa identificación se usa para decidir quién requiere evaluación antes del turno o monitoreo, y coincide con la dotación real? | D23: Datos de sistema | F23: EVA | G23: =IF(F23="EVA","EVA",IFERROR((MATCH(F23,'Listas Evaluación'!A19:F19,0)-2)/4,"")) -> EVA
C24: ¿En qué medida el análisis de riesgo distingue las causas de fatiga (carga, duración de la tarea, recuperación) de las causas de somnolencia (deuda de sueño, ventana circadiana, trastornos del sueño) e identifica las barreras críticas y sus responsables (por ejemplo, con un bow-tie)? | D24: Documental | F24: EVA | G24: =IF(F24="EVA","EVA",IFERROR((MATCH(F24,'Listas Evaluación'!A20:F20,0)-2)/4,"")) -> EVA
C25: ¿En qué medida el análisis de riesgo se revisó en terreno con operadores y supervisores en los últimos 12 meses y se actualiza después de incidentes o cambios? | D25: Registro | F25: EVA | G25: =IF(F25="EVA","EVA",IFERROR((MATCH(F25,'Listas Evaluación'!A21:F21,0)-2)/4,"")) -> EVA
C26: ¿En qué medida la estimación del riesgo que queda de fatiga se apoya en datos de exposición y de funcionamiento de los controles, y no solo en juicio experto, y muestra su evolución? | D26: Análisis de tendencia | F26: EVA | G26: =IF(F26="EVA","EVA",IFERROR((MATCH(F26,'Listas Evaluación'!A22:F22,0)-2)/4,"")) -> EVA
C27: ¿En qué medida los cambios de roster, dotación, flota, rutas o proyectos (por ejemplo, paradas de planta) se evalúan considerando su efecto en la fatiga y la somnolencia antes de aplicarlos? | D27: Documental | F27: EVA | G27: =IF(F27="EVA","EVA",IFERROR((MATCH(F27,'Listas Evaluación'!A23:F23,0)-2)/4,"")) -> EVA
C28: En los cambios relevantes de los últimos 12 meses (incluidas paradas de planta), ¿en qué medida se evaluó la fatiga antes de implementarlos? | D28: Registro | F28: EVA | G28: =IF(F28="EVA","EVA",IFERROR((MATCH(F28,'Listas Evaluación'!A24:F24,0)-2)/4,"")) -> EVA
C29: Durante paradas de planta, contingencias, ausentismo alto o emergencias, ¿en qué medida se mantienen los límites de jornada y los controles críticos, o se aplican excepciones autorizadas con controles compensatorios verificados? | D29: Datos de sistema | F29: EVA | G29: =IF(F29="EVA","EVA",IFERROR((MATCH(F29,'Listas Evaluación'!A25:F25,0)-2)/4,"")) -> EVA
C30: ¿En qué medida la forma de investigar incidentes exige considerar la fatiga y la somnolencia con datos objetivos (horas despierto, sueño en 24 y 48 h, hora del evento respecto a la ventana circadiana, duración del turno, alertas previas)? | D30: Documental | F30: EVA | G30: =IF(F30="EVA","EVA",IFERROR((MATCH(F30,'Listas Evaluación'!A26:F26,0)-2)/4,"")) -> EVA
C31: En las investigaciones de incidentes de alto potencial de los últimos 12 meses, ¿en qué medida se evaluó la fatiga con esos datos y se buscaron causas del sistema, no solo la conducta individual? | D31: Registro | F31: EVA | G31: =IF(F31="EVA","EVA",IFERROR((MATCH(F31,'Listas Evaluación'!A27:F27,0)-2)/4,"")) -> EVA
C32: ¿En qué medida las acciones derivadas de investigaciones con factor fatiga resultaron efectivas, sin repetición del mismo tipo de falla en los 6 meses siguientes? | D32: Análisis de tendencia | F32: EVA | G32: =IF(F32="EVA","EVA",IFERROR((MATCH(F32,'Listas Evaluación'!A28:F28,0)-2)/4,"")) -> EVA
B33: D.3 Diseño de turnos y jornadas | C33: ¿En qué medida los sistemas de turno se diseñan con criterios explícitos de fatiga (duración máxima, noches consecutivas, rotación, descanso entre ciclos, oportunidad de sueño) y con un método de evaluación declarado? | D33: Documental | F33: EVA | G33: =IF(F33="EVA","EVA",IFERROR((MATCH(F33,'Listas Evaluación'!A29:F29,0)-2)/4,"")) -> EVA
C34: ¿En qué medida los rosters programados en todas las áreas expuestas respetan esos criterios? | D34: Datos de sistema | F34: EVA | G34: =IF(F34="EVA","EVA",IFERROR((MATCH(F34,'Listas Evaluación'!A30:F30,0)-2)/4,"")) -> EVA
C35: ¿En qué medida los turnos realmente trabajados (control de acceso o asistencia) coinciden con los programados y respetan los límites, sin desviaciones repetidas? | D35: Datos de sistema | F35: EVA | G35: =IF(F35="EVA","EVA",IFERROR((MATCH(F35,'Listas Evaluación'!A31:F31,0)-2)/4,"")) -> EVA
C36: ¿En qué medida se analiza la relación entre el diseño del roster (noche 1 frente a noche 4, horas en ventana circadiana) y las alertas de somnolencia, y se ajusta el roster con efecto medido cuando aparecen patrones? | D36: Análisis de tendencia | F36: EVA | G36: =IF(F36="EVA","EVA",IFERROR((MATCH(F36,'Listas Evaluación'!A32:F32,0)-2)/4,"")) -> EVA
C37: ¿En qué medida los trabajadores expuestos participan en el diseño y la revisión de los sistemas de turno (consultas, comités, pilotos)? | D37: Registro | F37: EVA | G37: =IF(F37="EVA","EVA",IFERROR((MATCH(F37,'Listas Evaluación'!A33:F33,0)-2)/4,"")) -> EVA
C38: ¿En qué medida hay límites claros de horas extra, extensión de turno, llamados y horas máximas por período, con autorización escalonada y controles compensatorios? | D38: Documental | F38: EVA | G38: =IF(F38="EVA","EVA",IFERROR((MATCH(F38,'Listas Evaluación'!A34:F34,0)-2)/4,"")) -> EVA
C39: ¿En qué medida las extensiones de jornada sobre el límite se autorizan antes de ocurrir y se acompañan de controles compensatorios (evaluación de aptitud, restricción de tareas)? | D39: Registro | F39: EVA | G39: =IF(F39="EVA","EVA",IFERROR((MATCH(F39,'Listas Evaluación'!A35:F35,0)-2)/4,"")) -> EVA
C40: ¿En qué medida existe un seguimiento, idealmente automático, que avise a la supervisión cuando una persona se acerca o supera los límites de horas, con evidencia de que se actúa? | D40: Datos de sistema | F40: EVA | G40: =IF(F40="EVA","EVA",IFERROR((MATCH(F40,'Listas Evaluación'!A36:F36,0)-2)/4,"")) -> EVA
C41: ¿En qué medida se evaluó el riesgo del traslado después del turno (distancia, duración, conducción propia o bus, salida de turno de noche) y se definieron controles (transporte provisto, pausas, no conducir tras turno de noche)? | D41: Documental | F41: EVA | G41: =IF(F41="EVA","EVA",IFERROR((MATCH(F41,'Listas Evaluación'!A37:F37,0)-2)/4,"")) -> EVA
C42: ¿En qué medida los controles de traslado se aplican en la práctica (por ejemplo, % de trabajadores de turno de noche que usan el transporte provisto, conductores de bus evaluados)? | D42: Observación en terreno | F42: EVA | G42: =IF(F42="EVA","EVA",IFERROR((MATCH(F42,'Listas Evaluación'!A38:F38,0)-2)/4,"")) -> EVA
C43: ¿En qué medida se cumple en la programación real un descanso mínimo entre turnos, descontando traslado y alimentación? | D43: Datos de sistema | F43: EVA | G43: =IF(F43="EVA","EVA",IFERROR((MATCH(F43,'Listas Evaluación'!A39:F39,0)-2)/4,"")) -> EVA
B44: D.4 Gestión operacional de la fatiga | C44: ¿En qué medida la evaluación de aptitud antes del turno usa preguntas o mediciones objetivas (horas de sueño en 24 y 48 h, horas despierto, síntomas), umbrales de decisión y acciones definidas (apto, apto con restricción, no apto)? | D44: Documental | F44: EVA | G44: =IF(F44="EVA","EVA",IFERROR((MATCH(F44,'Listas Evaluación'!A40:F40,0)-2)/4,"")) -> EVA
C45: ¿En qué medida la evaluación antes del turno se aplica a todo el personal en tareas críticas, en todos los turnos (incluidas noches y fines de semana) y a contratistas? | D45: Registro | F45: EVA | G45: =IF(F45="EVA","EVA",IFERROR((MATCH(F45,'Listas Evaluación'!A41:F41,0)-2)/4,"")) -> EVA
C46: Cuando la evaluación antes del turno detecta riesgo, ¿en qué medida se aplica efectivamente la acción que corresponde (restricción, reasignación, no inicio)? | D46: Registro | F46: EVA | G46: =IF(F46="EVA","EVA",IFERROR((MATCH(F46,'Listas Evaluación'!A42:F42,0)-2)/4,"")) -> EVA
C47: ¿En qué medida un tercero (jefatura superior o área de seguridad) verifica periódicamente, observando directamente, la calidad de las evaluaciones antes del turno? | D47: Observación en terreno | F47: EVA | G47: =IF(F47="EVA","EVA",IFERROR((MATCH(F47,'Listas Evaluación'!A43:F43,0)-2)/4,"")) -> EVA
C48: ¿En qué medida se analiza si las personas identificadas en riesgo antes del turno concentran después más alertas o eventos, y se usa para ajustar los umbrales? | D48: Análisis de tendencia | F48: EVA | G48: =IF(F48="EVA","EVA",IFERROR((MATCH(F48,'Listas Evaluación'!A44:F44,0)-2)/4,"")) -> EVA
C49: Si la faena usa pupilometría u otra prueba objetiva de alerta, ¿en qué medida están claros su validez para el uso, el umbral y su papel como complemento (no reemplazo) del juicio del supervisor? | D49: Documental | F49: EVA | G49: =IF(F49="EVA","EVA",IFERROR((MATCH(F49,'Listas Evaluación'!A45:F45,0)-2)/4,"")) -> EVA
C50: ¿En qué medida los resultados fuera de umbral de la prueba objetiva generan una intervención registrada antes de iniciar la tarea? | D50: Datos de sistema | F50: EVA | G50: =IF(F50="EVA","EVA",IFERROR((MATCH(F50,'Listas Evaluación'!A46:F46,0)-2)/4,"")) -> EVA
C51: ¿En qué medida las personas pueden declarar "no estoy apto por fatiga" sin consecuencias punitivas, y efectivamente lo hacen en distintas áreas y turnos? | D51: Registro | F51: EVA | G51: =IF(F51="EVA","EVA",IFERROR((MATCH(F51,'Listas Evaluación'!A47:F47,0)-2)/4,"")) -> EVA
C52: ¿En qué medida los supervisores cuentan con una guía clara para reconocer signos de fatiga y somnolencia y saber qué hacer en cada caso? | D52: Documental | F52: EVA | G52: =IF(F52="EVA","EVA",IFERROR((MATCH(F52,'Listas Evaluación'!A48:F48,0)-2)/4,"")) -> EVA
C53: ¿En qué medida los supervisores conversan con su equipo sobre fatiga en terreno en horario crítico (02:00–06:00) y actúan cuando observan signos? | D53: Observación en terreno | F53: EVA | G53: =IF(F53="EVA","EVA",IFERROR((MATCH(F53,'Listas Evaluación'!A49:F49,0)-2)/4,"")) -> EVA
C54: ¿En qué medida la fatiga y la somnolencia se tratan en las charlas de inicio de turno con contenido específico (noche 1, retorno de descanso) y no solo como mención genérica? | D54: Observación en terreno | F54: EVA | G54: =IF(F54="EVA","EVA",IFERROR((MATCH(F54,'Listas Evaluación'!A50:F50,0)-2)/4,"")) -> EVA
C55: ¿En qué medida está previsto, por área y turno, quién reemplaza a una persona en una tarea crítica, incluido el turno de noche? | D55: Documental | F55: EVA | G55: =IF(F55="EVA","EVA",IFERROR((MATCH(F55,'Listas Evaluación'!A51:F51,0)-2)/4,"")) -> EVA
C56: Ante una persona evaluada como no apta durante el turno, ¿en qué medida se concreta el retiro de la tarea crítica dentro de un tiempo razonable y definido? | D56: Datos de sistema | F56: EVA | G56: =IF(F56="EVA","EVA",IFERROR((MATCH(F56,'Listas Evaluación'!A52:F52,0)-2)/4,"")) -> EVA
... C60: ¿En qué medida esas restricciones se respetan en la programación real y en los registros de despacho? | D60: Datos de sistema | F60: EVA | G60: =IF(F60="EVA","EVA",IFERROR((MATCH(F60,'Listas Evaluación'!A56:F56,0)-2)/4,"")) -> EVA
B61: D.5 Gestión de la somnolencia | C61: ¿En qué medida está definido, según el riesgo, qué equipos y tareas requieren detección de somnolencia en tiempo real? | D61: Documental | F61: EVA | G61: =IF(F61="EVA","EVA",IFERROR((MATCH(F61,'Listas Evaluación'!A57:F57,0)-2)/4,"")) -> EVA
C62: ¿En qué medida los equipos en alcance operan con el dispositivo de detección en uso y funcionando (L08)? | D62: Datos de sistema | F62: EVA | G62: =IF(F62="EVA","EVA",IFERROR((MATCH(F62,'Listas Evaluación'!A58:F58,0)-2)/4,"")) -> EVA
C63: ¿En qué medida las alertas llegan al centro de monitoreo o despacho y al supervisor en el tiempo esperado, sin pérdidas de comunicación relevantes? | D63: Datos de sistema | F63: EVA | G63: =IF(F63="EVA","EVA",IFERROR((MATCH(F63,'Listas Evaluación'!A59:F59,0)-2)/4,"")) -> EVA
C64: ¿En qué medida está definido, según el tipo y la gravedad de la alerta, quién responde, en qué tiempo y con qué acción (contacto, detención segura, evaluación, pausa, relevo, retiro)? | D64: Documental | F64: EVA | G64: =IF(F64="EVA","EVA",IFERROR((MATCH(F64,'Listas Evaluación'!A60:F60,0)-2)/4,"")) -> EVA
C65: ¿En qué medida las alertas de alto nivel se intervienen dentro del tiempo definido, considerando todas las alertas, incluida la noche (L02)? | D65: Datos de sistema | F65: EVA | G65: =IF(F65="EVA","EVA",IFERROR((MATCH(F65,'Listas Evaluación'!A61:F61,0)-2)/4,"")) -> EVA
C66: ¿En qué medida se verifica en una muestra de alertas que la intervención fue adecuada (la persona no siguió en la tarea crítica sin evaluación), y no solo que la alerta se "cerró" en el sistema? | D66: Muestreo o prueba | F66: EVA | G66: =IF(F66="EVA","EVA",IFERROR((MATCH(F66,'Listas Evaluación'!A62:F62,0)-2)/4,"")) -> EVA
C67: Tras una intervención, ¿en qué medida disminuye la repetición de alertas en la misma persona o turno, y la tasa de microsueños por 1.000 h baja (X05)? | D67: Análisis de tendencia | F67: EVA | G67: =IF(F67="EVA","EVA",IFERROR((MATCH(F67,'Listas Evaluación'!A63:F63,0)-2)/4,"")) -> EVA
C68: ¿En qué medida la respuesta se mantiene en períodos de alta carga (alertas simultáneas, cambios de turno, contingencias)? | D68: Datos de sistema | F68: EVA | G68: =IF(F68="EVA","EVA",IFERROR((MATCH(F68,'Listas Evaluación'!A64:F64,0)-2)/4,"")) -> EVA
C69: ¿En qué medida la tasa de alertas de somnolencia en la ventana circadiana baja disminuye tras las medidas aplicadas? | D69: Análisis de tendencia | F69: EVA | G69: =IF(F69="EVA","EVA",IFERROR((MATCH(F69,'Listas Evaluación'!A65:F65,0)-2)/4,"")) -> EVA
C70: ¿En qué medida se distingue en la práctica la respuesta ante somnolencia (riesgo inminente de microsueño: detención inmediata) de la respuesta ante fatiga (capacidad reducida: pausa, rotación de tarea)? | D70: Documental | F70: EVA | G70: =IF(F70="EVA","EVA",IFERROR((MATCH(F70,'Listas Evaluación'!A66:F66,0)-2)/4,"")) -> EVA
C71: ¿En qué medida las pausas y, cuando corresponda, las siestas estratégicas en turno tienen criterios claros (duración, momento, inercia del sueño, lugar)? | D71: Documental | F71: EVA | G71: =IF(F71="EVA","EVA",IFERROR((MATCH(F71,'Listas Evaluación'!A67:F67,0)-2)/4,"")) -> EVA
C72: ¿En qué medida las pausas y salas de recuperación se usan según lo previsto y están disponibles cerca de las áreas de trabajo? | D72: Observación en terreno | F72: EVA | G72: =IF(F72="EVA","EVA",IFERROR((MATCH(F72,'Listas Evaluación'!A68:F68,0)-2)/4,"")) -> EVA
B73: D.6 Salud ocupacional y trastornos del sueño | C73: ¿En qué medida se buscan trastornos del sueño en cargos críticos con un instrumento validado y criterios de derivación? | D73: Documental | F73: EVA | G73: =IF(F73="EVA","EVA",IFERROR((MATCH(F73,'Listas Evaluación'!A69:F69,0)-2)/4,"")) -> EVA
C74: ¿En qué medida los trabajadores de cargos críticos tienen esa evaluación vigente (L06)? | D74: Registro | F74: EVA | G74: =IF(F74="EVA","EVA",IFERROR((MATCH(F74,'Listas Evaluación'!A70:F70,0)-2)/4,"")) -> EVA
C75: ¿En qué medida los casos positivos se derivan, confirman y tratan, se determina su aptitud para tareas críticas y se sigue la adherencia al tratamiento (L07)? | D75: Registro | F75: EVA | G75: =IF(F75="EVA","EVA",IFERROR((MATCH(F75,'Listas Evaluación'!A71:F71,0)-2)/4,"")) -> EVA
C76: ¿En qué medida se observa una reducción de alertas de somnolencia en personas tratadas respecto de su situación anterior, en análisis agregado y anónimo? | D76: Análisis de tendencia | F76: EVA | G76: =IF(F76="EVA","EVA",IFERROR((MATCH(F76,'Listas Evaluación'!A72:F72,0)-2)/4,"")) -> EVA
C77: ¿En qué medida las personas pueden declarar en forma confidencial medicamentos o condiciones que afecten la vigilia, y se evalúa su aptitud para tareas críticas? | D77: Documental | F77: EVA | G77: =IF(F77="EVA","EVA",IFERROR((MATCH(F77,'Listas Evaluación'!A73:F73,0)-2)/4,"")) -> EVA
C78: ¿En qué medida los trabajadores conocen esa posibilidad y existen declaraciones registradas? | D78: Entrevista | F78: EVA | G78: =IF(F78="EVA","EVA",IFERROR((MATCH(F78,'Listas Evaluación'!A74:F74,0)-2)/4,"")) -> EVA
B79: D.7 Controles críticos | C79: ¿En qué medida está claro cuáles son los controles críticos de fatiga y somnolencia y, para cada uno, su objetivo, el desempeño esperado, cómo saber si funciona, su responsable y qué hacer si falla (hoja 05)? | D79: Documental | F79: EVA | G79: =IF(F79="EVA","EVA",IFERROR((MATCH(F79,'Listas Evaluación'!A75:F75,0)-2)/4,"")) -> EVA
C80: ¿En qué medida los responsables de los controles críticos conocen su rol y ejecutan lo que les corresponde (revisar verificaciones, decidir ante desviaciones)? | D80: Entrevista | F80: EVA | G80: =IF(F80="EVA","EVA",IFERROR((MATCH(F80,'Listas Evaluación'!A76:F76,0)-2)/4,"")) -> EVA
C81: ¿En qué medida los controles críticos se verifican con la frecuencia prevista (L04) e incluyen verificación en terreno, no solo documental? | D81: Registro | F81: EVA | G81: =IF(F81="EVA","EVA",IFERROR((MATCH(F81,'Listas Evaluación'!A77:F77,0)-2)/4,"")) -> EVA
C82: ¿En qué medida las verificaciones preguntan si el control funcionó y generan hallazgos cuando corresponde (tasa de verificaciones con hallazgo mayor que cero)? | D82: Registro | F82: EVA | G82: =IF(F82="EVA","EVA",IFERROR((MATCH(F82,'Listas Evaluación'!A78:F78,0)-2)/4,"")) -> EVA
C83: ¿En qué medida el desempeño de los controles críticos se analiza como tendencia y se relaciona con alertas e incidentes? | D83: Análisis de tendencia | F83: EVA | G83: =IF(F83="EVA","EVA",IFERROR((MATCH(F83,'Listas Evaluación'!A79:F79,0)-2)/4,"")) -> EVA
C84: Ante una desviación de un control crítico, ¿en qué medida se aplicó la acción inmediata que correspondía (detención, control compensatorio) en un tiempo razonable? | D84: Registro | F84: EVA | G84: =IF(F84="EVA","EVA",IFERROR((MATCH(F84,'Listas Evaluación'!A80:F80,0)-2)/4,"")) -> EVA
C85: ¿En qué medida las desviaciones de controles críticos cerradas no se repiten en el mismo control y área en los 6 meses siguientes (R04)? | D85: Análisis de tendencia | F85: EVA | G85: =IF(F85="EVA","EVA",IFERROR((MATCH(F85,'Listas Evaluación'!A81:F81,0)-2)/4,"")) -> EVA
C86: Cuando un control crítico no está disponible (falla de la tecnología, sin relevo), ¿en qué medida se aplican controles compensatorios previstos antes de continuar la operación? | D86: Registro | F86: EVA | G86: =IF(F86="EVA","EVA",IFERROR((MATCH(F86,'Listas Evaluación'!A82:F82,0)-2)/4,"")) -> EVA
B87: D.8 Tecnología y sistemas de monitoreo | C87: ¿En qué medida los sistemas de monitoreo de los equipos en alcance están disponibles (L08) y sus fallas se reparan en un plazo razonable? | D87: Datos de sistema | F87: EVA | G87: =IF(F87="EVA","EVA",IFERROR((MATCH(F87,'Listas Evaluación'!A83:F83,0)-2)/4,"")) -> EVA
C88: ¿En qué medida se prueba periódicamente la cadena completa (sensor, alerta en cabina, alerta en el centro de monitoreo, registro)? | D88: Muestreo o prueba | F88: EVA | G88: =IF(F88="EVA","EVA",IFERROR((MATCH(F88,'Listas Evaluación'!A84:F84,0)-2)/4,"")) -> EVA
C89: ¿En qué medida se detecta y gestiona la desconexión, manipulación u obstrucción del dispositivo? | D89: Datos de sistema | F89: EVA | G89: =IF(F89="EVA","EVA",IFERROR((MATCH(F89,'Listas Evaluación'!A85:F85,0)-2)/4,"")) -> EVA
C90: ¿En qué medida los datos de roster, asistencia, evaluación antes del turno, alertas y eventos pueden reunirse para analizarlos por turno, área y faena (y por persona en forma anónima)? | D90: Datos de sistema | F90: EVA | G90: =IF(F90="EVA","EVA",IFERROR((MATCH(F90,'Listas Evaluación'!A86:F86,0)-2)/4,"")) -> EVA
C91: ¿En qué medida el análisis de datos anticipa situaciones de riesgo (personas o turnos con alertas en aumento) y lleva a acciones preventivas documentadas? | D91: Análisis de tendencia | F91: EVA | G91: =IF(F91="EVA","EVA",IFERROR((MATCH(F91,'Listas Evaluación'!A87:F87,0)-2)/4,"")) -> EVA
C92: ¿En qué medida se mide la tasa de falsas alertas y se revisan eventos no detectados para ajustar el sistema? | D92: Análisis de tendencia | F92: EVA | G92: =IF(F92="EVA","EVA",IFERROR((MATCH(F92,'Listas Evaluación'!A88:F88,0)-2)/4,"")) -> EVA
C93: ¿En qué medida operadores y despachadores confían en las alertas y no las ignoran o silencian, según entrevistas y datos de alertas no reconocidas? | D93: Entrevista | F93: EVA | G93: =IF(F93="EVA","EVA",IFERROR((MATCH(F93,'Listas Evaluación'!A89:F89,0)-2)/4,"")) -> EVA
B94: D.9 Factores humanos y organizacionales | C94: ¿En qué medida se evalúa la carga mental y física y la monotonía de las tareas críticas (acarreo nocturno, sala de control)? | D94: Documental | F94: EVA | G94: =IF(F94="EVA","EVA",IFERROR((MATCH(F94,'Listas Evaluación'!A90:F90,0)-2)/4,"")) -> EVA
C95: ¿En qué medida se aplican medidas de diseño (rotación de tareas, variación de ciclos, automatización) en las tareas con mayor carga o monotonía? | D95: Observación en terreno | F95: EVA | G95: =IF(F95="EVA","EVA",IFERROR((MATCH(F95,'Listas Evaluación'!A91:F91,0)-2)/4,"")) -> EVA
C96: ¿En qué medida supervisores, despachadores y operadores saben gestionar la fatiga y la somnolencia, comprobado con una evaluación práctica y no solo con asistencia a cursos (L05)? | D96: Registro | F96: EVA | G96: =IF(F96="EVA","EVA",IFERROR((MATCH(F96,'Listas Evaluación'!A92:F92,0)-2)/4,"")) -> EVA
C97: En escenarios simulados o casos reales, ¿en qué medida los supervisores actúan correctamente ante una persona con fatiga o somnolencia (secuencia, tiempos, decisión de retiro)? | D97: Muestreo o prueba | F97: EVA | G97: =IF(F97="EVA","EVA",IFERROR((MATCH(F97,'Listas Evaluación'!A93:F93,0)-2)/4,"")) -> EVA
C98: ¿En qué medida la dotación de cargos críticos considera ausentismo, vacaciones y relevos, de modo que la operación no dependa en forma permanente de horas extra? | D98: Documental | F98: EVA | G98: =IF(F98="EVA","EVA",IFERROR((MATCH(F98,'Listas Evaluación'!A94:F94,0)-2)/4,"")) -> EVA
B99: D.10 Cultura de seguridad observable | C99: ¿En qué medida lo que se observa en terreno (uso de los controles, respeto de pausas y relevos, forma de actuar ante la fatiga) coincide con la forma de trabajo esperada, en distintos turnos y áreas? | D99: Observación en terreno | F99: EVA | G99: =IF(F99="EVA","EVA",IFERROR((MATCH(F99,'Listas Evaluación'!A95:F95,0)-2)/4,"")) -> EVA
C100: ¿En qué medida la fatiga, la somnolencia y otros riesgos críticos se conversan de forma específica en las reuniones de inicio de turno y en el trabajo diario, y no como una mención genérica? | D100: Observación en terreno | F100: EVA | G100: =IF(F100="EVA","EVA",IFERROR((MATCH(F100,'Listas Evaluación'!A96:F96,0)-2)/4,"")) -> EVA
C101: ¿En qué medida los trabajadores, en conversaciones abiertas, perciben que la organización gestiona en serio los riesgos críticos y la fatiga, y pueden dar ejemplos concretos que respalden esa percepción? | D101: Entrevista | F101: EVA | G101: =IF(F101="EVA","EVA",IFERROR((MATCH(F101,'Listas Evaluación'!A97:F97,0)-2)/4,"")) -> EVA
C102: ¿En qué medida lo que trabajadores y líderes dicen sobre la gestión de la seguridad coincide con los registros y con lo observado en terreno? | D102: Muestreo o prueba | F102: EVA | G102: =IF(F102="EVA","EVA",IFERROR((MATCH(F102,'Listas Evaluación'!A98:F98,0)-2)/4,"")) -> EVA
C103: Cuando hubo presión operacional, productiva o de plazos (relevo no disponible, metas de fin de mes, emergencias), ¿en qué medida las decisiones priorizaron la seguridad, deteniendo, reasignando o relevando a la persona? | D103: Registro | F103: EVA | G103: =IF(F103="EVA","EVA",IFERROR((MATCH(F103,'Listas Evaluación'!A99:F99,0)-2)/4,"")) -> EVA
C104: ¿En qué medida los datos muestran que los controles de fatiga se mantienen cuando aumenta la exigencia productiva, sin aumento de extensiones de jornada ni de alertas sin intervención? | D104: Análisis de tendencia | F104: EVA | G104: =IF(F104="EVA","EVA",IFERROR((MATCH(F104,'Listas Evaluación'!A100:F100,0)-2)/4,"")) -> EVA
C105: ¿En qué medida los trabajadores participan activamente en la identificación de riesgos y en la búsqueda de soluciones (proponen mejoras, participan en revisiones de turnos o tareas) y no solo reciben instrucciones? | D105: Registro | F105: EVA | G105: =IF(F105="EVA","EVA",IFERROR((MATCH(F105,'Listas Evaluación'!A101:F101,0)-2)/4,"")) -> EVA
C106: ¿En qué medida los trabajadores reciben a tiempo y entienden la información sobre los riesgos de su tarea (noche 1, retorno de descanso, condiciones anómalas) y pueden explicarla con sus palabras? | D106: Entrevista | F106: EVA | G106: =IF(F106="EVA","EVA",IFERROR((MATCH(F106,'Listas Evaluación'!A102:F102,0)-2)/4,"")) -> EVA
C107: ¿En qué medida las personas reportan fatiga, errores, cuasi-incidentes y alertas sin temor a sanciones, y los casos revisados confirman que reportar no tuvo consecuencias punitivas? | D107: Entrevista | F107: EVA | G107: =IF(F107="EVA","EVA",IFERROR((MATCH(F107,'Listas Evaluación'!A103:F103,0)-2)/4,"")) -> EVA
C108: ¿En qué medida los incidentes y desviaciones se analizan buscando causas del sistema (turnos, dotación, presión, diseño de la tarea) y no solo la culpa individual? | D108: Registro | F108: EVA | G108: =IF(F108="EVA","EVA",IFERROR((MATCH(F108,'Listas Evaluación'!A104:F104,0)-2)/4,"")) -> EVA
...

Sheet Rúbrica de Evaluación
B1: N° | C1: Dimensión | D1: Subdimensión | E1: Cód. sub | F1: Foco | G1: Punto de la cadena causal | H1: Riesgo | I1: Evento no deseado | J1: Control | K1: Propósito del control | L1: Criterio | M1: N° Preg. | N1: Pregunta | O1: Evidencia posible (ejemplos) | P1: Criterio 0% | Q1: Criterio 25% | R1: Criterio 50% | S1: Criterio 75% | T1: Criterio 100% | U1: Nivel de evaluación | V1: Tipo de evidencia | W1: Método de evaluación | X1: Consecuencia potencial | Y1: Tipo de control
B2: 1 | C2: D1. Gobernanza, organización y liderazgo | D2: Responsabilidades, roles y rendición de cuentas | E2: S01.1 | F2: Ambos | G2: Degradación de barreras | H2: Fatiga y/o somnolencia en persona expuesta a tarea crítica | I2: Persona fatigada o somnolienta permanece en tarea crítica sin ser detectada ni intervenida | J2: Responsabilidades frente a los riesgos críticos definidas, comprendidas y exigidas | K2: Que cada nivel sepa qué le corresponde frente a los riesgos críticos y responda por ello | L2: Responsabilidades de seguridad definidas por nivel | M2: 1 | N2: ¿En qué medida están definidas las responsabilidades frente a los riesgos críticos (incluidas la fatiga y la somnolencia) para cada nivel: gerencia, superintendencia, supervisión, despacho, trabajadores y contratistas, incluida la autoridad para detener una tarea o retirar a una persona? | O2: Ejemplos: descripciones de cargo, matrices de responsabilidades o instrucciones escritas; si no hay documentos, lo que declaran los responsables y lo que se observa | P2: El criterio «Responsabilidades de seguridad definidas por nivel» no está definido ni documentado; no existen criterios operativos, responsables ni evidencia aplicable. | Q2: El criterio «Responsabilidades de seguridad definidas por nivel» se aborda de manera informal o mediante documentos aislados, incompletos o desactualizados, sin alcance ni responsables claros. | R2: El criterio «Responsabilidades de seguridad definidas por nivel» está formalmente definido, pero cubre solo parte del alcance o presenta brechas relevantes de actualización, criterios, responsables o aprobación. | S2: El criterio «Responsabilidades de seguridad definidas por nivel» está definido, documentado, aprobado y vigente para la mayor parte del alcance; solo quedan brechas menores de cobertura o integración. | T2: El criterio «Responsabilidades de seguridad definidas por nivel» está completamente formalizado, aprobado, vigente e integrado a la gestión, con alcance, parámetros, responsables y revisión periódica verificables mediante revisión documental y entrevista. | U2: Design | V2: Documental | W2: Revisión documental y entrevista | X2: Grave | Y2: Administrativo
B3: 2 | D3: Responsabilidades, roles y rendición de cuentas | E3: S01.1 | F3: Ambos | G3: Degradación de barreras | H3: Fatiga y/o somnolencia en persona expuesta a tarea crítica | I3: Persona fatigada o somnolienta permanece en tarea crítica sin ser detectada ni intervenida | J3: Responsabilidades frente a los riesgos críticos definidas, comprendidas y exigidas | K3: Que cada nivel sepa qué le corresponde frente a los riesgos críticos y responda por ello | L3: Roles comprendidos en todos los niveles | M3: 2 | N3: ¿En qué medida las personas de distintos niveles describen correctamente qué les corresponde hacer frente a un riesgo crítico, por ejemplo ante un trabajador con signos de fatiga o somnolencia? | O3: Ejemplos: entrevistas breves a una muestra por nivel y turno (jefatura, supervisor, despachador, operador, contratista), comparando su respuesta con lo esperado | P3: El criterio «Roles comprendidos en todos los niveles» no se aplica en la práctica y no existe evidencia de implementación. | Q3: El criterio «Roles comprendidos en todos los niveles» se aplica solo en casos aislados o de manera informal, sin cobertura planificada ni consistencia entre áreas, turnos o personas expuestas. | R3: El criterio «Roles comprendidos en todos los niveles» está implementado parcialmente; alcanza parte de la población o del proceso, con brechas relevantes de cobertura, frecuencia o registro. | S3: El criterio «Roles comprendidos en todos los niveles» está implementado de forma regular en la mayor parte del alcance y con evidencia suficiente; persisten brechas menores de cobertura o consistencia. | T3: El criterio «Roles comprendidos en todos los niveles» está implementado sistemáticamente en todo el alcance aplicable, incluidos turnos y contratistas cuando corresponde, con registros completos y verificación mediante entrevista estructurada. | U3: Implementation | V3: Entrevista | W3: Entrevista estructurada | X3: Grave | Y3: Soporte
B4: 3 | D4: Responsabilidades, roles y rendición de cuentas | E4: S01.1 | F4: Ambos | G4: Degradación de barreras | H4: Fatiga y/o somnolencia en persona expuesta a tarea crítica | I4: Persona fatigada o somnolienta permanece en tarea crítica sin ser detectada ni intervenida | J4: Responsabilidades frente a los riesgos críticos definidas, comprendidas y exigidas | K4: Que cada nivel sepa qué le corresponde frente a los riesgos críticos y responda por ello | L4: Rendición de cuentas aplicada | M4: 3 | N4: ¿En qué medida el desempeño en seguridad de los responsables se revisa y tiene consecuencias en la práctica (reconocimiento, corrección, apoyo), y no solo el desempeño productivo? | O4: Ejemplos: evaluaciones de desempeño, revisiones de gestión, casos concretos en que se pidió cuenta por un incumplimiento o se reconoció una buena práctica | P4: El control asociado a «Rendición de cuentas aplicada» no opera en la práctica o, cuando se requiere, no genera la acción esperada. | Q4: El control asociado a «Rendición de cuentas aplicada» opera de forma esporádica y reactiva, depende de iniciativas individuales y carece de respuesta oportuna o registros consistentes. | R4: El control asociado a «Rendición de cuentas aplicada» funciona parcialmente o de manera irregular; genera algunas acciones, pero presenta brechas relevantes de oportunidad, calidad, seguimiento o trazabilidad. | S4: El control asociado a «Rendición de cuentas aplicada» funciona regularmente y genera la respuesta esperada en la mayoría de los casos; quedan desviaciones menores de oportunidad, cobertura o registro. | T4: El control asociado a «Rendición de cuentas aplicada» funciona de manera confiable, oportuna y consistente en todos los casos aplicables, con acciones trazables, seguimiento y evidencia verificable mediante reconstrucción de casos. | U4: Functioning | V4: Registro | W4: Reconstrucción de casos | X4: Grave | Y4: Administrativo
B5: 4 | D5: Compromiso visible de la dirección y de los líderes | E5: S01.2 | F5: Ambos | G5: Exposición | H5: Fatiga y/o somnolencia en persona expuesta a tarea crítica | I5: Persona fatigada o somnolienta permanece en tarea crítica sin ser detectada ni intervenida | J5: Liderazgo visible en seguridad | K5: Que la dirección y los líderes demuestren con acciones, no solo con declaraciones, que los riesgos críticos son prioridad | L5: Compromiso visible de la alta dirección | M5: 4 | N5: ¿En qué medida la alta dirección demuestra con acciones concretas su compromiso con la gestión de los riesgos críticos (presencia en terreno, asignación de recursos, participación en revisiones, decisiones que priorizan la seguridad)? | O5: Ejemplos: agenda de visitas a terreno, decisiones de recursos, actas o correos con decisiones; relato de trabajadores sobre la presencia de la dirección | P5: El criterio «Compromiso visible de la alta dirección» no se aplica en la práctica y no existe evidencia de implementación. | Q5: El criterio «Compromiso visible de la alta dirección» se aplica solo en casos aislados o de manera informal, sin cobertura planificada ni consistencia entre áreas, turnos o personas expuestas. | R5: El criterio «Compromiso visible de la alta dirección» está implementado parcialmente; alcanza parte de la población o del proceso, con brechas relevantes de cobertura, frecuencia o registro. | S5: El criterio «Compromiso visible de la alta dirección» está implementado de forma regular en la mayor parte del alcance y con evidencia suficiente; persisten brechas menores de cobertura o consistencia. | T5: El criterio «Compromiso visible de la alta dirección» está implementado sistemáticamente en todo el alcance aplicable, incluidos turnos y contratistas cuando corresponde, con registros completos y verificación mediante entrevista y muestreo de registros. | U5: Implementation | V5: Registro | W5: Entrevista y muestreo de registros | X5: Grave | Y5: Soporte
B6: 5 | D6: Compromiso visible de la dirección y de los líderes | E6: S01.2 | F6: Ambos | G6: Exposición | H6: Fatiga y/o somnolencia en persona expuesta a tarea crítica | I6: Persona fatigada o somnolienta permanece en tarea crítica sin ser detectada ni intervenida | J6: Liderazgo visible en seguridad | K6: Que la dirección y los líderes demuestren con acciones, no solo con declaraciones, que los riesgos críticos son prioridad | L6: Acciones visibles de los líderes en terreno | M6: 5 | N6: ¿En qué medida supervisores y jefaturas realizan acciones concretas y visibles de seguridad durante el turno (conversaciones de riesgo, verificación de controles, detención de trabajos inseguros, atención a la fatiga del equipo), incluido el turno de noche? | O6: Ejemplos: observación de al menos 2 turnos (día y noche), registros de interacciones, relato de trabajadores | P6: El control asociado a «Acciones visibles de los líderes en terreno» no opera en la práctica o, cuando se requiere, no genera la acción esperada. | Q6: El control asociado a «Acciones visibles de los líderes en terreno» opera de forma esporádica y reactiva, depende de iniciativas individuales y carece de respuesta oportuna o registros consistentes. | R6: El control asociado a «Acciones visibles de los líderes en terreno» funciona parcialmente o de manera irregular; genera algunas acciones, pero presenta brechas relevantes de oportunidad, calidad, seguimiento o trazabilidad. | S6: El control asociado a «Acciones visibles de los líderes en terreno» funciona regularmente y genera la respuesta esperada en la mayoría de los casos; quedan desviaciones menores de oportunidad, cobertura o registro. | T6: El control asociado a «Acciones visibles de los líderes en terreno» funciona de manera confiable, oportuna y consistente en todos los casos aplicables, con acciones trazables, seguimiento y evidencia verificable mediante observación en terreno. | U6: Functioning | V6: Observación en terreno | W6: Observación en terreno | X6: Grave | Y6: Soporte
B7: 6 | D7: Compromiso visible de la dirección y de los líderes | E7: S01.2 | F7: Ambos | G7: Exposición | H7: Fatiga y/o somnolencia en persona expuesta a tarea crítica | I7: Persona fatigada o somnolienta permanece en tarea crítica sin ser detectada ni intervenida | J7: Liderazgo visible en seguridad | K7: Que la dirección y los líderes demuestren con acciones, no solo con declaraciones, que los riesgos críticos son prioridad | L7: Objetivos claros que incluyen la fatiga | M7: 6 | N7: ¿En qué medida la organización tiene objetivos claros y verificables para sus riesgos críticos, incluidas la fatiga y la somnolencia, y la línea de mando los conoce? | O7: Ejemplos: objetivos o metas escritos, planes de área, conocimiento de los objetivos por parte de las jefaturas entrevistadas | P7: El criterio «Objetivos claros que incluyen la fatiga» no está definido ni documentado; no existen criterios operativos, responsables ni evidencia aplicable. | Q7: El criterio «Objetivos claros que incluyen la fatiga» se aborda de manera informal o mediante documentos aislados, incompletos o desactualizados, sin alcance ni responsables claros. | R7: El criterio «Objetivos claros que incluyen la fatiga» está formalmente definido, pero cubre solo parte del alcance o presenta brechas relevantes de actualización, criterios, responsables o aprobación. | S7: El criterio «Objetivos claros que incluyen la fatiga» está definido, documentado, aprobado y vigente para la mayor parte del alcance; solo quedan brechas menores de cobertura o integración. | T7: El criterio «Objetivos claros que incluyen la fatiga» está completamente formalizado, aprobado, vigente e integrado a la gestión, con alcance, parámetros, responsables y revisión periódica verificables mediante revisión documental y entrevista. | U7: Design | V7: Documental | W7: Revisión documental y entrevista | X7: Grave | Y7: Administrativo
B8: 7 | D8: Decisiones y planificación que consideran los riesgos críticos | E8: S01.3 | F8: Ambos | G8: Exposición | H8: Fatiga y/o somnolencia en persona expuesta a tarea crítica | I8: Pérdida de control de equipo móvil o vehículo (colisión, volcamiento, salida de vía) | J8: Riesgo crítico integrado en decisiones y planificación | K8: Que la fatiga y los demás riesgos críticos se consideren antes de decidir y planificar la operación | L8: Mecanismos para decidir considerando los riesgos críticos | M8: 7 | N8: ¿En qué medida existen instancias o criterios para tomar decisiones operacionales (cambios de turno, extensiones de jornada, programación de tareas críticas, metas de producción) considerando explícitamente los riesgos críticos? | O8: Ejemplos: reuniones de planificación con revisión de riesgos, criterios de autorización, listas de verificación de decisiones | P8: El criterio «Mecanismos para decidir considerando los riesgos críticos» no está definido ni documentado; no existen criterios operativos, responsables ni evidencia aplicable. | Q8: El criterio «Mecanismos para decidir considerando los riesgos críticos» se aborda de manera informal o mediante documentos aislados, incompletos o desactualizados, sin alcance ni responsables claros. | R8: El criterio «Mecanismos para decidir considerando los riesgos críticos» está formalmente definido, pero cubre solo parte del alcance o presenta brechas relevantes de actualización, criterios, responsables o aprobación. | S8: El criterio «Mecanismos para decidir considerando los riesgos críticos» está definido, documentado, aprobado y vigente para la mayor parte del alcance; solo quedan brechas menores de cobertura o integración. | T8: El criterio «Mecanismos para decidir considerando los riesgos críticos» está completamente formalizado, aprobado, vigente e integrado a la gestión, con alcance, parámetros, responsables y revisión periódica verificables mediante revisión documental y entrevista. | U8: Design | V8: Documental | W8: Revisión documental y entrevista | X8: Grave | Y8: Administrativo
B9: 8 | D9: Decisiones y planificación que consideran los riesgos críticos | E9: S01.3 | F9: Ambos | G9: Exposición | H9: Fatiga y/o somnolencia en persona expuesta a tarea crítica | I9: Pérdida de control de equipo móvil o vehículo (colisión, volcamiento, salida de vía) | J9: Riesgo crítico integrado en decisiones y planificación | K9: Que la fatiga y los demás riesgos críticos se consideren antes de decidir y planificar la operación | L9: Seguridad integrada en la planificación real | M9: 8 | N9: ¿En qué medida la planificación diaria, semanal y de proyectos (por ejemplo, paradas de planta) incorpora en la práctica la dotación, los turnos y el control de la fatiga antes de comprometer metas o plazos? | O9: Ejemplos: muestra de planes y programas recientes comparados con la dotación y los turnos reales; entrevistas a planificadores y jefes de turno | P9: El control asociado a «Seguridad integrada en la planificación real» no opera en la práctica o, cuando se requiere, no genera la acción esperada. | Q9: El control asociado a «Seguridad integrada en la planificación real» opera de forma esporádica y reactiva, depende de iniciativas individuales y carece de respuesta oportuna o registros consistentes. | R9: El control asociado a «Seguridad integrada en la planificación real» funciona parcialmente o de manera irregular; genera algunas acciones, pero presenta brechas relevantes de oportunidad, calidad, seguimiento o trazabilidad. | S9: El control asociado a «Seguridad integrada en la planificación real» funciona regularmente y genera la respuesta esperada en la mayoría de los casos; quedan desviaciones menores de oportunidad, cobertura o registro. | T9: El control asociado a «Seguridad integrada en la planificación real» funciona de manera confiable, oportuna y consistente en todos los casos aplicables, con acciones trazables, seguimiento y evidencia verificable mediante reconstrucción de casos. | U9: Functioning | V9: Registro | W9: Reconstrucción de casos | X9: Fatal | Y9: Soporte
B10: 9 | D10: Decisiones y planificación que consideran los riesgos críticos | E10: S01.3 | F10: Ambos | G10: Exposición | H10: Fatiga y/o somnolencia en persona expuesta a tarea crítica | I10: Pérdida de control de equipo móvil o vehículo (colisión, volcamiento, salida de vía) | J10: Riesgo crítico integrado en decisiones y planificación | K10: Que la fatiga y los demás riesgos críticos se consideren antes de decidir y planificar la operación | L10: Revisión periódica de la dirección con datos | M10: 9 | N10: ¿En qué medida la dirección revisa periódicamente información sobre fatiga y riesgos críticos (exposición, alertas, eventos, desviaciones) y deja decisiones con responsable? | O10: Ejemplos: actas, presentaciones o correos de revisión con datos, decisiones y seguimiento | P10: No se verifica el criterio «Revisión periódica de la dirección con datos» y no existe evidencia de revisión del control o de sus resultados. | Q10: El criterio «Revisión periódica de la dirección con datos» se verifica solo de manera ocasional o informal, sin método, frecuencia, muestra ni seguimiento definidos. | R10: El criterio «Revisión periódica de la dirección con datos» cuenta con verificaciones periódicas pero parciales, con cobertura o profundidad insuficiente y seguimiento inconsistente de los hallazgos. | S10: El criterio «Revisión periódica de la dirección con datos» se verifica sistemáticamente en la mayor parte del alcance, con hallazgos registrados y acciones de seguimiento; quedan brechas menores. | T10: El criterio «Revisión periódica de la dirección con datos» se verifica de forma sistemática, independiente y basada en riesgo en todo el alcance, mediante revisión documental y muestreo, con cierre comprobado de hallazgos y retroalimentación al sistema. | U10: Verification | V10: Registro | W10: Revisión documental y muestreo | X10: Grave | Y10: Administrativo
B11: 10 | D11: Decisiones y planificación que consideran los riesgos críticos | E11: S01.3 | F11: Ambos | G11: Exposición | H11: Fatiga y/o somnolencia en persona expuesta a tarea crítica | I11: Pérdida de control de equipo móvil o vehículo (colisión, volcamiento, salida de vía) | J11: Riesgo crítico integrado en decisiones y planificación | K11: Que la fatiga y los demás riesgos críticos se consideren antes de decidir y planificar la operación | L11: Decisiones de la dirección con efecto medible | M11: 10 | N11: ¿En qué medida las decisiones tomadas sobre riesgos críticos se implementaron y muestran efecto en los resultados asociados (por ejemplo, menos turnos fuera de límite)? | O11: Ejemplos: comparación de datos antes y después de cada decisión, al menos 3 períodos | P11: El criterio «Decisiones de la dirección con efecto medible» no muestra resultados medibles o no se evalúa su efecto sobre el riesgo y el desempeño. | Q11: El criterio «Decisiones de la dirección con efecto medible» presenta resultados anecdóticos o aislados, sin línea base, indicadores comparables ni evidencia de mejora atribuible. | R11: El criterio «Decisiones de la dirección con efecto medible» dispone de algunos indicadores o comparaciones, pero los resultados son parciales, inestables o insuficientes para demostrar efectividad sostenida. | S11: El criterio «Decisiones de la dirección con efecto medible» muestra una mejora medible y mayormente sostenida en los resultados; persisten brechas menores o variaciones que requieren seguimiento. | T11: El criterio «Decisiones de la dirección con efecto medible» demuestra efectividad sostenida con datos comparables de al menos tres períodos, tendencia favorable y ausencia o reducción comprobada de recurrencias, verificada mediante análisis de datos. | U11: Effectiveness | V11: Análisis de tendencia | W11: Análisis de datos | X11: Grave | Y11: Administrativo
B12: 11 | D12: Decisiones y planificación que consideran los riesgos críticos | E12: S01.3 | F12: Ambos | G12: Exposición | H12: Fatiga y/o somnolencia en persona expuesta a tarea crítica | I12: Pérdida de control de equipo móvil o vehículo (colisión, volcamiento, salida de vía) | J12: Riesgo crítico integrado en decisiones y planificación | K12: Que la fatiga y los demás riesgos críticos se consideren antes de decidir y planificar la operación | L12: Recursos para los controles disponibles en cada turno | M12: 11 | N12: ¿En qué medida los recursos necesarios para controlar la fatiga (relevos, tecnología, apoyo de salud) están disponibles en todos los turnos y no solo en el turno de día? | O12: Ejemplos: dotación de relevos por turno comparada con la necesaria; disponibilidad real de equipos y apoyo | P12: El control asociado a «Recursos para los controles disponibles en cada turno» no opera en la práctica o, cuando se requiere, no genera la acción esperada. | Q12: El control asociado a «Recursos para los controles disponibles en cada turno» opera de forma esporádica y reactiva, depende de iniciativas individuales y carece de respuesta oportuna o registros consistentes. | R12: El control asociado a «Recursos para los controles disponibles en cada turno» funciona parcialmente o de manera irregular; genera algunas acciones, pero presenta brechas relevantes de oportunidad, calidad, seguimiento o trazabilidad. | S12: El control asociado a «Recursos para los controles disponibles en cada turno» funciona regularmente y genera la respuesta esperada en la mayoría de los casos; quedan desviaciones menores de oportunidad, cobertura o registro. | T12: El control asociado a «Recursos para los controles disponibles en cada turno» funciona de manera confiable, oportuna y consistente en todos los casos aplicables, con acciones trazables, seguimiento y evidencia verificable mediante análisis de datos. | U12: Functioning | V12: Registro | W12: Análisis de datos | X12: Grave | Y12: Administrativo
B13: 12 | D13: Comunicación entre niveles y participación de los trabajadores | E13: S01.4 | F13: Ambos | G13: Deterioro del desempeño humano | H13: Fatiga y/o somnolencia en persona expuesta a tarea crítica | I13: Persona fatigada o somnolienta permanece en tarea crítica sin ser detectada ni intervenida | J13: Canales de comunicación y participación | K13: Que la información de riesgo fluya en ambos sentidos y los trabajadores puedan plantear preocupaciones | L13: Comunicación efectiva entre niveles | M13: 12 | N13: ¿En qué medida la información sobre riesgos fluye en ambos sentidos entre la dirección, la supervisión y los trabajadores, y las preocupaciones planteadas reciben respuesta? | O13: Ejemplos: casos de preocupaciones planteadas y su respuesta; reuniones de turno observadas; relato de trabajadores y supervisores | P13: El control asociado a «Comunicación efectiva entre niveles» no opera en la práctica o, cuando se requiere, no genera la acción esperada. | Q13: El control asociado a «Comunicación efectiva entre niveles» opera de forma esporádica y reactiva, depende de iniciativas individuales y carece de respuesta oportuna o registros consistentes. | R13: El control asociado a «Comunicación efectiva entre niveles» funciona parcialmente o de manera irregular; genera algunas acciones, pero presenta brechas relevantes de oportunidad, calidad, seguimiento o trazabilidad. | S13: El control asociado a «Comunicación efectiva entre niveles» funciona regularmente y genera la respuesta esperada en la mayoría de los casos; quedan desviaciones menores de oportunidad, cobertura o registro. | T13: El control asociado a «Comunicación efectiva entre niveles» funciona de manera confiable, oportuna y consistente en todos los casos aplicables, con acciones trazables, seguimiento y evidencia verificable mediante entrevista y reconstrucción de casos. | U13: Functioning | V13: Entrevista | W13: Entrevista y reconstrucción de casos | X13: Grave | Y13: Soporte
B14: 13 | D14: Comunicación entre niveles y participación de los trabajadores | E14: S01.4 | F14: Ambos | G14: Deterioro del desempeño humano | H14: Fatiga y/o somnolencia en persona expuesta a tarea crítica | I14: Persona fatigada o somnolienta permanece en tarea crítica sin ser detectada ni intervenida | J14: Canales de comunicación y participación | K14: Que la información de riesgo fluya en ambos sentidos y los trabajadores puedan plantear preocupaciones | L14: Mecanismos de participación de los trabajadores | M14: 13 | N14: ¿En qué medida los trabajadores tienen y usan formas reales de participar y plantear preocupaciones sobre los riesgos (comités, reuniones, canales directos, participación en el diseño de turnos o tareas)? | O14: Ejemplos: actas o registros de participación; ejemplos concretos de cambios propuestos por trabajadores | P14: El criterio «Mecanismos de participación de los trabajadores» no se aplica en la práctica y no existe evidencia de implementación. | Q14: El criterio «Mecanismos de participación de los trabajadores» se aplica solo en casos aislados o de manera informal, sin cobertura planificada ni consistencia entre áreas, turnos o personas expuestas. | R14: El criterio «Mecanismos de participación de los trabajadores» está implementado parcialmente; alcanza parte de la población o del proceso, con brechas relevantes de cobertura, frecuencia o registro. | S14: El criterio «Mecanismos de participación de los trabajadores» está implementado de forma regular en la mayor parte del alcance y con evidencia suficiente; persisten brechas menores de cobertura o consistencia. | T14: El criterio «Mecanismos de participación de los trabajadores» está implementado sistemáticamente en todo el alcance aplicable, incluidos turnos y contratistas cuando corresponde, con registros completos y verificación mediante entrevista y muestreo de registros. | U14: Implementation | V14: Registro | W14: Entrevista y muestreo de registros | X14: Grave | Y14: Soporte
... B18: 17 | D18: Gestión de la fatiga en empresas contratistas | E18: S01.6 | F18: Ambos | G18: Exposición | H18: Fatiga y/o somnolencia en persona expuesta a tarea crítica | I18: Pérdida de control de equipo móvil o vehículo (colisión, volcamiento, salida de vía) | J18: Requisitos de fatiga para contratistas | K18: Extender los controles a toda persona expuesta, independiente del empleador | L18: Jornadas de contratistas verificadas con datos | M18: 17 | N18: ¿En qué medida se verifica con datos (control de acceso, registros de turnos) que los contratistas cumplen los límites de jornada y descanso? | O18: Ejemplos: cruce de control de acceso con los límites, por empresa, últimos 3 meses | P18: No se verifica el criterio «Jornadas de contratistas verificadas con datos» y no existe evidencia de revisión del control o de sus resultados. | Q18: El criterio «Jornadas de contratistas verificadas con datos» se verifica solo de manera ocasional o informal, sin método, frecuencia, muestra ni seguimiento definidos. | R18: El criterio «Jornadas de contratistas verificadas con datos» cuenta con verificaciones periódicas pero parciales, con cobertura o profundidad insuficiente y seguimiento inconsistente de los hallazgos. | S18: El criterio «Jornadas de contratistas verificadas con datos» se verifica sistemáticamente en la mayor parte del alcance, con hallazgos registrados y acciones de seguimiento; quedan brechas menores. | T18: El criterio «Jornadas de contratistas verificadas con datos» se verifica de forma sistemática, independiente y basada en riesgo en todo el alcance, mediante análisis de datos, con cierre comprobado de hallazgos y retroalimentación al sistema. | U18: Verification | V18: Datos de sistema | W18: Análisis de datos | X18: Fatal | Y18: Soporte
B19: 18 | C19: D.2 Gestión del riesgo de fatiga | D19: Tareas críticas y población expuesta | E19: S02.1 | F19: Ambos | G19: Exposición | H19: Fatiga y/o somnolencia en persona expuesta a tarea crítica | I19: Pérdida de control de equipo móvil o vehículo (colisión, volcamiento, salida de vía) | J19: Inventario de tareas críticas sensibles a fatiga | K19: Saber quién está expuesto, dónde y cuándo | L19: Tareas críticas y población expuesta identificadas | M19: 1 | N19: ¿En qué medida la organización sabe qué tareas y cargos son sensibles a la fatiga o la somnolencia (equipos móviles, aislamiento, izaje, conducción, operación de planta) y cuántas personas están expuestas en cada turno? | O19: Ejemplos: listado de tareas o cargos críticos con dotación por turno; si no existe, lo que pueden indicar las jefaturas | P19: El criterio «Tareas críticas y población expuesta identificadas» no está definido ni documentado; no existen criterios operativos, responsables ni evidencia aplicable. | Q19: El criterio «Tareas críticas y población expuesta identificadas» se aborda de manera informal o mediante documentos aislados, incompletos o desactualizados, sin alcance ni responsables claros. | R19: El criterio «Tareas críticas y población expuesta identificadas» está formalmente definido, pero cubre solo parte del alcance o presenta brechas relevantes de actualización, criterios, responsables o aprobación. | S19: El criterio «Tareas críticas y población expuesta identificadas» está definido, documentado, aprobado y vigente para la mayor parte del alcance; solo quedan brechas menores de cobertura o integración. | T19: El criterio «Tareas críticas y población expuesta identificadas» está completamente formalizado, aprobado, vigente e integrado a la gestión, con alcance, parámetros, responsables y revisión periódica verificables mediante revisión documental y entrevista. | U19: Design | V19: Documental | W19: Revisión documental y entrevista | X19: Fatal | Y19: Soporte
B20: 19 | D20: Tareas críticas y población expuesta | E20: S02.1 | F20: Ambos | G20: Exposición | H20: Fatiga y/o somnolencia en persona expuesta a tarea crítica | I20: Pérdida de control de equipo móvil o vehículo (colisión, volcamiento, salida de vía) | J20: Inventario de tareas críticas sensibles a fatiga | K20: Saber quién está expuesto, dónde y cuándo | L20: Identificación usada para asignar controles | M20: 2 | N20: ¿En qué medida esa identificación se usa para decidir quién requiere evaluación antes del turno o monitoreo, y coincide con la dotación real? | O20: Ejemplos: cruce entre el listado de cargos críticos, la nómina y los turnos; diferencias encontradas | P20: El criterio «Identificación usada para asignar controles» no se aplica en la práctica y no existe evidencia de implementación. | Q20: El criterio «Identificación usada para asignar controles» se aplica solo en casos aislados o de manera informal, sin cobertura planificada ni consistencia entre áreas, turnos o personas expuestas. | R20: El criterio «Identificación usada para asignar controles» está implementado parcialmente; alcanza parte de la población o del proceso, con brechas relevantes de cobertura, frecuencia o registro. | S20: El criterio «Identificación usada para asignar controles» está implementado de forma regular en la mayor parte del alcance y con evidencia suficiente; persisten brechas menores de cobertura o consistencia. | T20: El criterio «Identificación usada para asignar controles» está implementado sistemáticamente en todo el alcance aplicable, incluidos turnos y contratistas cuando corresponde, con registros completos y verificación mediante muestreo de registros. | U20: Implementation | V20: Datos de sistema | W20: Muestreo de registros | X20: Fatal | Y20: Soporte
B21: 20 | D21: Evaluación de riesgos y bow-tie | E21: S02.2 | F21: Ambos | G21: Fatiga o somnolencia | H21: Fatiga y/o somnolencia en persona expuesta a tarea crítica | I21: Pérdida de control de equipo móvil o vehículo (colisión, volcamiento, salida de vía) | J21: Bow-tie de fatiga y somnolencia | K21: Identificar causas, consecuencias y barreras diferenciando fatiga de somnolencia | L21: Análisis de riesgo que diferencia fatiga y somnolencia | M21: 3 | N21: ¿En qué medida el análisis de riesgo distingue las causas de fatiga (carga, duración de la tarea, recuperación) de las causas de somnolencia (deuda de sueño, ventana circadiana, trastornos del sueño) e identifica las barreras críticas y sus responsables (por ejemplo, con un bow-tie)? | O21: Ejemplos: análisis de riesgo, bow-tie o matriz de riesgos con barreras y responsables | P21: El criterio «Análisis de riesgo que diferencia fatiga y somnolencia» no está definido ni documentado; no existen criterios operativos, responsables ni evidencia aplicable. | Q21: El criterio «Análisis de riesgo que diferencia fatiga y somnolencia» se aborda de manera informal o mediante documentos aislados, incompletos o desactualizados, sin alcance ni responsables claros. | R21: El criterio «Análisis de riesgo que diferencia fatiga y somnolencia» está formalmente definido, pero cubre solo parte del alcance o presenta brechas relevantes de actualización, criterios, responsables o aprobación. | S21: El criterio «Análisis de riesgo que diferencia fatiga y somnolencia» está definido, documentado, aprobado y vigente para la mayor parte del alcance; solo quedan brechas menores de cobertura o integración. | T21: El criterio «Análisis de riesgo que diferencia fatiga y somnolencia» está completamente formalizado, aprobado, vigente e integrado a la gestión, con alcance, parámetros, responsables y revisión periódica verificables mediante revisión documental. | U21: Design | V21: Documental | W21: Revisión documental | X21: Fatal | Y21: Crítico
B22: 21 | D22: Evaluación de riesgos y bow-tie | E22: S02.2 | F22: Ambos | G22: Fatiga o somnolencia | H22: Fatiga y/o somnolencia en persona expuesta a tarea crítica | I22: Pérdida de control de equipo móvil o vehículo (colisión, volcamiento, salida de vía) | J22: Bow-tie de fatiga y somnolencia | K22: Identificar causas, consecuencias y barreras diferenciando fatiga de somnolencia | L22: Análisis de riesgo validado en terreno y actualizado | M22: 4 | N22: ¿En qué medida el análisis de riesgo se revisó en terreno con operadores y supervisores en los últimos 12 meses y se actualiza después de incidentes o cambios? | O22: Ejemplos: registro de la revisión con participantes; versión actualizada | P22: No se verifica el criterio «Análisis de riesgo validado en terreno y actualizado» y no existe evidencia de revisión del control o de sus resultados. | Q22: El criterio «Análisis de riesgo validado en terreno y actualizado» se verifica solo de manera ocasional o informal, sin método, frecuencia, muestra ni seguimiento definidos. | R22: El criterio «Análisis de riesgo validado en terreno y actualizado» cuenta con verificaciones periódicas pero parciales, con cobertura o profundidad insuficiente y seguimiento inconsistente de los hallazgos. | S22: El criterio «Análisis de riesgo validado en terreno y actualizado» se verifica sistemáticamente en la mayor parte del alcance, con hallazgos registrados y acciones de seguimiento; quedan brechas menores. | T22: El criterio «Análisis de riesgo validado en terreno y actualizado» se verifica de forma sistemática, independiente y basada en riesgo en todo el alcance, mediante revisión documental y entrevista, con cierre comprobado de hallazgos y retroalimentación al sistema. | U22: Verification | V22: Registro | W22: Revisión documental y entrevista | X22: Fatal | Y22: Crítico
B23: 22 | D23: Evaluación de riesgos y bow-tie | E23: S02.2 | F23: Ambos | G23: Fatiga o somnolencia | H23: Fatiga y/o somnolencia en persona expuesta a tarea crítica | I23: Pérdida de control de equipo móvil o vehículo (colisión, volcamiento, salida de vía) | J23: Bow-tie de fatiga y somnolencia | K23: Identificar causas, consecuencias y barreras diferenciando fatiga de somnolencia | L23: Riesgo residual sustentado en datos | M23: 5 | N23: ¿En qué medida la estimación del riesgo que queda de fatiga se apoya en datos de exposición y de funcionamiento de los controles, y no solo en juicio experto, y muestra su evolución? | O23: Ejemplos: evaluación con datos de exposición, alertas e incidentes; serie de al menos 3 períodos | P23: El criterio «Riesgo residual sustentado en datos» no muestra resultados medibles o no se evalúa su efecto sobre el riesgo y el desempeño. | Q23: El criterio «Riesgo residual sustentado en datos» presenta resultados anecdóticos o aislados, sin línea base, indicadores comparables ni evidencia de mejora atribuible. | R23: El criterio «Riesgo residual sustentado en datos» dispone de algunos indicadores o comparaciones, pero los resultados son parciales, inestables o insuficientes para demostrar efectividad sostenida. | S23: El criterio «Riesgo residual sustentado en datos» muestra una mejora medible y mayormente sostenida en los resultados; persisten brechas menores o variaciones que requieren seguimiento. | T23: El criterio «Riesgo residual sustentado en datos» demuestra efectividad sostenida con datos comparables de al menos tres períodos, tendencia favorable y ausencia o reducción comprobada de recurrencias, verificada mediante análisis de datos. | U23: Effectiveness | V23: Análisis de tendencia | W23: Análisis de datos | X23: Fatal | Y23: Crítico
B24: 23 | D24: Gestión del cambio y condiciones anómalas | E24: S02.3 | F24: Fatiga | G24: Exposición | H24: Fatiga (disminución de capacidad física o mental) en persona expuesta a tarea crítica | I24: Pérdida de control de equipo móvil o vehículo (colisión, volcamiento, salida de vía) | J24: Evaluación de impacto en fatiga ante cambios | K24: Evitar que cambios de roster, dotación, flota o procesos aumenten la exposición sin control | L24: Cambios evaluados considerando la fatiga | M24: 6 | N24: ¿En qué medida los cambios de roster, dotación, flota, rutas o proyectos (por ejemplo, paradas de planta) se evalúan considerando su efecto en la fatiga y la somnolencia antes de aplicarlos? | O24: Ejemplos: criterio o lista de verificación de gestión del cambio que incluya la fatiga | P24: El criterio «Cambios evaluados considerando la fatiga» no está definido ni documentado; no existen criterios operativos, responsables ni evidencia aplicable. | Q24: El criterio «Cambios evaluados considerando la fatiga» se aborda de manera informal o mediante documentos aislados, incompletos o desactualizados, sin alcance ni responsables claros. | R24: El criterio «Cambios evaluados considerando la fatiga» está formalmente definido, pero cubre solo parte del alcance o presenta brechas relevantes de actualización, criterios, responsables o aprobación. | S24: El criterio «Cambios evaluados considerando la fatiga» está definido, documentado, aprobado y vigente para la mayor parte del alcance; solo quedan brechas menores de cobertura o integración. | T24: El criterio «Cambios evaluados considerando la fatiga» está completamente formalizado, aprobado, vigente e integrado a la gestión, con alcance, parámetros, responsables y revisión periódica verificables mediante revisión documental. | U24: Design | V24: Documental | W24: Revisión documental | X24: Grave | Y24: Administrativo
B25: 24 | D25: Gestión del cambio y condiciones anómalas | E25: S02.3 | F25: Fatiga | G25: Exposición | H25: Fatiga (disminución de capacidad física o mental) en persona expuesta a tarea crítica | I25: Pérdida de control de equipo móvil o vehículo (colisión, volcamiento, salida de vía) | J25: Evaluación de impacto en fatiga ante cambios | K25: Evitar que cambios de roster, dotación, flota o procesos aumenten la exposición sin control | L25: Evaluación de fatiga aplicada a cambios reales | M25: 7 | N25: En los cambios relevantes de los últimos 12 meses (incluidas paradas de planta), ¿en qué medida se evaluó la fatiga antes de implementarlos? | O25: Ejemplos: muestra de al menos 3 cambios o paradas con su evaluación | P25: El criterio «Evaluación de fatiga aplicada a cambios reales» no se aplica en la práctica y no existe evidencia de implementación. | Q25: El criterio «Evaluación de fatiga aplicada a cambios reales» se aplica solo en casos aislados o de manera informal, sin cobertura planificada ni consistencia entre áreas, turnos o personas expuestas. | R25: El criterio «Evaluación de fatiga aplicada a cambios reales» está implementado parcialmente; alcanza parte de la población o del proceso, con brechas relevantes de cobertura, frecuencia o registro. | S25: El criterio «Evaluación de fatiga aplicada a cambios reales» está implementado de forma regular en la mayor parte del alcance y con evidencia suficiente; persisten brechas menores de cobertura o consistencia. | T25: El criterio «Evaluación de fatiga aplicada a cambios reales» está implementado sistemáticamente en todo el alcance aplicable, incluidos turnos y contratistas cuando corresponde, con registros completos y verificación mediante muestreo de registros. | U25: Implementation | V25: Registro | W25: Muestreo de registros | X25: Grave | Y25: Soporte
B26: 25 | D26: Gestión del cambio y condiciones anómalas | E26: S02.3 | F26: Ambos | G26: Exposición | H26: Fatiga y/o somnolencia en persona expuesta a tarea crítica | I26: Pérdida de control de equipo móvil o vehículo (colisión, volcamiento, salida de vía) | J26: Evaluación de impacto en fatiga ante cambios | K26: Evitar que cambios de roster, dotación, flota o procesos aumenten la exposición sin control | L26: Controles que se mantienen en condiciones anómalas | M26: 8 | N26: Durante paradas de planta, contingencias, ausentismo alto o emergencias, ¿en qué medida se mantienen los límites de jornada y los controles críticos, o se aplican excepciones autorizadas con controles compensatorios verificados? | O26: Ejemplos: datos de jornada y alertas en eventos anómalos comparados con la operación normal; excepciones autorizadas | P26: El control asociado a «Controles que se mantienen en condiciones anómalas» deja de operar ante contingencias, dotación reducida, emergencias u otras condiciones anómalas. | Q26: El control asociado a «Controles que se mantienen en condiciones anómalas» se mantiene solo mediante respuestas improvisadas, sin criterios de excepción, autorización ni controles compensatorios definidos. | R26: El control asociado a «Controles que se mantienen en condiciones anómalas» se mantiene parcialmente en condiciones anómalas, pero presenta brechas relevantes de recursos, cobertura, autorización o verificación de controles compensatorios. | S26: El control asociado a «Controles que se mantienen en condiciones anómalas» se mantiene en la mayoría de las condiciones anómalas, con excepciones autorizadas y controles compensatorios; quedan brechas menores de consistencia. | T26: El control asociado a «Controles que se mantienen en condiciones anómalas» se mantiene plenamente efectivo en condiciones normales y anómalas, con recursos disponibles, excepciones controladas, pruebas periódicas y evidencia verificable mediante análisis de datos. | U26: Resilience | V26: Datos de sistema | W26: Análisis de datos | X26: Fatal | Y26: Soporte
B27: 26 | D27: Investigación de incidentes con factor fatiga | E27: S02.4 | F27: Ambos | G27: Evento de alto potencial | H27: Fatiga y/o somnolencia en persona expuesta a tarea crítica | I27: Pérdida de control de equipo móvil o vehículo (colisión, volcamiento, salida de vía) | J27: Investigación estructurada de fatiga | K27: Detectar la fatiga o somnolencia como factor contribuyente y aprender | L27: Investigación con variables objetivas de fatiga | M27: 9 | N27: ¿En qué medida la forma de investigar incidentes exige considerar la fatiga y la somnolencia con datos objetivos (horas despierto, sueño en 24 y 48 h, hora del evento respecto a la ventana circadiana, duración del turno, alertas previas)? | O27: Ejemplos: procedimiento o formulario de investigación con campos de fatiga | P27: El criterio «Investigación con variables objetivas de fatiga» no está definido ni documentado; no existen criterios operativos, responsables ni evidencia aplicable. | Q27: El criterio «Investigación con variables objetivas de fatiga» se aborda de manera informal o mediante documentos aislados, incompletos o desactualizados, sin alcance ni responsables claros. | R27: El criterio «Investigación con variables objetivas de fatiga» está formalmente definido, pero cubre solo parte del alcance o presenta brechas relevantes de actualización, criterios, responsables o aprobación. | S27: El criterio «Investigación con variables objetivas de fatiga» está definido, documentado, aprobado y vigente para la mayor parte del alcance; solo quedan brechas menores de cobertura o integración. | T27: El criterio «Investigación con variables objetivas de fatiga» está completamente formalizado, aprobado, vigente e integrado a la gestión, con alcance, parámetros, responsables y revisión periódica verificables mediante revisión documental. | U27: Design | V27: Documental | W27: Revisión documental | X27: Grave | Y27: Administrativo
B28: 27 | D28: Investigación de incidentes con factor fatiga | E28: S02.4 | F28: Ambos | G28: Evento de alto potencial | H28: Fatiga y/o somnolencia en persona expuesta a tarea crítica | I28: Pérdida de control de equipo móvil o vehículo (colisión, volcamiento, salida de vía) | J28: Investigación estructurada de fatiga | K28: Detectar la fatiga o somnolencia como factor contribuyente y aprender | L28: Fatiga evaluada en investigaciones reales | M28: 10 | N28: En las investigaciones de incidentes de alto potencial de los últimos 12 meses, ¿en qué medida se evaluó la fatiga con esos datos y se buscaron causas del sistema, no solo la conducta individual? | O28: Ejemplos: muestra de al menos 5 investigaciones, o todas si son menos | P28: El control asociado a «Fatiga evaluada en investigaciones reales» no opera en la práctica o, cuando se requiere, no genera la acción esperada. | Q28: El control asociado a «Fatiga evaluada en investigaciones reales» opera de forma esporádica y reactiva, depende de iniciativas individuales y carece de respuesta oportuna o registros consistentes. | R28: El control asociado a «Fatiga evaluada en investigaciones reales» funciona parcialmente o de manera irregular; genera algunas acciones, pero presenta brechas relevantes de oportunidad, calidad, seguimiento o trazabilidad. | S28: El control asociado a «Fatiga evaluada en investigaciones reales» funciona regularmente y genera la respuesta esperada en la mayoría de los casos; quedan desviaciones menores de oportunidad, cobertura o registro. | T28: El control asociado a «Fatiga evaluada en investigaciones reales» funciona de manera confiable, oportuna y consistente en todos los casos aplicables, con acciones trazables, seguimiento y evidencia verificable mediante muestreo de registros. | U28: Functioning | V28: Registro | W28: Muestreo de registros | X28: Fatal | Y28: Soporte
B29: 28 | D29: Investigación de incidentes con factor fatiga | E29: S02.4 | F29: Ambos | G29: Evento de alto potencial | H29: Fatiga y/o somnolencia en persona expuesta a tarea crítica | I29: Pérdida de control de equipo móvil o vehículo (colisión, volcamiento, salida de vía) | J29: Investigación estructurada de fatiga | K29: Detectar la fatiga o somnolencia como factor contribuyente y aprender | L29: Acciones de investigaciones sin recurrencia | M29: 11 | N29: ¿En qué medida las acciones derivadas de investigaciones con factor fatiga resultaron efectivas, sin repetición del mismo tipo de falla en los 6 meses siguientes? | O29: Ejemplos: seguimiento de acciones con verificación de efectividad; análisis de repetición | P29: El criterio «Acciones de investigaciones sin recurrencia» no muestra resultados medibles o no se evalúa su efecto sobre el riesgo y el desempeño. | Q29: El criterio «Acciones de investigaciones sin recurrencia» presenta resultados anecdóticos o aislados, sin línea base, indicadores comparables ni evidencia de mejora atribuible. | R29: El criterio «Acciones de investigaciones sin recurrencia» dispone de algunos indicadores o comparaciones, pero los resultados son parciales, inestables o insuficientes para demostrar efectividad sostenida. | S29: El criterio «Acciones de investigaciones sin recurrencia» muestra una mejora medible y mayormente sostenida en los resultados; persisten brechas menores o variaciones que requieren seguimiento. | T29: El criterio «Acciones de investigaciones sin recurrencia» demuestra efectividad sostenida con datos comparables de al menos tres períodos, tendencia favorable y ausencia o reducción comprobada de recurrencias, verificada mediante análisis de datos. | U29: Effectiveness | V29: Análisis de tendencia | W29: Análisis de datos | X29: Fatal | Y29: Soporte
B30: 29 | C30: D.3 Diseño de turnos y jornadas | D30: Diseño de rosters basado en fatiga | E30: S03.1 | F30: Fatiga | G30: Exposición | H30: Fatiga (disminución de capacidad física o mental) en persona expuesta a tarea crítica | I30: Pérdida de control de equipo móvil o vehículo (colisión, volcamiento, salida de vía) | J30: Diseño de sistemas de turno con criterios de fatiga | K30: Limitar la exposición por duración, secuencia de noches y oportunidad de sueño | L30: Criterios de fatiga en el diseño de turnos | M30: 1 | N30: ¿En qué medida los sistemas de turno se diseñan con criterios explícitos de fatiga (duración máxima, noches consecutivas, rotación, descanso entre ciclos, oportunidad de sueño) y con un método de evaluación declarado? | O30: Ejemplos: criterios de diseño de turnos; evaluación del roster con el método usado | P30: El criterio «Criterios de fatiga en el diseño de turnos» no está definido ni documentado; no existen criterios operativos, responsables ni evidencia aplicable. | Q30: El criterio «Criterios de fatiga en el diseño de turnos» se aborda de manera informal o mediante documentos aislados, incompletos o desactualizados, sin alcance ni responsables claros. | R30: El criterio «Criterios de fatiga en el diseño de turnos» está formalmente definido, pero cubre solo parte del alcance o presenta brechas relevantes de actualización, criterios, responsables o aprobación. | S30: El criterio «Criterios de fatiga en el diseño de turnos» está definido, documentado, aprobado y vigente para la mayor parte del alcance; solo quedan brechas menores de cobertura o integración. | T30: El criterio «Criterios de fatiga en el diseño de turnos» está completamente formalizado, aprobado, vigente e integrado a la gestión, con alcance, parámetros, responsables y revisión periódica verificables mediante revisión documental. | U30: Design | V30: Documental | W30: Revisión documental | X30: Fatal | Y30: Crítico
B31: 30 | D31: Diseño de rosters basado en fatiga | E31: S03.1 | F31: Fatiga | G31: Exposición | H31: Fatiga (disminución de capacidad física o mental) en persona expuesta a tarea crítica | I31: Pérdida de control de equipo móvil o vehículo (colisión, volcamiento, salida de vía) | J31: Diseño de sistemas de turno con criterios de fatiga | K31: Limitar la exposición por duración, secuencia de noches y oportunidad de sueño | L31: Rosters programados dentro de criterios | M31: 2 | N31: ¿En qué medida los rosters programados en todas las áreas expuestas respetan esos criterios? | O31: Ejemplos: rosters de las áreas expuestas comparados con los criterios; % de conformidad | P31: El criterio «Rosters programados dentro de criterios» no se aplica en la práctica y no existe evidencia de implementación. | Q31: El criterio «Rosters programados dentro de criterios» se aplica solo en casos aislados o de manera informal, sin cobertura planificada ni consistencia entre áreas, turnos o personas expuestas. | R31: El criterio «Rosters programados dentro de criterios» está implementado parcialmente; alcanza parte de la población o del proceso, con brechas relevantes de cobertura, frecuencia o registro. | S31: El criterio «Rosters programados dentro de criterios» está implementado de forma regular en la mayor parte del alcance y con evidencia suficiente; persisten brechas menores de cobertura o consistencia. | T31: El criterio «Rosters programados dentro de criterios» está implementado sistemáticamente en todo el alcance aplicable, incluidos turnos y contratistas cuando corresponde, con registros completos y verificación mediante análisis de datos. | U31: Implementation | V31: Datos de sistema | W31: Análisis de datos | X31: Fatal | Y31: Crítico
B32: 31 | D32: Diseño de rosters basado en fatiga | E32: S03.1 | F32: Fatiga | G32: Exposición | H32: Fatiga (disminución de capacidad física o mental) en persona expuesta a tarea crítica | I32: Pérdida de control de equipo móvil o vehículo (colisión, volcamiento, salida de vía) | J32: Diseño de sistemas de turno con criterios de fatiga | K32: Limitar la exposición por duración, secuencia de noches y oportunidad de sueño | L32: Turnos trabajados dentro de límites | M32: 3 | N32: ¿En qué medida los turnos realmente trabajados (control de acceso o asistencia) coinciden con los programados y respetan los límites, sin desviaciones repetidas? | O32: Ejemplos: cruce de asistencia con la programación de los últimos 3 meses; % de turnos fuera de límite (X01) | P32: El control asociado a «Turnos trabajados dentro de límites» no opera en la práctica o, cuando se requiere, no genera la acción esperada. | Q32: El control asociado a «Turnos trabajados dentro de límites» opera de forma esporádica y reactiva, depende de iniciativas individuales y carece de respuesta oportuna o registros consistentes. | R32: El control asociado a «Turnos trabajados dentro de límites» funciona parcialmente o de manera irregular; genera algunas acciones, pero presenta brechas relevantes de oportunidad, calidad, seguimiento o trazabilidad. | S32: El control asociado a «Turnos trabajados dentro de límites» funciona regularmente y genera la respuesta esperada en la mayoría de los casos; quedan desviaciones menores de oportunidad, cobertura o registro. | T32: El control asociado a «Turnos trabajados dentro de límites» funciona de manera confiable, oportuna y consistente en todos los casos aplicables, con acciones trazables, seguimiento y evidencia verificable mediante análisis de datos. | U32: Functioning | V32: Datos de sistema | W32: Análisis de datos | X32: Fatal | Y32: Crítico
B33: 32 | D33: Diseño de rosters basado en fatiga | E33: S03.1 | F33: Somnolencia | G33: Exposición | H33: Somnolencia o microsueño en persona que opera equipo o ejecuta tarea crítica | I33: Pérdida de control de equipo móvil o vehículo (colisión, volcamiento, salida de vía) | J33: Diseño de sistemas de turno con criterios de fatiga | K33: Limitar la exposición por duración, secuencia de noches y oportunidad de sueño | L33: Roster ajustado según patrones de somnolencia | M33: 4 | N33: ¿En qué medida se analiza la relación entre el diseño del roster (noche 1 frente a noche 4, horas en ventana circadiana) y las alertas de somnolencia, y se ajusta el roster con efecto medido cuando aparecen patrones? | O33: Ejemplos: análisis de alertas por día de ciclo y hora; ajustes realizados y su efecto | P33: El criterio «Roster ajustado según patrones de somnolencia» no muestra resultados medibles o no se evalúa su efecto sobre el riesgo y el desempeño. | Q33: El criterio «Roster ajustado según patrones de somnolencia» presenta resultados anecdóticos o aislados, sin línea base, indicadores comparables ni evidencia de mejora atribuible. | R33: El criterio «Roster ajustado según patrones de somnolencia» dispone de algunos indicadores o comparaciones, pero los resultados son parciales, inestables o insuficientes para demostrar efectividad sostenida. | S33: El criterio «Roster ajustado según patrones de somnolencia» muestra una mejora medible y mayormente sostenida en los resultados; persisten brechas menores o variaciones que requieren seguimiento. | T33: El criterio «Roster ajustado según patrones de somnolencia» demuestra efectividad sostenida con datos comparables de al menos tres períodos, tendencia favorable y ausencia o reducción comprobada de recurrencias, verificada mediante análisis de datos. | U33: Effectiveness | V33: Análisis de tendencia | W33: Análisis de datos | X33: Fatal | Y33: Crítico
B34: 33 | D34: Diseño de rosters basado en fatiga | E34: S03.1 | F34: Ambos | G34: Exposición | H34: Fatiga y/o somnolencia en persona expuesta a tarea crítica | I34: Pérdida de control de equipo móvil o vehículo (colisión, volcamiento, salida de vía) | J34: Diseño de sistemas de turno con criterios de fatiga | K34: Limitar la exposición por duración, secuencia de noches y oportunidad de sueño | L34: Participación de trabajadores en el diseño de turnos | M34: 5 | N34: ¿En qué medida los trabajadores expuestos participan en el diseño y la revisión de los sistemas de turno (consultas, comités, pilotos)? | O34: Ejemplos: registros de consulta o comités con participación de trabajadores; relato de trabajadores | P34: El criterio «Participación de trabajadores en el diseño de turnos» no está definido ni documentado; no existen criterios operativos, responsables ni evidencia aplicable. | Q34: El criterio «Participación de trabajadores en el diseño de turnos» se aborda de manera informal o mediante documentos aislados, incompletos o desactualizados, sin alcance ni responsables claros. | R34: El criterio «Participación de trabajadores en el diseño de turnos» está formalmente definido, pero cubre solo parte del alcance o presenta brechas relevantes de actualización, criterios, responsables o aprobación. | S34: El criterio «Participación de trabajadores en el diseño de turnos» está definido, documentado, aprobado y vigente para la mayor parte del alcance; solo quedan brechas menores de cobertura o integración. | T34: El criterio «Participación de trabajadores en el diseño de turnos» está completamente formalizado, aprobado, vigente e integrado a la gestión, con alcance, parámetros, responsables y revisión periódica verificables mediante revisión documental y entrevista. | U34: Design | V34: Registro | W34: Revisión documental y entrevista | X34: Grave | Y34: Soporte
B35: 34 | D35: Horas extra, extensiones y llamados | E35: S03.2 | F35: Fatiga | G35: Exposición | H35: Fatiga (disminución de capacidad física o mental) en persona expuesta a tarea crítica | I35: Pérdida de control de equipo móvil o vehículo (colisión, volcamiento, salida de vía) | J35: Límites y autorización de horas extra y extensiones | K35: Evitar la acumulación de deuda de sueño por jornadas extendidas | L35: Límites de horas extra, extensiones y llamados | M35: 6 | N35: ¿En qué medida hay límites claros de horas extra, extensión de turno, llamados y horas máximas por período, con autorización escalonada y controles compensatorios? | O35: Ejemplos: límites escritos o instrucciones; casos de autorización | P35: El criterio «Límites de horas extra, extensiones y llamados» no está definido ni documentado; no existen criterios operativos, responsables ni evidencia aplicable. | Q35: El criterio «Límites de horas extra, extensiones y llamados» se aborda de manera informal o mediante documentos aislados, incompletos o desactualizados, sin alcance ni responsables claros. | R35: El criterio «Límites de horas extra, extensiones y llamados» está formalmente definido, pero cubre solo parte del alcance o presenta brechas relevantes de actualización, criterios, responsables o aprobación. | S35: El criterio «Límites de horas extra, extensiones y llamados» está definido, documentado, aprobado y vigente para la mayor parte del alcance; solo quedan brechas menores de cobertura o integración. | T35: El criterio «Límites de horas extra, extensiones y llamados» está completamente formalizado, aprobado, vigente e integrado a la gestión, con alcance, parámetros, responsables y revisión periódica verificables mediante revisión documental. | U35: Design | V35: Documental | W35: Revisión documental | X35: Grave | Y35: Soporte
B36: 35 | D36: Horas extra, extensiones y llamados | E36: S03.2 | F36: Fatiga | G36: Exposición | H36: Fatiga (disminución de capacidad física o mental) en persona expuesta a tarea crítica | I36: Pérdida de control de equipo móvil o vehículo (colisión, volcamiento, salida de vía) | J36: Límites y autorización de horas extra y extensiones | K36: Evitar la acumulación de deuda de sueño por jornadas extendidas | L36: Extensiones autorizadas antes de ocurrir | M36: 7 | N36: ¿En qué medida las extensiones de jornada sobre el límite se autorizan antes de ocurrir y se acompañan de controles compensatorios (evaluación de aptitud, restricción de tareas)? | O36: Ejemplos: muestra de al menos 20 extensiones con su autorización previa y control compensatorio | P36: El control asociado a «Extensiones autorizadas antes de ocurrir» no opera en la práctica o, cuando se requiere, no genera la acción esperada. | Q36: El control asociado a «Extensiones autorizadas antes de ocurrir» opera de forma esporádica y reactiva, depende de iniciativas individuales y carece de respuesta oportuna o registros consistentes. | R36: El control asociado a «Extensiones autorizadas antes de ocurrir» funciona parcialmente o de manera irregular; genera algunas acciones, pero presenta brechas relevantes de oportunidad, calidad, seguimiento o trazabilidad. | S36: El control asociado a «Extensiones autorizadas antes de ocurrir» funciona regularmente y genera la respuesta esperada en la mayoría de los casos; quedan desviaciones menores de oportunidad, cobertura o registro. | T36: El control asociado a «Extensiones autorizadas antes de ocurrir» funciona de manera confiable, oportuna y consistente en todos los casos aplicables, con acciones trazables, seguimiento y evidencia verificable mediante muestreo de registros. | U36: Functioning | V36: Registro | W36: Muestreo de registros | X36: Fatal | Y36: Soporte
B37: 36 | D37: Horas extra, extensiones y llamados | E37: S03.2 | F37: Fatiga | G37: Exposición | H37: Fatiga (disminución de capacidad física o mental) en persona expuesta a tarea crítica | I37: Pérdida de control de equipo móvil o vehículo (colisión, volcamiento, salida de vía) | J37: Límites y autorización de horas extra y extensiones | K37: Evitar la acumulación de deuda de sueño por jornadas extendidas | L37: Seguimiento de horas acumuladas | M37: 8 | N37: ¿En qué medida existe un seguimiento, idealmente automático, que avise a la supervisión cuando una persona se acerca o supera los límites de horas, con evidencia de que se actúa? | O37: Ejemplos: reportes o avisos del sistema de asistencia y su gestión | P37: No se verifica el criterio «Seguimiento de horas acumuladas» y no existe evidencia de revisión del control o de sus resultados. | Q37: El criterio «Seguimiento de horas acumuladas» se verifica solo de manera ocasional o informal, sin método, frecuencia, muestra ni seguimiento definidos. | R37: El criterio «Seguimiento de horas acumuladas» cuenta con verificaciones periódicas pero parciales, con cobertura o profundidad insuficiente y seguimiento inconsistente de los hallazgos. | S37: El criterio «Seguimiento de horas acumuladas» se verifica sistemáticamente en la mayor parte del alcance, con hallazgos registrados y acciones de seguimiento; quedan brechas menores. | T37: El criterio «Seguimiento de horas acumuladas» se verifica de forma sistemática, independiente y basada en riesgo en todo el alcance, mediante prueba del control, con cierre comprobado de hallazgos y retroalimentación al sistema. | U37: Verification | V37: Datos de sistema | W37: Prueba del control | X37: Grave | Y37: Soporte
B38: 37 | D38: Descanso inter-turno y traslados | E38: S03.3 | F38: Somnolencia | G38: Exposición | H38: Somnolencia o microsueño en persona que opera equipo o ejecuta tarea crítica | I38: Accidente vehicular en traslado post-turno | J38: Oportunidad de sueño y gestión del traslado | K38: Asegurar descanso suficiente y controlar el riesgo de traslado post-turno | L38: Riesgo de traslado post-turno evaluado | M38: 9 | N38: ¿En qué medida se evaluó el riesgo del traslado después del turno (distancia, duración, conducción propia o bus, salida de turno de noche) y se definieron controles (transporte provisto, pausas, no conducir tras turno de noche)? | O38: Ejemplos: evaluación del riesgo del traslado; reglas de transporte | P38: El criterio «Riesgo de traslado post-turno evaluado» no está definido ni documentado; no existen criterios operativos, responsables ni evidencia aplicable. | Q38: El criterio «Riesgo de traslado post-turno evaluado» se aborda de manera informal o mediante documentos aislados, incompletos o desactualizados, sin alcance ni responsables claros. | R38: El criterio «Riesgo de traslado post-turno evaluado» está formalmente definido, pero cubre solo parte del alcance o presenta brechas relevantes de actualización, criterios, responsables o aprobación. | S38: El criterio «Riesgo de traslado post-turno evaluado» está definido, documentado, aprobado y vigente para la mayor parte del alcance; solo quedan brechas menores de cobertura o integración. | T38: El criterio «Riesgo de traslado post-turno evaluado» está completamente formalizado, aprobado, vigente e integrado a la gestión, con alcance, parámetros, responsables y revisión periódica verificables mediante revisión documental. | U38: Design | V38: Documental | W38: Revisión documental | X38: Fatal | Y38: Crítico
B39: 38 | D39: Descanso inter-turno y traslados | E39: S03.3 | F39: Somnolencia | G39: Exposición | H39: Somnolencia o microsueño en persona que opera equipo o ejecuta tarea crítica | I39: Accidente vehicular en traslado post-turno | J39: Oportunidad de sueño y gestión del traslado | K39: Asegurar descanso suficiente y controlar el riesgo de traslado post-turno | L39: Controles de traslado aplicados | M39: 10 | N39: ¿En qué medida los controles de traslado se aplican en la práctica (por ejemplo, % de trabajadores de turno de noche que usan el transporte provisto, conductores de bus evaluados)? | O39: Ejemplos: registros de transporte; evaluaciones de conductores; observación en la salida de turno | P39: El control asociado a «Controles de traslado aplicados» no opera en la práctica o, cuando se requiere, no genera la acción esperada. | Q39: El control asociado a «Controles de traslado aplicados» opera de forma esporádica y reactiva, depende de iniciativas individuales y carece de respuesta oportuna o registros consistentes. | R39: El control asociado a «Controles de traslado aplicados» funciona parcialmente o de manera irregular; genera algunas acciones, pero presenta brechas relevantes de oportunidad, calidad, seguimiento o trazabilidad. | S39: El control asociado a «Controles de traslado aplicados» funciona regularmente y genera la respuesta esperada en la mayoría de los casos; quedan desviaciones menores de oportunidad, cobertura o registro. | T39: El control asociado a «Controles de traslado aplicados» funciona de manera confiable, oportuna y consistente en todos los casos aplicables, con acciones trazables, seguimiento y evidencia verificable mediante observación en terreno. | U39: Functioning | V39: Observación en terreno | W39: Observación en terreno | X39: Fatal | Y39: Crítico
B40: 39 | D40: Descanso inter-turno y traslados | E40: S03.3 | F40: Fatiga | G40: Exposición | H40: Fatiga (disminución de capacidad física o mental) en persona expuesta a tarea crítica | I40: Accidente vehicular en traslado post-turno | J40: Oportunidad de sueño y gestión del traslado | K40: Asegurar descanso suficiente y controlar el riesgo de traslado post-turno | L40: Descanso mínimo entre turnos cumplido | M40: 11 | N40: ¿En qué medida se cumple en la programación real un descanso mínimo entre turnos, descontando traslado y alimentación? | O40: Ejemplos: cálculo del descanso entre turnos con datos de asistencia y traslado (X04) | P40: El criterio «Descanso mínimo entre turnos cumplido» no se aplica en la práctica y no existe evidencia de implementación. | Q40: El criterio «Descanso mínimo entre turnos cumplido» se aplica solo en casos aislados o de manera informal, sin cobertura planificada ni consistencia entre áreas, turnos o personas expuestas. | R40: El criterio «Descanso mínimo entre turnos cumplido» está implementado parcialmente; alcanza parte de la población o del proceso, con brechas relevantes de cobertura, frecuencia o registro. | S40: El criterio «Descanso mínimo entre turnos cumplido» está implementado de forma regular en la mayor parte del alcance y con evidencia suficiente; persisten brechas menores de cobertura o consistencia. | T40: El criterio «Descanso mínimo entre turnos cumplido» está implementado sistemáticamente en todo el alcance aplicable, incluidos turnos y contratistas cuando corresponde, con registros completos y verificación mediante análisis de datos. | U40: Implementation | V40: Datos de sistema | W40: Análisis de datos | X40: Grave | Y40: Soporte
B41: 40 | C41: D.4 Gestión operacional de la fatiga | D41: Evaluación de aptitud pre-turno | E41: S04.1 | F41: Ambos | G41: Fatiga o somnolencia | H41: Fatiga y/o somnolencia en persona expuesta a tarea crítica | I41: Persona fatigada o somnolienta permanece en tarea crítica sin ser detectada ni intervenida | J41: Evaluación pre-turno de aptitud (fit for work) | K41: Impedir que una persona con fatiga o somnolencia inicie una tarea crítica | L41: Evaluación antes del turno con criterios objetivos | M41: 1 | N41: ¿En qué medida la evaluación de aptitud antes del turno usa preguntas o mediciones objetivas (horas de sueño en 24 y 48 h, horas despierto, síntomas), umbrales de decisión y acciones definidas (apto, apto con restricción, no apto)? | O41: Ejemplos: formulario o instrucción con umbrales y decisiones; si es informal, cómo lo hacen los supervisores | P41: El criterio «Evaluación antes del turno con criterios objetivos» no está definido ni documentado; no existen criterios operativos, responsables ni evidencia aplicable. | Q41: El criterio «Evaluación antes del turno con criterios objetivos» se aborda de manera informal o mediante documentos aislados, incompletos o desactualizados, sin alcance ni responsables claros. | R41: El criterio «Evaluación antes del turno con criterios objetivos» está formalmente definido, pero cubre solo parte del alcance o presenta brechas relevantes de actualización, criterios, responsables o aprobación. | S41: El criterio «Evaluación antes del turno con criterios objetivos» está definido, documentado, aprobado y vigente para la mayor parte del alcance; solo quedan brechas menores de cobertura o integración. | T41: El criterio «Evaluación antes del turno con criterios objetivos» está completamente formalizado, aprobado, vigente e integrado a la gestión, con alcance, parámetros, responsables y revisión periódica verificables mediante revisión documental y entrevista. | U41: Design | V41: Documental | W41: Revisión documental y entrevista | X41: Fatal | Y41: Crítico
B42: 41 | D42: Evaluación de aptitud pre-turno | E42: S04.1 | F42: Ambos | G42: Fatiga o somnolencia | H42: Fatiga y/o somnolencia en persona expuesta a tarea crítica | I42: Persona fatigada o somnolienta permanece en tarea crítica sin ser detectada ni intervenida | J42: Evaluación pre-turno de aptitud (fit for work) | K42: Impedir que una persona con fatiga o somnolencia inicie una tarea crítica | L42: Cobertura total de la evaluación antes del turno | M42: 2 | N42: ¿En qué medida la evaluación antes del turno se aplica a todo el personal en tareas críticas, en todos los turnos (incluidas noches y fines de semana) y a contratistas? | O42: Ejemplos: registros de evaluación comparados con la dotación por turno; % de cobertura (L01) | P42: El criterio «Cobertura total de la evaluación antes del turno» no se aplica en la práctica y no existe evidencia de implementación. | Q42: El criterio «Cobertura total de la evaluación antes del turno» se aplica solo en casos aislados o de manera informal, sin cobertura planificada ni consistencia entre áreas, turnos o personas expuestas. | R42: El criterio «Cobertura total de la evaluación antes del turno» está implementado parcialmente; alcanza parte de la población o del proceso, con brechas relevantes de cobertura, frecuencia o registro. | S42: El criterio «Cobertura total de la evaluación antes del turno» está implementado de forma regular en la mayor parte del alcance y con evidencia suficiente; persisten brechas menores de cobertura o consistencia. | T42: El criterio «Cobertura total de la evaluación antes del turno» está implementado sistemáticamente en todo el alcance aplicable, incluidos turnos y contratistas cuando corresponde, con registros completos y verificación mediante muestreo de registros. | U42: Implementation | V42: Registro | W42: Muestreo de registros | X42: Fatal | Y42: Crítico
B43: 42 | D43: Evaluación de aptitud pre-turno | E43: S04.1 | F43: Ambos | G43: Fatiga o somnolencia | H43: Fatiga y/o somnolencia en persona expuesta a tarea crítica | I43: Persona fatigada o somnolienta permanece en tarea crítica sin ser detectada ni intervenida | J43: Evaluación pre-turno de aptitud (fit for work) | K43: Impedir que una persona con fatiga o somnolencia inicie una tarea crítica | L43: Acción aplicada cuando se detecta riesgo | M43: 3 | N43: Cuando la evaluación antes del turno detecta riesgo, ¿en qué medida se aplica efectivamente la acción que corresponde (restricción, reasignación, no inicio)? | O43: Ejemplos: muestra de evaluaciones con riesgo y la acción aplicada; tasa de coherencia | P43: El control asociado a «Acción aplicada cuando se detecta riesgo» no opera en la práctica o, cuando se requiere, no genera la acción esperada. | Q43: El control asociado a «Acción aplicada cuando se detecta riesgo» opera de forma esporádica y reactiva, depende de iniciativas individuales y carece de respuesta oportuna o registros consistentes. | R43: El control asociado a «Acción aplicada cuando se detecta riesgo» funciona parcialmente o de manera irregular; genera algunas acciones, pero presenta brechas relevantes de oportunidad, calidad, seguimiento o trazabilidad. | S43: El control asociado a «Acción aplicada cuando se detecta riesgo» funciona regularmente y genera la respuesta esperada en la mayoría de los casos; quedan desviaciones menores de oportunidad, cobertura o registro. | T43: El control asociado a «Acción aplicada cuando se detecta riesgo» funciona de manera confiable, oportuna y consistente en todos los casos aplicables, con acciones trazables, seguimiento y evidencia verificable mediante reconstrucción de casos. | U43: Functioning | V43: Registro | W43: Reconstrucción de casos | X43: Fatal | Y43: Crítico
B44: 43 | D44: Evaluación de aptitud pre-turno | E44: S04.1 | F44: Ambos | G44: Fatiga o somnolencia | H44: Fatiga y/o somnolencia en persona expuesta a tarea crítica | I44: Persona fatigada o somnolienta permanece en tarea crítica sin ser detectada ni intervenida | J44: Evaluación pre-turno de aptitud (fit for work) | K44: Impedir que una persona con fatiga o somnolencia inicie una tarea crítica | L44: Verificación independiente de la evaluación antes del turno | M44: 4 | N44: ¿En qué medida un tercero (jefatura superior o área de seguridad) verifica periódicamente, observando directamente, la calidad de las evaluaciones antes del turno? | O44: Ejemplos: registros de verificación por observación | P44: No se verifica el criterio «Verificación independiente de la evaluación antes del turno» y no existe evidencia de revisión del control o de sus resultados. | Q44: El criterio «Verificación independiente de la evaluación antes del turno» se verifica solo de manera ocasional o informal, sin método, frecuencia, muestra ni seguimiento definidos. | R44: El criterio «Verificación independiente de la evaluación antes del turno» cuenta con verificaciones periódicas pero parciales, con cobertura o profundidad insuficiente y seguimiento inconsistente de los hallazgos. | S44: El criterio «Verificación independiente de la evaluación antes del turno» se verifica sistemáticamente en la mayor parte del alcance, con hallazgos registrados y acciones de seguimiento; quedan brechas menores. | T44: El criterio «Verificación independiente de la evaluación antes del turno» se verifica de forma sistemática, independiente y basada en riesgo en todo el alcance, mediante observación en terreno, con cierre comprobado de hallazgos y retroalimentación al sistema. | U44: Verification | V44: Observación en terreno | W44: Observación en terreno | X44: Grave | Y44: Crítico
B45: 44 | D45: Evaluación de aptitud pre-turno | E45: S04.1 | F45: Somnolencia | G45: Fatiga o somnolencia | H45: Somnolencia o microsueño en persona que opera equipo o ejecuta tarea crítica | I45: Persona fatigada o somnolienta permanece en tarea crítica sin ser detectada ni intervenida | J45: Evaluación pre-turno de aptitud (fit for work) | K45: Impedir que una persona con fatiga o somnolencia inicie una tarea crítica | L45: Capacidad predictiva de la evaluación antes del turno | M45: 5 | N45: ¿En qué medida se analiza si las personas identificadas en riesgo antes del turno concentran después más alertas o eventos, y se usa para ajustar los umbrales? | O45: Ejemplos: análisis cruzado de evaluaciones con alertas y eventos, al menos 3 meses | P45: El criterio «Capacidad predictiva de la evaluación antes del turno» no muestra resultados medibles o no se evalúa su efecto sobre el riesgo y el desempeño. | Q45: El criterio «Capacidad predictiva de la evaluación antes del turno» presenta resultados anecdóticos o aislados, sin línea base, indicadores comparables ni evidencia de mejora atribuible. | R45: El criterio «Capacidad predictiva de la evaluación antes del turno» dispone de algunos indicadores o comparaciones, pero los resultados son parciales, inestables o insuficientes para demostrar efectividad sostenida. | S45: El criterio «Capacidad predictiva de la evaluación antes del turno» muestra una mejora medible y mayormente sostenida en los resultados; persisten brechas menores o variaciones que requieren seguimiento. | T45: El criterio «Capacidad predictiva de la evaluación antes del turno» demuestra efectividad sostenida con datos comparables de al menos tres períodos, tendencia favorable y ausencia o reducción comprobada de recurrencias, verificada mediante análisis de datos. | U45: Effectiveness | V45: Análisis de tendencia | W45: Análisis de datos | X45: Fatal | Y45: Crítico
B46: 45 | D46: Evaluación de aptitud pre-turno | E46: S04.1 | F46: Somnolencia | G46: Fatiga o somnolencia | H46: Somnolencia o microsueño en persona que opera equipo o ejecuta tarea crítica | I46: Persona fatigada o somnolienta permanece en tarea crítica sin ser detectada ni intervenida | J46: Evaluación pre-turno de aptitud (fit for work) | K46: Impedir que una persona con fatiga o somnolencia inicie una tarea crítica | L46: Prueba objetiva de alerta usada como complemento | M46: 6 | N46: Si la faena usa pupilometría u otra prueba objetiva de alerta, ¿en qué medida están claros su validez para el uso, el umbral y su papel como complemento (no reemplazo) del juicio del supervisor? | O46: Ejemplos: especificación del método, umbral y validación del uso local. Marcar Aplica = No si no se usa ninguna prueba | P46: El criterio «Prueba objetiva de alerta usada como complemento» no está definido ni documentado; no existen criterios operativos, responsables ni evidencia aplicable. | Q46: El criterio «Prueba objetiva de alerta usada como complemento» se aborda de manera informal o mediante documentos aislados, incompletos o desactualizados, sin alcance ni responsables claros. | R46: El criterio «Prueba objetiva de alerta usada como complemento» está formalmente definido, pero cubre solo parte del alcance o presenta brechas relevantes de actualización, criterios, responsables o aprobación. | S46: El criterio «Prueba objetiva de alerta usada como complemento» está definido, documentado, aprobado y vigente para la mayor parte del alcance; solo quedan brechas menores de cobertura o integración. | T46: El criterio «Prueba objetiva de alerta usada como complemento» está completamente formalizado, aprobado, vigente e integrado a la gestión, con alcance, parámetros, responsables y revisión periódica verificables mediante revisión documental. | U46: Design | V46: Documental | W46: Revisión documental | X46: Grave | Y46: Soporte
B47: 46 | D47: Evaluación de aptitud pre-turno | E47: S04.1 | F47: Somnolencia | G47: Fatiga o somnolencia | H47: Somnolencia o microsueño en persona que opera equipo o ejecuta tarea crítica | I47: Persona fatigada o somnolienta permanece en tarea crítica sin ser detectada ni intervenida | J47: Evaluación pre-turno de aptitud (fit for work) | K47: Impedir que una persona con fatiga o somnolencia inicie una tarea crítica | L47: Resultados fuera de umbral intervenidos | M47: 7 | N47: ¿En qué medida los resultados fuera de umbral de la prueba objetiva generan una intervención registrada antes de iniciar la tarea? | O47: Ejemplos: resultados fuera de umbral con su intervención | P47: El control asociado a «Resultados fuera de umbral intervenidos» no opera en la práctica o, cuando se requiere, no genera la acción esperada. | Q47: El control asociado a «Resultados fuera de umbral intervenidos» opera de forma esporádica y reactiva, depende de iniciativas individuales y carece de respuesta oportuna o registros consistentes. | R47: El control asociado a «Resultados fuera de umbral intervenidos» funciona parcialmente o de manera irregular; genera algunas acciones, pero presenta brechas relevantes de oportunidad, calidad, seguimiento o trazabilidad. | S47: El control asociado a «Resultados fuera de umbral intervenidos» funciona regularmente y genera la respuesta esperada en la mayoría de los casos; quedan desviaciones menores de oportunidad, cobertura o registro. | T47: El control asociado a «Resultados fuera de umbral intervenidos» funciona de manera confiable, oportuna y consistente en todos los casos aplicables, con acciones trazables, seguimiento y evidencia verificable mediante reconstrucción de casos. | U47: Functioning | V47: Datos de sistema | W47: Reconstrucción de casos | X47: Grave | Y47: Soporte
B48: 47 | D48: Evaluación de aptitud pre-turno | E48: S04.1 | F48: Ambos | G48: Fatiga o somnolencia | H48: Fatiga y/o somnolencia en persona expuesta a tarea crítica | I48: Persona fatigada o somnolienta permanece en tarea crítica sin ser detectada ni intervenida | J48: Evaluación pre-turno de aptitud (fit for work) | K48: Impedir que una persona con fatiga o somnolencia inicie una tarea crítica | L48: Auto-reporte de fatiga sin represalia en uso | M48: 8 | N48: ¿En qué medida las personas pueden declarar "no estoy apto por fatiga" sin consecuencias punitivas, y efectivamente lo hacen en distintas áreas y turnos? | O48: Ejemplos: registros de auto-reportes (L10); casos y su tratamiento; entrevistas | P48: El criterio «Auto-reporte de fatiga sin represalia en uso» no se aplica en la práctica y no existe evidencia de implementación. | Q48: El criterio «Auto-reporte de fatiga sin represalia en uso» se aplica solo en casos aislados o de manera informal, sin cobertura planificada ni consistencia entre áreas, turnos o personas expuestas. | R48: El criterio «Auto-reporte de fatiga sin represalia en uso» está implementado parcialmente; alcanza parte de la población o del proceso, con brechas relevantes de cobertura, frecuencia o registro. | S48: El criterio «Auto-reporte de fatiga sin represalia en uso» está implementado de forma regular en la mayor parte del alcance y con evidencia suficiente; persisten brechas menores de cobertura o consistencia. | T48: El criterio «Auto-reporte de fatiga sin represalia en uso» está implementado sistemáticamente en todo el alcance aplicable, incluidos turnos y contratistas cuando corresponde, con registros completos y verificación mediante muestreo de registros y entrevista. | U48: Implementation | V48: Registro | W48: Muestreo de registros y entrevista | X48: Grave | Y48: Soporte
B49: 48 | D49: Supervisión e interacción en terreno | E49: S04.2 | F49: Fatiga | G49: Deterioro del desempeño humano | H49: Fatiga (disminución de capacidad física o mental) en persona expuesta a tarea crítica | I49: Persona fatigada o somnolienta permanece en tarea crítica sin ser detectada ni intervenida | J49: Monitoreo de supervisión durante el turno | K49: Detectar signos de fatiga durante el turno | L49: Guía de signos de fatiga para supervisores | M49: 9 | N49: ¿En qué medida los supervisores cuentan con una guía clara para reconocer signos de fatiga y somnolencia y saber qué hacer en cada caso? | O49: Ejemplos: lista de verificación o guía; lo que los supervisores dicen usar | P49: El criterio «Guía de signos de fatiga para supervisores» no está definido ni documentado; no existen criterios operativos, responsables ni evidencia aplicable. | Q49: El criterio «Guía de signos de fatiga para supervisores» se aborda de manera informal o mediante documentos aislados, incompletos o desactualizados, sin alcance ni responsables claros. | R49: El criterio «Guía de signos de fatiga para supervisores» está formalmente definido, pero cubre solo parte del alcance o presenta brechas relevantes de actualización, criterios, responsables o aprobación. | S49: El criterio «Guía de signos de fatiga para supervisores» está definido, documentado, aprobado y vigente para la mayor parte del alcance; solo quedan brechas menores de cobertura o integración. | T49: El criterio «Guía de signos de fatiga para supervisores» está completamente formalizado, aprobado, vigente e integrado a la gestión, con alcance, parámetros, responsables y revisión periódica verificables mediante revisión documental y entrevista. | U49: Design | V49: Documental | W49: Revisión documental y entrevista | X49: Grave | Y49: Soporte
B50: 49 | D50: Supervisión e interacción en terreno | E50: S04.2 | F50: Ambos | G50: Deterioro del desempeño humano | H50: Fatiga y/o somnolencia en persona expuesta a tarea crítica | I50: Persona fatigada o somnolienta permanece en tarea crítica sin ser detectada ni intervenida | J50: Monitoreo de supervisión durante el turno | K50: Detectar signos de fatiga durante el turno | L50: Interacciones en horario crítico que generan acción | M50: 10 | N50: ¿En qué medida los supervisores conversan con su equipo sobre fatiga en terreno en horario crítico (02:00–06:00) y actúan cuando observan signos? | O50: Ejemplos: registros de interacciones por horario; casos con acción; observación | P50: El control asociado a «Interacciones en horario crítico que generan acción» no opera en la práctica o, cuando se requiere, no genera la acción esperada. | Q50: El control asociado a «Interacciones en horario crítico que generan acción» opera de forma esporádica y reactiva, depende de iniciativas individuales y carece de respuesta oportuna o registros consistentes. | R50: El control asociado a «Interacciones en horario crítico que generan acción» funciona parcialmente o de manera irregular; genera algunas acciones, pero presenta brechas relevantes de oportunidad, calidad, seguimiento o trazabilidad. | S50: El control asociado a «Interacciones en horario crítico que generan acción» funciona regularmente y genera la respuesta esperada en la mayoría de los casos; quedan desviaciones menores de oportunidad, cobertura o registro. | T50: El control asociado a «Interacciones en horario crítico que generan acción» funciona de manera confiable, oportuna y consistente en todos los casos aplicables, con acciones trazables, seguimiento y evidencia verificable mediante observación en terreno. | U50: Functioning | V50: Observación en terreno | W50: Observación en terreno | X50: Grave | Y50: Soporte
B51: 50 | D51: Supervisión e interacción en terreno | E51: S04.2 | F51: Fatiga | G51: Deterioro del desempeño humano | H51: Fatiga (disminución de capacidad física o mental) en persona expuesta a tarea crítica | I51: Persona fatigada o somnolienta permanece en tarea crítica sin ser detectada ni intervenida | J51: Monitoreo de supervisión durante el turno | K51: Detectar signos de fatiga durante el turno | L51: Contenido específico de fatiga en charlas de inicio de turno | M51: 11 | N51: ¿En qué medida la fatiga y la somnolencia se tratan en las charlas de inicio de turno con contenido específico (noche 1, retorno de descanso) y no solo como mención genérica? | O51: Ejemplos: registros de charlas; observación de 3 charlas | P51: El criterio «Contenido específico de fatiga en charlas de inicio de turno» no se aplica en la práctica y no existe evidencia de implementación. | Q51: El criterio «Contenido específico de fatiga en charlas de inicio de turno» se aplica solo en casos aislados o de manera informal, sin cobertura planificada ni consistencia entre áreas, turnos o personas expuestas. | R51: El criterio «Contenido específico de fatiga en charlas de inicio de turno» está implementado parcialmente; alcanza parte de la población o del proceso, con brechas relevantes de cobertura, frecuencia o registro. | S51: El criterio «Contenido específico de fatiga en charlas de inicio de turno» está implementado de forma regular en la mayor parte del alcance y con evidencia suficiente; persisten brechas menores de cobertura o consistencia. | T51: El criterio «Contenido específico de fatiga en charlas de inicio de turno» está implementado sistemáticamente en todo el alcance aplicable, incluidos turnos y contratistas cuando corresponde, con registros completos y verificación mediante observación en terreno. | U51: Implementation | V51: Observación en terreno | W51: Observación en terreno | X51: Moderado | Y51: Administrativo
B52: 51 | D52: Relevos y retiro de tarea crítica | E52: S04.3 | F52: Ambos | G52: Degradación de barreras | H52: Fatiga y/o somnolencia en persona expuesta a tarea crítica | I52: Persona fatigada o somnolienta permanece en tarea crítica sin ser detectada ni intervenida | J52: Gestión de relevos y retiro de tarea | K52: Retirar efectivamente a la persona de la exposición | L52: Relevos previstos para tareas críticas | M52: 12 | N52: ¿En qué medida está previsto, por área y turno, quién reemplaza a una persona en una tarea crítica, incluido el turno de noche? | O52: Ejemplos: plan o lista de relevos con dotación disponible por turno; si no existe, cómo se resuelve hoy | P52: El criterio «Relevos previstos para tareas críticas» no está definido ni documentado; no existen criterios operativos, responsables ni evidencia aplicable. | Q52: El criterio «Relevos previstos para tareas críticas» se aborda de manera informal o mediante documentos aislados, incompletos o desactualizados, sin alcance ni responsables claros. | R52: El criterio «Relevos previstos para tareas críticas» está formalmente definido, pero cubre solo parte del alcance o presenta brechas relevantes de actualización, criterios, responsables o aprobación. | S52: El criterio «Relevos previstos para tareas críticas» está definido, documentado, aprobado y vigente para la mayor parte del alcance; solo quedan brechas menores de cobertura o integración. | T52: El criterio «Relevos previstos para tareas críticas» está completamente formalizado, aprobado, vigente e integrado a la gestión, con alcance, parámetros, responsables y revisión periódica verificables mediante revisión documental y entrevista. | U52: Design | V52: Documental | W52: Revisión documental y entrevista | X52: Fatal | Y52: Crítico
B53: 52 | D53: Relevos y retiro de tarea crítica | E53: S04.3 | F53: Ambos | G53: Degradación de barreras | H53: Fatiga y/o somnolencia en persona expuesta a tarea crítica | I53: Persona fatigada o somnolienta permanece en tarea crítica sin ser detectada ni intervenida | J53: Gestión de relevos y retiro de tarea | K53: Retirar efectivamente a la persona de la exposición | L53: Retiro de la tarea dentro del tiempo objetivo | M53: 13 | N53: Ante una persona evaluada como no apta durante el turno, ¿en qué medida se concreta el retiro de la tarea crítica dentro de un tiempo razonable y definido? | O53: Ejemplos: casos de retiro con tiempos desde la alerta hasta el retiro; muestra de al menos 20 casos | P53: El control asociado a «Retiro de la tarea dentro del tiempo objetivo» no opera en la práctica o, cuando se requiere, no genera la acción esperada. | Q53: El control asociado a «Retiro de la tarea dentro del tiempo objetivo» opera de forma esporádica y reactiva, depende de iniciativas individuales y carece de respuesta oportuna o registros consistentes. | R53: El control asociado a «Retiro de la tarea dentro del tiempo objetivo» funciona parcialmente o de manera irregular; genera algunas acciones, pero presenta brechas relevantes de oportunidad, calidad, seguimiento o trazabilidad. | S53: El control asociado a «Retiro de la tarea dentro del tiempo objetivo» funciona regularmente y genera la respuesta esperada en la mayoría de los casos; quedan desviaciones menores de oportunidad, cobertura o registro. | T53: El control asociado a «Retiro de la tarea dentro del tiempo objetivo» funciona de manera confiable, oportuna y consistente en todos los casos aplicables, con acciones trazables, seguimiento y evidencia verificable mediante reconstrucción de casos. | U53: Functioning | V53: Datos de sistema | W53: Reconstrucción de casos | X53: Fatal | Y53: Crítico
... B57: 56 | D57: Planificación de tareas críticas | E57: S04.4 | F57: Somnolencia | G57: Exposición | H57: Somnolencia o microsueño en persona que opera equipo o ejecuta tarea crítica | I57: Error u omisión en tarea crítica (aislamiento, izaje, operación de planta) por desempeño degradado | J57: Planificación de tareas críticas considerando fatiga | K57: Evitar programar tareas de alto riesgo en condiciones de máxima vulnerabilidad | L57: Restricciones aplicadas en la programación | M57: 17 | N57: ¿En qué medida esas restricciones se respetan en la programación real y en los registros de despacho? | O57: Ejemplos: programación de tareas y registros de despacho comparados con las restricciones | P57: El control asociado a «Restricciones aplicadas en la programación» no opera en la práctica o, cuando se requiere, no genera la acción esperada. | Q57: El control asociado a «Restricciones aplicadas en la programación» opera de forma esporádica y reactiva, depende de iniciativas individuales y carece de respuesta oportuna o registros consistentes. | R57: El control asociado a «Restricciones aplicadas en la programación» funciona parcialmente o de manera irregular; genera algunas acciones, pero presenta brechas relevantes de oportunidad, calidad, seguimiento o trazabilidad. | S57: El control asociado a «Restricciones aplicadas en la programación» funciona regularmente y genera la respuesta esperada en la mayoría de los casos; quedan desviaciones menores de oportunidad, cobertura o registro. | T57: El control asociado a «Restricciones aplicadas en la programación» funciona de manera confiable, oportuna y consistente en todos los casos aplicables, con acciones trazables, seguimiento y evidencia verificable mediante muestreo de registros. | U57: Functioning | V57: Datos de sistema | W57: Muestreo de registros | X57: Fatal | Y57: Crítico
B58: 57 | C58: D.5 Gestión de la somnolencia | D58: Detección de somnolencia en tiempo real | E58: S05.1 | F58: Somnolencia | G58: Deterioro del desempeño humano | H58: Somnolencia o microsueño en persona que opera equipo o ejecuta tarea crítica | I58: Pérdida de control de equipo móvil o vehículo (colisión, volcamiento, salida de vía) | J58: Tecnología de detección (SmartCap, DSS u otra) | K58: Detectar somnolencia o microsueño antes de la pérdida de control | L58: Alcance de la detección definido por riesgo | M58: 1 | N58: ¿En qué medida está definido, según el riesgo, qué equipos y tareas requieren detección de somnolencia en tiempo real? | O58: Ejemplos: definición del alcance por flota o tarea y su justificación. Si no existe tecnología, registrar Existencia = No | P58: El criterio «Alcance de la detección definido por riesgo» no está definido ni documentado; no existen criterios operativos, responsables ni evidencia aplicable. | Q58: El criterio «Alcance de la detección definido por riesgo» se aborda de manera informal o mediante documentos aislados, incompletos o desactualizados, sin alcance ni responsables claros. | R58: El criterio «Alcance de la detección definido por riesgo» está formalmente definido, pero cubre solo parte del alcance o presenta brechas relevantes de actualización, criterios, responsables o aprobación. | S58: El criterio «Alcance de la detección definido por riesgo» está definido, documentado, aprobado y vigente para la mayor parte del alcance; solo quedan brechas menores de cobertura o integración. | T58: El criterio «Alcance de la detección definido por riesgo» está completamente formalizado, aprobado, vigente e integrado a la gestión, con alcance, parámetros, responsables y revisión periódica verificables mediante revisión documental. | U58: Design | V58: Documental | W58: Revisión documental | X58: Fatal | Y58: Crítico
B59: 58 | D59: Detección de somnolencia en tiempo real | E59: S05.1 | F59: Somnolencia | G59: Deterioro del desempeño humano | H59: Somnolencia o microsueño en persona que opera equipo o ejecuta tarea crítica | I59: Pérdida de control de equipo móvil o vehículo (colisión, volcamiento, salida de vía) | J59: Tecnología de detección (SmartCap, DSS u otra) | K59: Detectar somnolencia o microsueño antes de la pérdida de control | L59: Tecnología en uso y operativa (no solo instalada) | M59: 2 | N59: ¿En qué medida los equipos en alcance operan con el dispositivo de detección en uso y funcionando (L08)? | O59: Ejemplos: datos del sistema con horas con dispositivo activo sobre horas operadas | P59: El criterio «Tecnología en uso y operativa (no solo instalada)» no se aplica en la práctica y no existe evidencia de implementación. | Q59: El criterio «Tecnología en uso y operativa (no solo instalada)» se aplica solo en casos aislados o de manera informal, sin cobertura planificada ni consistencia entre áreas, turnos o personas expuestas. | R59: El criterio «Tecnología en uso y operativa (no solo instalada)» está implementado parcialmente; alcanza parte de la población o del proceso, con brechas relevantes de cobertura, frecuencia o registro. | S59: El criterio «Tecnología en uso y operativa (no solo instalada)» está implementado de forma regular en la mayor parte del alcance y con evidencia suficiente; persisten brechas menores de cobertura o consistencia. | T59: El criterio «Tecnología en uso y operativa (no solo instalada)» está implementado sistemáticamente en todo el alcance aplicable, incluidos turnos y contratistas cuando corresponde, con registros completos y verificación mediante análisis de datos. | U59: Implementation | V59: Datos de sistema | W59: Análisis de datos | X59: Fatal | Y59: Crítico
B60: 59 | D60: Detección de somnolencia en tiempo real | E60: S05.1 | F60: Somnolencia | G60: Deterioro del desempeño humano | H60: Somnolencia o microsueño en persona que opera equipo o ejecuta tarea crítica | I60: Pérdida de control de equipo móvil o vehículo (colisión, volcamiento, salida de vía) | J60: Tecnología de detección (SmartCap, DSS u otra) | K60: Detectar somnolencia o microsueño antes de la pérdida de control | L60: Alertas transmitidas a tiempo | M60: 3 | N60: ¿En qué medida las alertas llegan al centro de monitoreo o despacho y al supervisor en el tiempo esperado, sin pérdidas de comunicación relevantes? | O60: Ejemplos: trazabilidad de alertas (generación, recepción y demora); % de alertas recibidas | P60: El control asociado a «Alertas transmitidas a tiempo» no opera en la práctica o, cuando se requiere, no genera la acción esperada. | Q60: El control asociado a «Alertas transmitidas a tiempo» opera de forma esporádica y reactiva, depende de iniciativas individuales y carece de respuesta oportuna o registros consistentes. | R60: El control asociado a «Alertas transmitidas a tiempo» funciona parcialmente o de manera irregular; genera algunas acciones, pero presenta brechas relevantes de oportunidad, calidad, seguimiento o trazabilidad. | S60: El control asociado a «Alertas transmitidas a tiempo» funciona regularmente y genera la respuesta esperada en la mayoría de los casos; quedan desviaciones menores de oportunidad, cobertura o registro. | T60: El control asociado a «Alertas transmitidas a tiempo» funciona de manera confiable, oportuna y consistente en todos los casos aplicables, con acciones trazables, seguimiento y evidencia verificable mediante prueba del control. | U60: Functioning | V60: Datos de sistema | W60: Prueba del control | X60: Fatal | Y60: Crítico
B61: 60 | D61: Respuesta e intervención frente a alertas | E61: S05.2 | F61: Somnolencia | G61: Degradación de barreras | H61: Somnolencia o microsueño en persona que opera equipo o ejecuta tarea crítica | I61: Persona fatigada o somnolienta permanece en tarea crítica sin ser detectada ni intervenida | J61: Protocolo de intervención frente a alertas | K61: Convertir la detección en intervención que retire a la persona de la exposición | L61: Respuesta a alertas definida por nivel | M61: 4 | N61: ¿En qué medida está definido, según el tipo y la gravedad de la alerta, quién responde, en qué tiempo y con qué acción (contacto, detención segura, evaluación, pausa, relevo, retiro)? | O61: Ejemplos: instrucción o matriz alerta-acción-tiempo; si es informal, cómo responden hoy despacho y supervisión | P61: El criterio «Respuesta a alertas definida por nivel» no está definido ni documentado; no existen criterios operativos, responsables ni evidencia aplicable. | Q61: El criterio «Respuesta a alertas definida por nivel» se aborda de manera informal o mediante documentos aislados, incompletos o desactualizados, sin alcance ni responsables claros. | R61: El criterio «Respuesta a alertas definida por nivel» está formalmente definido, pero cubre solo parte del alcance o presenta brechas relevantes de actualización, criterios, responsables o aprobación. | S61: El criterio «Respuesta a alertas definida por nivel» está definido, documentado, aprobado y vigente para la mayor parte del alcance; solo quedan brechas menores de cobertura o integración. | T61: El criterio «Respuesta a alertas definida por nivel» está completamente formalizado, aprobado, vigente e integrado a la gestión, con alcance, parámetros, responsables y revisión periódica verificables mediante revisión documental y entrevista. | U61: Design | V61: Documental | W61: Revisión documental y entrevista | X61: Fatal | Y61: Crítico
B62: 61 | D62: Respuesta e intervención frente a alertas | E62: S05.2 | F62: Somnolencia | G62: Degradación de barreras | H62: Somnolencia o microsueño en persona que opera equipo o ejecuta tarea crítica | I62: Persona fatigada o somnolienta permanece en tarea crítica sin ser detectada ni intervenida | J62: Protocolo de intervención frente a alertas | K62: Convertir la detección en intervención que retire a la persona de la exposición | L62: Alertas intervenidas dentro del tiempo objetivo | M62: 5 | N62: ¿En qué medida las alertas de alto nivel se intervienen dentro del tiempo definido, considerando todas las alertas, incluida la noche (L02)? | O62: Ejemplos: trazabilidad alerta-intervención con tiempos | P62: El control asociado a «Alertas intervenidas dentro del tiempo objetivo» no opera en la práctica o, cuando se requiere, no genera la acción esperada. | Q62: El control asociado a «Alertas intervenidas dentro del tiempo objetivo» opera de forma esporádica y reactiva, depende de iniciativas individuales y carece de respuesta oportuna o registros consistentes. | R62: El control asociado a «Alertas intervenidas dentro del tiempo objetivo» funciona parcialmente o de manera irregular; genera algunas acciones, pero presenta brechas relevantes de oportunidad, calidad, seguimiento o trazabilidad. | S62: El control asociado a «Alertas intervenidas dentro del tiempo objetivo» funciona regularmente y genera la respuesta esperada en la mayoría de los casos; quedan desviaciones menores de oportunidad, cobertura o registro. | T62: El control asociado a «Alertas intervenidas dentro del tiempo objetivo» funciona de manera confiable, oportuna y consistente en todos los casos aplicables, con acciones trazables, seguimiento y evidencia verificable mediante reconstrucción de casos. | U62: Functioning | V62: Datos de sistema | W62: Reconstrucción de casos | X62: Fatal | Y62: Crítico
B63: 62 | D63: Respuesta e intervención frente a alertas | E63: S05.2 | F63: Somnolencia | G63: Degradación de barreras | H63: Somnolencia o microsueño en persona que opera equipo o ejecuta tarea crítica | I63: Persona fatigada o somnolienta permanece en tarea crítica sin ser detectada ni intervenida | J63: Protocolo de intervención frente a alertas | K63: Convertir la detección en intervención que retire a la persona de la exposición | L63: Calidad real de la intervención verificada | M63: 6 | N63: ¿En qué medida se verifica en una muestra de alertas que la intervención fue adecuada (la persona no siguió en la tarea crítica sin evaluación), y no solo que la alerta se "cerró" en el sistema? | O63: Ejemplos: revisión de una muestra de alertas cerradas comparando la acción real con la registrada (R03) | P63: No se verifica el criterio «Calidad real de la intervención verificada» y no existe evidencia de revisión del control o de sus resultados. | Q63: El criterio «Calidad real de la intervención verificada» se verifica solo de manera ocasional o informal, sin método, frecuencia, muestra ni seguimiento definidos. | R63: El criterio «Calidad real de la intervención verificada» cuenta con verificaciones periódicas pero parciales, con cobertura o profundidad insuficiente y seguimiento inconsistente de los hallazgos. | S63: El criterio «Calidad real de la intervención verificada» se verifica sistemáticamente en la mayor parte del alcance, con hallazgos registrados y acciones de seguimiento; quedan brechas menores. | T63: El criterio «Calidad real de la intervención verificada» se verifica de forma sistemática, independiente y basada en riesgo en todo el alcance, mediante reconstrucción de casos, con cierre comprobado de hallazgos y retroalimentación al sistema. | U63: Verification | V63: Muestreo o prueba | W63: Reconstrucción de casos | X63: Fatal | Y63: Crítico
B64: 63 | D64: Respuesta e intervención frente a alertas | E64: S05.2 | F64: Somnolencia | G64: Degradación de barreras | H64: Somnolencia o microsueño en persona que opera equipo o ejecuta tarea crítica | I64: Persona fatigada o somnolienta permanece en tarea crítica sin ser detectada ni intervenida | J64: Protocolo de intervención frente a alertas | K64: Convertir la detección en intervención que retire a la persona de la exposición | L64: Menor recurrencia de alertas tras intervención | M64: 7 | N64: Tras una intervención, ¿en qué medida disminuye la repetición de alertas en la misma persona o turno, y la tasa de microsueños por 1.000 h baja (X05)? | O64: Ejemplos: serie de alertas por persona y tasa por 1.000 h, al menos 6 meses | P64: El criterio «Menor recurrencia de alertas tras intervención» no muestra resultados medibles o no se evalúa su efecto sobre el riesgo y el desempeño. | Q64: El criterio «Menor recurrencia de alertas tras intervención» presenta resultados anecdóticos o aislados, sin línea base, indicadores comparables ni evidencia de mejora atribuible. | R64: El criterio «Menor recurrencia de alertas tras intervención» dispone de algunos indicadores o comparaciones, pero los resultados son parciales, inestables o insuficientes para demostrar efectividad sostenida. | S64: El criterio «Menor recurrencia de alertas tras intervención» muestra una mejora medible y mayormente sostenida en los resultados; persisten brechas menores o variaciones que requieren seguimiento. | T64: El criterio «Menor recurrencia de alertas tras intervención» demuestra efectividad sostenida con datos comparables de al menos tres períodos, tendencia favorable y ausencia o reducción comprobada de recurrencias, verificada mediante análisis de datos. | U64: Effectiveness | V64: Análisis de tendencia | W64: Análisis de datos | X64: Fatal | Y64: Crítico
B65: 64 | D65: Respuesta e intervención frente a alertas | E65: S05.2 | F65: Somnolencia | G65: Degradación de barreras | H65: Somnolencia o microsueño en persona que opera equipo o ejecuta tarea crítica | I65: Persona fatigada o somnolienta permanece en tarea crítica sin ser detectada ni intervenida | J65: Protocolo de intervención frente a alertas | K65: Convertir la detección en intervención que retire a la persona de la exposición | L65: Respuesta sostenida con alta carga de alertas | M65: 8 | N65: ¿En qué medida la respuesta se mantiene en períodos de alta carga (alertas simultáneas, cambios de turno, contingencias)? | O65: Ejemplos: tiempos de respuesta separados por carga de alertas | P65: El control asociado a «Respuesta sostenida con alta carga de alertas» deja de operar ante contingencias, dotación reducida, emergencias u otras condiciones anómalas. | Q65: El control asociado a «Respuesta sostenida con alta carga de alertas» se mantiene solo mediante respuestas improvisadas, sin criterios de excepción, autorización ni controles compensatorios definidos. | R65: El control asociado a «Respuesta sostenida con alta carga de alertas» se mantiene parcialmente en condiciones anómalas, pero presenta brechas relevantes de recursos, cobertura, autorización o verificación de controles compensatorios. | S65: El control asociado a «Respuesta sostenida con alta carga de alertas» se mantiene en la mayoría de las condiciones anómalas, con excepciones autorizadas y controles compensatorios; quedan brechas menores de consistencia. | T65: El control asociado a «Respuesta sostenida con alta carga de alertas» se mantiene plenamente efectivo en condiciones normales y anómalas, con recursos disponibles, excepciones controladas, pruebas periódicas y evidencia verificable mediante análisis de datos. | U65: Resilience | V65: Datos de sistema | W65: Análisis de datos | X65: Fatal | Y65: Crítico
B66: 65 | D66: Ventana circadiana y diferenciación fatiga/somnolencia | E66: S05.3 | F66: Somnolencia | G66: Fatiga o somnolencia | H66: Somnolencia o microsueño en persona que opera equipo o ejecuta tarea crítica | I66: Pérdida de control de equipo móvil o vehículo (colisión, volcamiento, salida de vía) | J66: Gestión de la ventana circadiana baja | K66: Reducir la probabilidad de somnolencia en horarios de máxima vulnerabilidad | L66: Menos alertas en ventana circadiana baja | M66: 9 | N66: ¿En qué medida la tasa de alertas de somnolencia en la ventana circadiana baja disminuye tras las medidas aplicadas? | O66: Ejemplos: serie de alertas por hora del día, al menos 6 meses | P66: El criterio «Menos alertas en ventana circadiana baja» no muestra resultados medibles o no se evalúa su efecto sobre el riesgo y el desempeño. | Q66: El criterio «Menos alertas en ventana circadiana baja» presenta resultados anecdóticos o aislados, sin línea base, indicadores comparables ni evidencia de mejora atribuible. | R66: El criterio «Menos alertas en ventana circadiana baja» dispone de algunos indicadores o comparaciones, pero los resultados son parciales, inestables o insuficientes para demostrar efectividad sostenida. | S66: El criterio «Menos alertas en ventana circadiana baja» muestra una mejora medible y mayormente sostenida en los resultados; persisten brechas menores o variaciones que requieren seguimiento. | T66: El criterio «Menos alertas en ventana circadiana baja» demuestra efectividad sostenida con datos comparables de al menos tres períodos, tendencia favorable y ausencia o reducción comprobada de recurrencias, verificada mediante análisis de datos. | U66: Effectiveness | V66: Análisis de tendencia | W66: Análisis de datos | X66: Fatal | Y66: Crítico
B67: 66 | D67: Ventana circadiana y diferenciación fatiga/somnolencia | E67: S05.3 | F67: Somnolencia | G67: Fatiga o somnolencia | H67: Somnolencia o microsueño en persona que opera equipo o ejecuta tarea crítica | I67: Pérdida de control de equipo móvil o vehículo (colisión, volcamiento, salida de vía) | J67: Gestión de la ventana circadiana baja | K67: Reducir la probabilidad de somnolencia en horarios de máxima vulnerabilidad | L67: Acciones diferenciadas para fatiga y somnolencia | M67: 10 | N67: ¿En qué medida se distingue en la práctica la respuesta ante somnolencia (riesgo inminente de microsueño: detención inmediata) de la respuesta ante fatiga (capacidad reducida: pausa, rotación de tarea)? | O67: Ejemplos: instrucciones con acciones diferenciadas; respuestas de supervisores entrevistados | P67: El criterio «Acciones diferenciadas para fatiga y somnolencia» no está definido ni documentado; no existen criterios operativos, responsables ni evidencia aplicable. | Q67: El criterio «Acciones diferenciadas para fatiga y somnolencia» se aborda de manera informal o mediante documentos aislados, incompletos o desactualizados, sin alcance ni responsables claros. | R67: El criterio «Acciones diferenciadas para fatiga y somnolencia» está formalmente definido, pero cubre solo parte del alcance o presenta brechas relevantes de actualización, criterios, responsables o aprobación. | S67: El criterio «Acciones diferenciadas para fatiga y somnolencia» está definido, documentado, aprobado y vigente para la mayor parte del alcance; solo quedan brechas menores de cobertura o integración. | T67: El criterio «Acciones diferenciadas para fatiga y somnolencia» está completamente formalizado, aprobado, vigente e integrado a la gestión, con alcance, parámetros, responsables y revisión periódica verificables mediante revisión documental y entrevista. | U67: Design | V67: Documental | W67: Revisión documental y entrevista | X67: Grave | Y67: Soporte
B68: 67 | D68: Pausas y contramedidas durante el turno | E68: S05.4 | F68: Ambos | G68: Fatiga o somnolencia | H68: Fatiga y/o somnolencia en persona expuesta a tarea crítica | I68: Pérdida de control de equipo móvil o vehículo (colisión, volcamiento, salida de vía) | J68: Pausas activas y siestas estratégicas en turno | K68: Recuperar el estado de alerta durante el turno | L68: Pausas y siestas en turno con criterio técnico | M68: 11 | N68: ¿En qué medida las pausas y, cuando corresponda, las siestas estratégicas en turno tienen criterios claros (duración, momento, inercia del sueño, lugar)? | O68: Ejemplos: criterios escritos o prácticas acordadas; lo que relatan supervisores y trabajadores | P68: El criterio «Pausas y siestas en turno con criterio técnico» no está definido ni documentado; no existen criterios operativos, responsables ni evidencia aplicable. | Q68: El criterio «Pausas y siestas en turno con criterio técnico» se aborda de manera informal o mediante documentos aislados, incompletos o desactualizados, sin alcance ni responsables claros. | R68: El criterio «Pausas y siestas en turno con criterio técnico» está formalmente definido, pero cubre solo parte del alcance o presenta brechas relevantes de actualización, criterios, responsables o aprobación. | S68: El criterio «Pausas y siestas en turno con criterio técnico» está definido, documentado, aprobado y vigente para la mayor parte del alcance; solo quedan brechas menores de cobertura o integración. | T68: El criterio «Pausas y siestas en turno con criterio técnico» está completamente formalizado, aprobado, vigente e integrado a la gestión, con alcance, parámetros, responsables y revisión periódica verificables mediante revisión documental y entrevista. | U68: Design | V68: Documental | W68: Revisión documental y entrevista | X68: Grave | Y68: Soporte
B69: 68 | D69: Pausas y contramedidas durante el turno | E69: S05.4 | F69: Ambos | G69: Fatiga o somnolencia | H69: Fatiga y/o somnolencia en persona expuesta a tarea crítica | I69: Pérdida de control de equipo móvil o vehículo (colisión, volcamiento, salida de vía) | J69: Pausas activas y siestas estratégicas en turno | K69: Recuperar el estado de alerta durante el turno | L69: Uso real de pausas y salas de recuperación | M69: 12 | N69: ¿En qué medida las pausas y salas de recuperación se usan según lo previsto y están disponibles cerca de las áreas de trabajo? | O69: Ejemplos: registros de uso por turno; observación; distancias | P69: El control asociado a «Uso real de pausas y salas de recuperación» no opera en la práctica o, cuando se requiere, no genera la acción esperada. | Q69: El control asociado a «Uso real de pausas y salas de recuperación» opera de forma esporádica y reactiva, depende de iniciativas individuales y carece de respuesta oportuna o registros consistentes. | R69: El control asociado a «Uso real de pausas y salas de recuperación» funciona parcialmente o de manera irregular; genera algunas acciones, pero presenta brechas relevantes de oportunidad, calidad, seguimiento o trazabilidad. | S69: El control asociado a «Uso real de pausas y salas de recuperación» funciona regularmente y genera la respuesta esperada en la mayoría de los casos; quedan desviaciones menores de oportunidad, cobertura o registro. | T69: El control asociado a «Uso real de pausas y salas de recuperación» funciona de manera confiable, oportuna y consistente en todos los casos aplicables, con acciones trazables, seguimiento y evidencia verificable mediante observación en terreno. | U69: Functioning | V69: Observación en terreno | W69: Observación en terreno | X69: Grave | Y69: Soporte
B70: 69 | C70: D.6 Salud ocupacional y trastornos del sueño | D70: Screening de trastornos del sueño | E70: S06.1 | F70: Somnolencia | G70: Fatiga o somnolencia | H70: Somnolencia o microsueño en persona que opera equipo o ejecuta tarea crítica | I70: Pérdida de control de equipo móvil o vehículo (colisión, volcamiento, salida de vía) | J70: Programa de detección de trastornos del sueño | K70: Identificar personas con trastornos que generan somnolencia (p. ej., apnea obstructiva) | L70: Detección de trastornos del sueño con instrumento validado | M70: 1 | N70: ¿En qué medida se buscan trastornos del sueño en cargos críticos con un instrumento validado y criterios de derivación? | O70: Ejemplos: programa o práctica médica con instrumento, criterios y derivación | P70: El criterio «Detección de trastornos del sueño con instrumento validado» no está definido ni documentado; no existen criterios operativos, responsables ni evidencia aplicable. | Q70: El criterio «Detección de trastornos del sueño con instrumento validado» se aborda de manera informal o mediante documentos aislados, incompletos o desactualizados, sin alcance ni responsables claros. | R70: El criterio «Detección de trastornos del sueño con instrumento validado» está formalmente definido, pero cubre solo parte del alcance o presenta brechas relevantes de actualización, criterios, responsables o aprobación. | S70: El criterio «Detección de trastornos del sueño con instrumento validado» está definido, documentado, aprobado y vigente para la mayor parte del alcance; solo quedan brechas menores de cobertura o integración. | T70: El criterio «Detección de trastornos del sueño con instrumento validado» está completamente formalizado, aprobado, vigente e integrado a la gestión, con alcance, parámetros, responsables y revisión periódica verificables mediante revisión documental. | U70: Design | V70: Documental | W70: Revisión documental | X70: Fatal | Y70: Soporte
B71: 70 | D71: Screening de trastornos del sueño | E71: S06.1 | F71: Somnolencia | G71: Fatiga o somnolencia | H71: Somnolencia o microsueño en persona que opera equipo o ejecuta tarea crítica | I71: Pérdida de control de equipo móvil o vehículo (colisión, volcamiento, salida de vía) | J71: Programa de detección de trastornos del sueño | K71: Identificar personas con trastornos que generan somnolencia (p. ej., apnea obstructiva) | L71: Cobertura de la detección en cargos críticos | M71: 2 | N71: ¿En qué medida los trabajadores de cargos críticos tienen esa evaluación vigente (L06)? | O71: Ejemplos: registros médicos agregados, respetando la confidencialidad | P71: El criterio «Cobertura de la detección en cargos críticos» no se aplica en la práctica y no existe evidencia de implementación. | Q71: El criterio «Cobertura de la detección en cargos críticos» se aplica solo en casos aislados o de manera informal, sin cobertura planificada ni consistencia entre áreas, turnos o personas expuestas. | R71: El criterio «Cobertura de la detección en cargos críticos» está implementado parcialmente; alcanza parte de la población o del proceso, con brechas relevantes de cobertura, frecuencia o registro. | S71: El criterio «Cobertura de la detección en cargos críticos» está implementado de forma regular en la mayor parte del alcance y con evidencia suficiente; persisten brechas menores de cobertura o consistencia. | T71: El criterio «Cobertura de la detección en cargos críticos» está implementado sistemáticamente en todo el alcance aplicable, incluidos turnos y contratistas cuando corresponde, con registros completos y verificación mediante análisis de datos. | U71: Implementation | V71: Registro | W71: Análisis de datos | X71: Fatal | Y71: Soporte
B72: 71 | D72: Tratamiento, seguimiento y aptitud | E72: S06.2 | F72: Somnolencia | G72: Fatiga o somnolencia | H72: Somnolencia o microsueño en persona que opera equipo o ejecuta tarea crítica | I72: Pérdida de control de equipo móvil o vehículo (colisión, volcamiento, salida de vía) | J72: Seguimiento y aptitud de casos positivos | K72: Asegurar tratamiento y aptitud antes de volver a tarea crítica | L72: Casos positivos tratados y con aptitud determinada | M72: 3 | N72: ¿En qué medida los casos positivos se derivan, confirman y tratan, se determina su aptitud para tareas críticas y se sigue la adherencia al tratamiento (L07)? | O72: Ejemplos: registros agregados de derivación, aptitud y adherencia | P72: El control asociado a «Casos positivos tratados y con aptitud determinada» no opera en la práctica o, cuando se requiere, no genera la acción esperada. | Q72: El control asociado a «Casos positivos tratados y con aptitud determinada» opera de forma esporádica y reactiva, depende de iniciativas individuales y carece de respuesta oportuna o registros consistentes. | R72: El control asociado a «Casos positivos tratados y con aptitud determinada» funciona parcialmente o de manera irregular; genera algunas acciones, pero presenta brechas relevantes de oportunidad, calidad, seguimiento o trazabilidad. | S72: El control asociado a «Casos positivos tratados y con aptitud determinada» funciona regularmente y genera la respuesta esperada en la mayoría de los casos; quedan desviaciones menores de oportunidad, cobertura o registro. | T72: El control asociado a «Casos positivos tratados y con aptitud determinada» funciona de manera confiable, oportuna y consistente en todos los casos aplicables, con acciones trazables, seguimiento y evidencia verificable mediante análisis de datos. | U72: Functioning | V72: Registro | W72: Análisis de datos | X72: Fatal | Y72: Soporte
B73: 72 | D73: Tratamiento, seguimiento y aptitud | E73: S06.2 | F73: Somnolencia | G73: Fatiga o somnolencia | H73: Somnolencia o microsueño en persona que opera equipo o ejecuta tarea crítica | I73: Pérdida de control de equipo móvil o vehículo (colisión, volcamiento, salida de vía) | J73: Seguimiento y aptitud de casos positivos | K73: Asegurar tratamiento y aptitud antes de volver a tarea crítica | L73: Efecto del tratamiento en las alertas | M73: 4 | N73: ¿En qué medida se observa una reducción de alertas de somnolencia en personas tratadas respecto de su situación anterior, en análisis agregado y anónimo? | O73: Ejemplos: análisis anónimo antes y después del tratamiento | P73: El criterio «Efecto del tratamiento en las alertas» no muestra resultados medibles o no se evalúa su efecto sobre el riesgo y el desempeño. | Q73: El criterio «Efecto del tratamiento en las alertas» presenta resultados anecdóticos o aislados, sin línea base, indicadores comparables ni evidencia de mejora atribuible. | R73: El criterio «Efecto del tratamiento en las alertas» dispone de algunos indicadores o comparaciones, pero los resultados son parciales, inestables o insuficientes para demostrar efectividad sostenida. | S73: El criterio «Efecto del tratamiento en las alertas» muestra una mejora medible y mayormente sostenida en los resultados; persisten brechas menores o variaciones que requieren seguimiento. | T73: El criterio «Efecto del tratamiento en las alertas» demuestra efectividad sostenida con datos comparables de al menos tres períodos, tendencia favorable y ausencia o reducción comprobada de recurrencias, verificada mediante análisis de datos. | U73: Effectiveness | V73: Análisis de tendencia | W73: Análisis de datos | X73: Grave | Y73: Soporte
B74: 73 | D74: Medicamentos y condiciones de salud | E74: S06.3 | F74: Somnolencia | G74: Fatiga o somnolencia | H74: Somnolencia o microsueño en persona que opera equipo o ejecuta tarea crítica | I74: Error u omisión en tarea crítica (aislamiento, izaje, operación de planta) por desempeño degradado | J74: Gestión de medicamentos sedantes y condiciones de salud | K74: Evitar somnolencia inducida por fármacos o enfermedad | L74: Declaración confidencial de medicamentos | M74: 5 | N74: ¿En qué medida las personas pueden declarar en forma confidencial medicamentos o condiciones que afecten la vigilia, y se evalúa su aptitud para tareas críticas? | O74: Ejemplos: procedimiento médico o práctica del policlínico; registros agregados | P74: El criterio «Declaración confidencial de medicamentos» no está definido ni documentado; no existen criterios operativos, responsables ni evidencia aplicable. | Q74: El criterio «Declaración confidencial de medicamentos» se aborda de manera informal o mediante documentos aislados, incompletos o desactualizados, sin alcance ni responsables claros. | R74: El criterio «Declaración confidencial de medicamentos» está formalmente definido, pero cubre solo parte del alcance o presenta brechas relevantes de actualización, criterios, responsables o aprobación. | S74: El criterio «Declaración confidencial de medicamentos» está definido, documentado, aprobado y vigente para la mayor parte del alcance; solo quedan brechas menores de cobertura o integración. | T74: El criterio «Declaración confidencial de medicamentos» está completamente formalizado, aprobado, vigente e integrado a la gestión, con alcance, parámetros, responsables y revisión periódica verificables mediante revisión documental y entrevista. | U74: Design | V74: Documental | W74: Revisión documental y entrevista | X74: Grave | Y74: Soporte
B75: 74 | D75: Medicamentos y condiciones de salud | E75: S06.3 | F75: Somnolencia | G75: Fatiga o somnolencia | H75: Somnolencia o microsueño en persona que opera equipo o ejecuta tarea crítica | I75: Error u omisión en tarea crítica (aislamiento, izaje, operación de planta) por desempeño degradado | J75: Gestión de medicamentos sedantes y condiciones de salud | K75: Evitar somnolencia inducida por fármacos o enfermedad | L75: Declaración conocida y usada | M75: 6 | N75: ¿En qué medida los trabajadores conocen esa posibilidad y existen declaraciones registradas? | O75: Ejemplos: registros agregados; entrevistas | P75: El criterio «Declaración conocida y usada» no se aplica en la práctica y no existe evidencia de implementación. | Q75: El criterio «Declaración conocida y usada» se aplica solo en casos aislados o de manera informal, sin cobertura planificada ni consistencia entre áreas, turnos o personas expuestas. | R75: El criterio «Declaración conocida y usada» está implementado parcialmente; alcanza parte de la población o del proceso, con brechas relevantes de cobertura, frecuencia o registro. | S75: El criterio «Declaración conocida y usada» está implementado de forma regular en la mayor parte del alcance y con evidencia suficiente; persisten brechas menores de cobertura o consistencia. | T75: El criterio «Declaración conocida y usada» está implementado sistemáticamente en todo el alcance aplicable, incluidos turnos y contratistas cuando corresponde, con registros completos y verificación mediante entrevista estructurada. | U75: Implementation | V75: Entrevista | W75: Entrevista estructurada | X75: Grave | Y75: Soporte
B76: 75 | C76: D.7 Controles críticos | D76: Identificación y definición de controles críticos | E76: S07.1 | F76: Ambos | G76: Degradación de barreras | H76: Fatiga y/o somnolencia en persona expuesta a tarea crítica | I76: Pérdida de control de equipo móvil o vehículo (colisión, volcamiento, salida de vía) | J76: Definición de controles críticos de fatiga | K76: Establecer qué controles son críticos, su estándar de desempeño y su dueño | L76: Controles críticos definidos con estándar y responsable | M76: 1 | N76: ¿En qué medida está claro cuáles son los controles críticos de fatiga y somnolencia y, para cada uno, su objetivo, el desempeño esperado, cómo saber si funciona, su responsable y qué hacer si falla (hoja 05)? | O76: Ejemplos: fichas de controles o equivalentes; si no existen, lo que responden los responsables | P76: El criterio «Controles críticos definidos con estándar y responsable» no está definido ni documentado; no existen criterios operativos, responsables ni evidencia aplicable. | Q76: El criterio «Controles críticos definidos con estándar y responsable» se aborda de manera informal o mediante documentos aislados, incompletos o desactualizados, sin alcance ni responsables claros. | R76: El criterio «Controles críticos definidos con estándar y responsable» está formalmente definido, pero cubre solo parte del alcance o presenta brechas relevantes de actualización, criterios, responsables o aprobación. | S76: El criterio «Controles críticos definidos con estándar y responsable» está definido, documentado, aprobado y vigente para la mayor parte del alcance; solo quedan brechas menores de cobertura o integración. | T76: El criterio «Controles críticos definidos con estándar y responsable» está completamente formalizado, aprobado, vigente e integrado a la gestión, con alcance, parámetros, responsables y revisión periódica verificables mediante revisión documental y entrevista. | U76: Design | V76: Documental | W76: Revisión documental y entrevista | X76: Fatal | Y76: Crítico
B77: 76 | D77: Identificación y definición de controles críticos | E77: S07.1 | F77: Ambos | G77: Degradación de barreras | H77: Fatiga y/o somnolencia en persona expuesta a tarea crítica | I77: Pérdida de control de equipo móvil o vehículo (colisión, volcamiento, salida de vía) | J77: Definición de controles críticos de fatiga | K77: Establecer qué controles son críticos, su estándar de desempeño y su dueño | L77: Responsables de controles críticos activos | M77: 2 | N77: ¿En qué medida los responsables de los controles críticos conocen su rol y ejecutan lo que les corresponde (revisar verificaciones, decidir ante desviaciones)? | O77: Ejemplos: entrevistas a responsables; registros de revisión | P77: El criterio «Responsables de controles críticos activos» no se aplica en la práctica y no existe evidencia de implementación. | Q77: El criterio «Responsables de controles críticos activos» se aplica solo en casos aislados o de manera informal, sin cobertura planificada ni consistencia entre áreas, turnos o personas expuestas. | R77: El criterio «Responsables de controles críticos activos» está implementado parcialmente; alcanza parte de la población o del proceso, con brechas relevantes de cobertura, frecuencia o registro. | S77: El criterio «Responsables de controles críticos activos» está implementado de forma regular en la mayor parte del alcance y con evidencia suficiente; persisten brechas menores de cobertura o consistencia. | T77: El criterio «Responsables de controles críticos activos» está implementado sistemáticamente en todo el alcance aplicable, incluidos turnos y contratistas cuando corresponde, con registros completos y verificación mediante entrevista estructurada. | U77: Implementation | V77: Entrevista | W77: Entrevista estructurada | X77: Fatal | Y77: Crítico
B78: 77 | D78: Verificación de controles críticos | E78: S07.2 | F78: Ambos | G78: Degradación de barreras | H78: Fatiga y/o somnolencia en persona expuesta a tarea crítica | I78: Pérdida de control de equipo móvil o vehículo (colisión, volcamiento, salida de vía) | J78: Programa de verificación (assurance) de CC | K78: Confirmar con evidencia que los CC funcionan como fueron diseñados | L78: Verificaciones de controles ejecutadas y en terreno | M78: 3 | N78: ¿En qué medida los controles críticos se verifican con la frecuencia prevista (L04) e incluyen verificación en terreno, no solo documental? | O78: Ejemplos: programa de verificación comparado con lo ejecutado; muestra de verificaciones | P78: No se verifica el criterio «Verificaciones de controles ejecutadas y en terreno» y no existe evidencia de revisión del control o de sus resultados. | Q78: El criterio «Verificaciones de controles ejecutadas y en terreno» se verifica solo de manera ocasional o informal, sin método, frecuencia, muestra ni seguimiento definidos. | R78: El criterio «Verificaciones de controles ejecutadas y en terreno» cuenta con verificaciones periódicas pero parciales, con cobertura o profundidad insuficiente y seguimiento inconsistente de los hallazgos. | S78: El criterio «Verificaciones de controles ejecutadas y en terreno» se verifica sistemáticamente en la mayor parte del alcance, con hallazgos registrados y acciones de seguimiento; quedan brechas menores. | T78: El criterio «Verificaciones de controles ejecutadas y en terreno» se verifica de forma sistemática, independiente y basada en riesgo en todo el alcance, mediante muestreo de registros, con cierre comprobado de hallazgos y retroalimentación al sistema. | U78: Verification | V78: Registro | W78: Muestreo de registros | X78: Fatal | Y78: Crítico
B79: 78 | D79: Verificación de controles críticos | E79: S07.2 | F79: Ambos | G79: Degradación de barreras | H79: Fatiga y/o somnolencia en persona expuesta a tarea crítica | I79: Pérdida de control de equipo móvil o vehículo (colisión, volcamiento, salida de vía) | J79: Programa de verificación (assurance) de CC | K79: Confirmar con evidencia que los CC funcionan como fueron diseñados | L79: Verificaciones que miran el desempeño | M79: 4 | N79: ¿En qué medida las verificaciones preguntan si el control funcionó y generan hallazgos cuando corresponde (tasa de verificaciones con hallazgo mayor que cero)? | O79: Ejemplos: muestra de formularios de verificación; tasa de hallazgos | P79: No se verifica el criterio «Verificaciones que miran el desempeño» y no existe evidencia de revisión del control o de sus resultados. | Q79: El criterio «Verificaciones que miran el desempeño» se verifica solo de manera ocasional o informal, sin método, frecuencia, muestra ni seguimiento definidos. | R79: El criterio «Verificaciones que miran el desempeño» cuenta con verificaciones periódicas pero parciales, con cobertura o profundidad insuficiente y seguimiento inconsistente de los hallazgos. | S79: El criterio «Verificaciones que miran el desempeño» se verifica sistemáticamente en la mayor parte del alcance, con hallazgos registrados y acciones de seguimiento; quedan brechas menores. | T79: El criterio «Verificaciones que miran el desempeño» se verifica de forma sistemática, independiente y basada en riesgo en todo el alcance, mediante muestreo de registros, con cierre comprobado de hallazgos y retroalimentación al sistema. | U79: Verification | V79: Registro | W79: Muestreo de registros | X79: Fatal | Y79: Crítico
B80: 79 | D80: Verificación de controles críticos | E80: S07.2 | F80: Ambos | G80: Degradación de barreras | H80: Fatiga y/o somnolencia en persona expuesta a tarea crítica | I80: Pérdida de control de equipo móvil o vehículo (colisión, volcamiento, salida de vía) | J80: Programa de verificación (assurance) de CC | K80: Confirmar con evidencia que los CC funcionan como fueron diseñados | L80: Desempeño de controles analizado en el tiempo | M80: 5 | N80: ¿En qué medida el desempeño de los controles críticos se analiza como tendencia y se relaciona con alertas e incidentes? | O80: Ejemplos: tendencia de cumplimiento de controles, al menos 6 meses, y análisis de relación | P80: El criterio «Desempeño de controles analizado en el tiempo» no muestra resultados medibles o no se evalúa su efecto sobre el riesgo y el desempeño. | Q80: El criterio «Desempeño de controles analizado en el tiempo» presenta resultados anecdóticos o aislados, sin línea base, indicadores comparables ni evidencia de mejora atribuible. | R80: El criterio «Desempeño de controles analizado en el tiempo» dispone de algunos indicadores o comparaciones, pero los resultados son parciales, inestables o insuficientes para demostrar efectividad sostenida. | S80: El criterio «Desempeño de controles analizado en el tiempo» muestra una mejora medible y mayormente sostenida en los resultados; persisten brechas menores o variaciones que requieren seguimiento. | T80: El criterio «Desempeño de controles analizado en el tiempo» demuestra efectividad sostenida con datos comparables de al menos tres períodos, tendencia favorable y ausencia o reducción comprobada de recurrencias, verificada mediante análisis de datos. | U80: Effectiveness | V80: Análisis de tendencia | W80: Análisis de datos | X80: Fatal | Y80: Crítico
B81: 80 | D81: Desviaciones y pérdida de control | E81: S07.3 | F81: Ambos | G81: Pérdida del control | H81: Fatiga y/o somnolencia en persona expuesta a tarea crítica | I81: Pérdida de control de equipo móvil o vehículo (colisión, volcamiento, salida de vía) | J81: Respuesta a desviaciones de CC | K81: Restablecer el control antes de que se materialice el evento | L81: Respuesta inmediata ante desviaciones de controles | M81: 6 | N81: Ante una desviación de un control crítico, ¿en qué medida se aplicó la acción inmediata que correspondía (detención, control compensatorio) en un tiempo razonable? | O81: Ejemplos: muestra de desviaciones con su acción inmediata y tiempos | P81: El control asociado a «Respuesta inmediata ante desviaciones de controles» no opera en la práctica o, cuando se requiere, no genera la acción esperada. | Q81: El control asociado a «Respuesta inmediata ante desviaciones de controles» opera de forma esporádica y reactiva, depende de iniciativas individuales y carece de respuesta oportuna o registros consistentes. | R81: El control asociado a «Respuesta inmediata ante desviaciones de controles» funciona parcialmente o de manera irregular; genera algunas acciones, pero presenta brechas relevantes de oportunidad, calidad, seguimiento o trazabilidad. | S81: El control asociado a «Respuesta inmediata ante desviaciones de controles» funciona regularmente y genera la respuesta esperada en la mayoría de los casos; quedan desviaciones menores de oportunidad, cobertura o registro. | T81: El control asociado a «Respuesta inmediata ante desviaciones de controles» funciona de manera confiable, oportuna y consistente en todos los casos aplicables, con acciones trazables, seguimiento y evidencia verificable mediante reconstrucción de casos. | U81: Functioning | V81: Registro | W81: Reconstrucción de casos | X81: Fatal | Y81: Crítico
B82: 81 | D82: Desviaciones y pérdida de control | E82: S07.3 | F82: Ambos | G82: Pérdida del control | H82: Fatiga y/o somnolencia en persona expuesta a tarea crítica | I82: Pérdida de control de equipo móvil o vehículo (colisión, volcamiento, salida de vía) | J82: Respuesta a desviaciones de CC | K82: Restablecer el control antes de que se materialice el evento | L82: Desviaciones de controles sin repetición | M82: 7 | N82: ¿En qué medida las desviaciones de controles críticos cerradas no se repiten en el mismo control y área en los 6 meses siguientes (R04)? | O82: Ejemplos: análisis de repetición por control y área | P82: El criterio «Desviaciones de controles sin repetición» no muestra resultados medibles o no se evalúa su efecto sobre el riesgo y el desempeño. | Q82: El criterio «Desviaciones de controles sin repetición» presenta resultados anecdóticos o aislados, sin línea base, indicadores comparables ni evidencia de mejora atribuible. | R82: El criterio «Desviaciones de controles sin repetición» dispone de algunos indicadores o comparaciones, pero los resultados son parciales, inestables o insuficientes para demostrar efectividad sostenida. | S82: El criterio «Desviaciones de controles sin repetición» muestra una mejora medible y mayormente sostenida en los resultados; persisten brechas menores o variaciones que requieren seguimiento. | T82: El criterio «Desviaciones de controles sin repetición» demuestra efectividad sostenida con datos comparables de al menos tres períodos, tendencia favorable y ausencia o reducción comprobada de recurrencias, verificada mediante análisis de datos. | U82: Effectiveness | V82: Análisis de tendencia | W82: Análisis de datos | X82: Fatal | Y82: Crítico
B83: 82 | D83: Desviaciones y pérdida de control | E83: S07.3 | F83: Ambos | G83: Pérdida del control | H83: Fatiga y/o somnolencia en persona expuesta a tarea crítica | I83: Pérdida de control de equipo móvil o vehículo (colisión, volcamiento, salida de vía) | J83: Respuesta a desviaciones de CC | K83: Restablecer el control antes de que se materialice el evento | L83: Controles compensatorios ante falla de un control | M83: 8 | N83: Cuando un control crítico no está disponible (falla de la tecnología, sin relevo), ¿en qué medida se aplican controles compensatorios previstos antes de continuar la operación? | O83: Ejemplos: fallas de controles con el control compensatorio aplicado | P83: El control asociado a «Controles compensatorios ante falla de un control» deja de operar ante contingencias, dotación reducida, emergencias u otras condiciones anómalas. | Q83: El control asociado a «Controles compensatorios ante falla de un control» se mantiene solo mediante respuestas improvisadas, sin criterios de excepción, autorización ni controles compensatorios definidos. | R83: El control asociado a «Controles compensatorios ante falla de un control» se mantiene parcialmente en condiciones anómalas, pero presenta brechas relevantes de recursos, cobertura, autorización o verificación de controles compensatorios. | S83: El control asociado a «Controles compensatorios ante falla de un control» se mantiene en la mayoría de las condiciones anómalas, con excepciones autorizadas y controles compensatorios; quedan brechas menores de consistencia. | T83: El control asociado a «Controles compensatorios ante falla de un control» se mantiene plenamente efectivo en condiciones normales y anómalas, con recursos disponibles, excepciones controladas, pruebas periódicas y evidencia verificable mediante reconstrucción de casos. | U83: Resilience | V83: Registro | W83: Reconstrucción de casos | X83: Fatal | Y83: Crítico
B84: 83 | C84: D.8 Tecnología y sistemas de monitoreo | D84: Disponibilidad e integridad de la tecnología | E84: S08.1 | F84: Somnolencia | G84: Deterioro del desempeño humano | H84: Somnolencia o microsueño en persona que opera equipo o ejecuta tarea crítica | I84: Pérdida de control de equipo móvil o vehículo (colisión, volcamiento, salida de vía) | J84: Disponibilidad de la tecnología de monitoreo | K84: Mantener operativa la detección | L84: Disponibilidad técnica de la tecnología | M84: 1 | N84: ¿En qué medida los sistemas de monitoreo de los equipos en alcance están disponibles (L08) y sus fallas se reparan en un plazo razonable? | O84: Ejemplos: reportes de disponibilidad y órdenes de trabajo | P84: El criterio «Disponibilidad técnica de la tecnología» no se aplica en la práctica y no existe evidencia de implementación. | Q84: El criterio «Disponibilidad técnica de la tecnología» se aplica solo en casos aislados o de manera informal, sin cobertura planificada ni consistencia entre áreas, turnos o personas expuestas. | R84: El criterio «Disponibilidad técnica de la tecnología» está implementado parcialmente; alcanza parte de la población o del proceso, con brechas relevantes de cobertura, frecuencia o registro. | S84: El criterio «Disponibilidad técnica de la tecnología» está implementado de forma regular en la mayor parte del alcance y con evidencia suficiente; persisten brechas menores de cobertura o consistencia. | T84: El criterio «Disponibilidad técnica de la tecnología» está implementado sistemáticamente en todo el alcance aplicable, incluidos turnos y contratistas cuando corresponde, con registros completos y verificación mediante análisis de datos. | U84: Implementation | V84: Datos de sistema | W84: Análisis de datos | X84: Fatal | Y84: Soporte
B85: 84 | D85: Disponibilidad e integridad de la tecnología | E85: S08.1 | F85: Somnolencia | G85: Deterioro del desempeño humano | H85: Somnolencia o microsueño en persona que opera equipo o ejecuta tarea crítica | I85: Pérdida de control de equipo móvil o vehículo (colisión, volcamiento, salida de vía) | J85: Disponibilidad de la tecnología de monitoreo | K85: Mantener operativa la detección | L85: Pruebas funcionales de la cadena completa | M85: 2 | N85: ¿En qué medida se prueba periódicamente la cadena completa (sensor, alerta en cabina, alerta en el centro de monitoreo, registro)? | O85: Ejemplos: registros de pruebas funcionales | P85: No se verifica el criterio «Pruebas funcionales de la cadena completa» y no existe evidencia de revisión del control o de sus resultados. | Q85: El criterio «Pruebas funcionales de la cadena completa» se verifica solo de manera ocasional o informal, sin método, frecuencia, muestra ni seguimiento definidos. | R85: El criterio «Pruebas funcionales de la cadena completa» cuenta con verificaciones periódicas pero parciales, con cobertura o profundidad insuficiente y seguimiento inconsistente de los hallazgos. | S85: El criterio «Pruebas funcionales de la cadena completa» se verifica sistemáticamente en la mayor parte del alcance, con hallazgos registrados y acciones de seguimiento; quedan brechas menores. | T85: El criterio «Pruebas funcionales de la cadena completa» se verifica de forma sistemática, independiente y basada en riesgo en todo el alcance, mediante prueba del control, con cierre comprobado de hallazgos y retroalimentación al sistema. | U85: Verification | V85: Muestreo o prueba | W85: Prueba del control | X85: Fatal | Y85: Soporte
B86: 85 | D86: Disponibilidad e integridad de la tecnología | E86: S08.1 | F86: Somnolencia | G86: Deterioro del desempeño humano | H86: Somnolencia o microsueño en persona que opera equipo o ejecuta tarea crítica | I86: Pérdida de control de equipo móvil o vehículo (colisión, volcamiento, salida de vía) | J86: Disponibilidad de la tecnología de monitoreo | K86: Mantener operativa la detección | L86: Detección de manipulación o desconexión | M86: 3 | N86: ¿En qué medida se detecta y gestiona la desconexión, manipulación u obstrucción del dispositivo? | O86: Ejemplos: reportes de desconexión o manipulación y su gestión | P86: El control asociado a «Detección de manipulación o desconexión» deja de operar ante contingencias, dotación reducida, emergencias u otras condiciones anómalas. | Q86: El control asociado a «Detección de manipulación o desconexión» se mantiene solo mediante respuestas improvisadas, sin criterios de excepción, autorización ni controles compensatorios definidos. | R86: El control asociado a «Detección de manipulación o desconexión» se mantiene parcialmente en condiciones anómalas, pero presenta brechas relevantes de recursos, cobertura, autorización o verificación de controles compensatorios. | S86: El control asociado a «Detección de manipulación o desconexión» se mantiene en la mayoría de las condiciones anómalas, con excepciones autorizadas y controles compensatorios; quedan brechas menores de consistencia. | T86: El control asociado a «Detección de manipulación o desconexión» se mantiene plenamente efectivo en condiciones normales y anómalas, con recursos disponibles, excepciones controladas, pruebas periódicas y evidencia verificable mediante análisis de datos. | U86: Resilience | V86: Datos de sistema | W86: Análisis de datos | X86: Fatal | Y86: Soporte
B87: 86 | D87: Calidad de datos y analítica | E87: S08.2 | F87: Ambos | G87: Exposición | H87: Fatiga y/o somnolencia en persona expuesta a tarea crítica | I87: Persona fatigada o somnolienta permanece en tarea crítica sin ser detectada ni intervenida | J87: Analítica de datos de fatiga | K87: Transformar datos en predicción y decisiones | L87: Datos de fatiga reunidos para análisis | M87: 4 | N87: ¿En qué medida los datos de roster, asistencia, evaluación antes del turno, alertas y eventos pueden reunirse para analizarlos por turno, área y faena (y por persona en forma anónima)? | O87: Ejemplos: base de datos o planillas que permitan cruzar la información; ejemplo de reporte | P87: El criterio «Datos de fatiga reunidos para análisis» no está definido ni documentado; no existen criterios operativos, responsables ni evidencia aplicable. | Q87: El criterio «Datos de fatiga reunidos para análisis» se aborda de manera informal o mediante documentos aislados, incompletos o desactualizados, sin alcance ni responsables claros. | R87: El criterio «Datos de fatiga reunidos para análisis» está formalmente definido, pero cubre solo parte del alcance o presenta brechas relevantes de actualización, criterios, responsables o aprobación. | S87: El criterio «Datos de fatiga reunidos para análisis» está definido, documentado, aprobado y vigente para la mayor parte del alcance; solo quedan brechas menores de cobertura o integración. | T87: El criterio «Datos de fatiga reunidos para análisis» está completamente formalizado, aprobado, vigente e integrado a la gestión, con alcance, parámetros, responsables y revisión periódica verificables mediante revisión documental y prueba. | U87: Design | V87: Datos de sistema | W87: Revisión documental y prueba | X87: Grave | Y87: Soporte
B88: 87 | D88: Calidad de datos y analítica | E88: S08.2 | F88: Ambos | G88: Exposición | H88: Fatiga y/o somnolencia en persona expuesta a tarea crítica | I88: Persona fatigada o somnolienta permanece en tarea crítica sin ser detectada ni intervenida | J88: Analítica de datos de fatiga | K88: Transformar datos en predicción y decisiones | L88: Análisis de datos que generan acciones preventivas | M88: 5 | N88: ¿En qué medida el análisis de datos anticipa situaciones de riesgo (personas o turnos con alertas en aumento) y lleva a acciones preventivas documentadas? | O88: Ejemplos: reportes de análisis y acciones derivadas | P88: El criterio «Análisis de datos que generan acciones preventivas» no muestra resultados medibles o no se evalúa su efecto sobre el riesgo y el desempeño. | Q88: El criterio «Análisis de datos que generan acciones preventivas» presenta resultados anecdóticos o aislados, sin línea base, indicadores comparables ni evidencia de mejora atribuible. | R88: El criterio «Análisis de datos que generan acciones preventivas» dispone de algunos indicadores o comparaciones, pero los resultados son parciales, inestables o insuficientes para demostrar efectividad sostenida. | S88: El criterio «Análisis de datos que generan acciones preventivas» muestra una mejora medible y mayormente sostenida en los resultados; persisten brechas menores o variaciones que requieren seguimiento. | T88: El criterio «Análisis de datos que generan acciones preventivas» demuestra efectividad sostenida con datos comparables de al menos tres períodos, tendencia favorable y ausencia o reducción comprobada de recurrencias, verificada mediante análisis de datos. | U88: Effectiveness | V88: Análisis de tendencia | W88: Análisis de datos | X88: Grave | Y88: Soporte
